Workbook

Sheet Report
J2: No of Days | L2: 42
J3: Shoppers Engaged per Promoter per Day | L3: =10*L2 -> 420
J4: Shoppers Converted per Promoter per Day | L4: =L3*70% -> 294
J6: Target Combos Per day | L6: 25
J7: DB Selling Price per Case | L7: 1888
J8: Agency Selling Price per Case | L8: 2000
J9: Margin | L9: 112
A10: Date: 11-08-2026
F12: Agency Team | I12: Reconciliation
B13: 11857 | C13: Area | D13: Supervisor | E13: No of DB's | F13: No of Supervisors | G13: No of BA's | H13: Daily Expected Target | I13: Hollandia Evap Milk 120g(Picked by Combos) | J13: Hollandia Evap Milk 120g(Sold by Combos) | K13: TOTAL | L13: DB Amount to be Reconciled | M13: Agency Amount to be Reconciled | N13: DB Picked from | O13: Market/Neighbourhood Visited
B14: 0.23608338 | C14: Enugu | F14: 1 | G14: 10 | H14: =G$16*L$8*L$6 -> 500000
B15: 0.12878964 | C15: Abakaliki | F15: 1 | G15: 10 | H15: =G$16*L$8*L$6 -> 500000
B16: 0.2527044 | C16: Onitsha | F16: 1 | G16: 10 | H16: =G$16*L$8*L$6 -> 500000 | AE16: Hollandia Evap Milk 120g
B17: 0.10980083 | C17: Asaba | F17: 1 | G17: 10 | H17: =G$16*L$8*L$6 -> 500000
B18: 0.27262176 | C18: Owerri | F18: 1 | G18: 10 | H18: =G$16*L$8*L$6 -> 500000
B19: #N/A | C19: EAST 1 | E19: =SUM(E14:E18) -> 0 | F19: =SUM(F14:F18) -> 5 | G19: =SUM(G14:G18) -> 50 | H19: =SUM(H14:H18) -> 2500000 | J19: =SUM(J14:J18) -> 0 | K19: =SUM(K14:K18) -> 0
B20: 0.23548802 | C20: Aba | F20: 1 | G20: 10 | H20: =G$16*L$8*L$6 -> 500000
B21: 0.20875543 | C21: Phc 1 | F21: 1 | G21: 10 | H21: =G$16*L$8*L$6 -> 500000
B22: 0.19516803 | C22: Phc 2 | F22: 1 | G22: 10 | H22: =G$16*L$8*L$6 -> 500000
B23: 0.065645602 | C23: Bayelsa | F23: 1 | G23: 10 | H23: =G$16*L$8*L$6 -> 500000
B24: 0.10729217 | C24: Uyo | F24: 1 | G24: 10 | H24: =G$16*L$8*L$6 -> 500000
B25: 0.18765075 | C25: Calabar | D25: Akpan Enoidem | F25: 1 | G25: 10 | H25: =G$16*L$8*L$6 -> 500000 | I25: 41 | J25: 41 | K25: =J$25*2000 -> 82000 | L25: =J$25*1888 -> 77408 | M25: =J$25*112 -> 4592 | N25: POLYTEX | O25: ETTA AGBOR & EDIM OTOP
B26: #N/A | C26: EAST 2 | E26: =SUM(E20:E25) -> 0 | F26: =SUM(F20:F25) -> 6 | G26: =SUM(G20:G25) -> 60 | H26: =SUM(H20:H25) -> 3000000 | I26: 41 | J26: =SUM(J20:J25) -> 41 | K26: =SUM(K20:K25) -> 82000 | L26: =SUM(L25) -> 77408 | M26: =SUM(M25) -> 4592
C27: Ado-Ekiti | D27: Akingbolu Isiaka Opeyemi | G27: 10 | H27: =G$16*L$8*L$6 -> 500000 | I27: 60 | J27: 60 | K27: =J27*2000 -> 120000 | L27: =J27*1888 -> 113280 | M27: =J27*112 -> 6720 | N27: GADAMS ROYAL PULS | O27: POST OFFICE, ATIKANKAN
G28: 10 | H28: =G$16*L$8*L$6 -> 500000
G29: 10 | H29: =G$16*L$8*L$6 -> 500000
B30: #N/A | C30: WEST 1 | E30: =SUM(E21:E26) -> 0 | F30: =SUM(F21:F26) -> 11 | G30: =SUM(G27:G29) -> 30 | H30: =SUM(H27:H29) -> 1500000 | I30: =SUM(I27:I29) -> 60 | J30: =SUM(J27:J29) -> 60 | K30: =SUM(K27:K29) -> 120000 | L30: =SUM(L27:L29) -> 113280 | M30: =SUM(M27:M29) -> 6720
C31: TOTAL 3DIM | E31: =E19+E26 -> 0 | F31: =F19+F26 -> 11 | G31: =G19+G26+G30 -> 140 | H31: =H19+H26+H30 -> 7000000 | I31: =SUM(I26+I19+I30) -> 101 | J31: =SUM(J26+J19+J30) -> 101 | K31: =SUM(K26+K19+K30) -> 202000 | L31: =SUM(L26+L19+L30) -> 190688 | M31: =SUM(M26+M19+M30) -> 11312
A33: Date: 12-08-2026
F35: Agency Team | I35: Reconciliation
B36: 11857 | C36: Area | D36: Supervisor | E36: No of DB's | F36: No of Supervisors | G36: No of BA's | H36: Daily Expected Target | I36: Hollandia Evap Milk 120g(Picked by Combos) | J36: Hollandia Evap Milk 120g(Sold by Combos) | K36: TOTAL | L36: DB Amount to be Reconciled | M36: Agency Amount to be Reconciled | N36: DB Picked from | O36: Market/Neighbourhood Visited
B37: 0.23608338 | C37: Enugu | F37: 1 | G37: 10 | H37: =G$16*L$8*L$6 -> 500000
B38: 0.12878964 | C38: Abakaliki | F38: 1 | G38: 10 | H38: =G$16*L$8*L$6 -> 500000
B39: 0.2527044 | C39: Onitsha | F39: 1 | G39: 10 | H39: =G$16*L$8*L$6 -> 500000
B40: 0.10980083 | C40: Asaba | F40: 1 | G40: 10 | H40: =G$16*L$8*L$6 -> 500000
B41: 0.27262176 | C41: Owerri | F41: 1 | G41: 10 | H41: =G$16*L$8*L$6 -> 500000
B42: #N/A | C42: EAST 1 | E42: =SUM(E37:E41) -> 0 | F42: =SUM(F37:F41) -> 5 | G42: =SUM(G37:G41) -> 50 | H42: =SUM(H37:H41) -> 2500000 | J42: =SUM(J37:J41) -> 0 | K42: =SUM(K37:K41) -> 0
B43: 0.23548802 | C43: Aba | F43: 1 | G43: 10 | H43: =G$16*L$8*L$6 -> 500000
B44: 0.20875543 | C44: Phc 1 | F44: 1 | G44: 10 | H44: =G$16*L$8*L$6 -> 500000
B45: 0.19516803 | C45: Phc 2 | F45: 1 | G45: 10 | H45: =G$16*L$8*L$6 -> 500000
B46: 0.065645602 | C46: Bayelsa | F46: 1 | G46: 10 | H46: =G$16*L$8*L$6 -> 500000
B47: 0.10729217 | C47: Uyo | D47: Victor Umeh | F47: 1 | G47: 10 | H47: =G$16*L$8*L$6 -> 500000 | I47: 48 | J47: 48 | K47: =48*2000 -> 96000 | L47: =48*1888 -> 90624 | M47: =48*112 -> 5376 | N47: ALLGRACE | O47: UDOUMANA RD,JOHNSON STREET
B48: 0.18765075 | C48: Calabar | D48: Akpan Enoidem | F48: 1 | G48: 10 | H48: =G$16*L$8*L$6 -> 500000 | I48: 36 | J48: 36 | K48: =J48*2000 -> 72000 | L48: =J48*1888 -> 67968 | M48: =J48*112 -> 4032 | N48: POLYTEX | O48: GOLDIE, MOUNT ZION, ENVIRONS
B49: #N/A | C49: EAST 2 | E49: =SUM(E43:E48) -> 0 | F49: =SUM(F43:F48) -> 6 | G49: =SUM(G43:G48) -> 60 | H49: =SUM(H43:H48) -> 3000000 | I49: 41 | J49: =SUM(J43:J48) -> 84 | K49: =SUM(K43:K48) -> 168000 | L49: =SUM(L43:L48) -> 158592 | M49: =SUM(M43:M48) -> 9408
C50: Ado-Ekiti | D50: Akingbolu Isiaka Opeyemi | F50: 1 | G50: 10 | H50: =G$16*L$8*L$6 -> 500000 | I50: 72 | J50: 72 | K50: =72*2000 -> 144000 | L50: =72*1888 -> 135936 | M50: =72*112 -> 8064 | N50: GADAMS ROYAL PULS | O50: POST OFFICE ATIKANKAN
G51: 10 | H51: =G$16*L$8*L$6 -> 500000
G52: 10 | H52: =G$16*L$8*L$6 -> 500000
B53: #N/A | C53: WEST 1 | E53: =SUM(E44:E49) -> 0 | F53: 1 | G53: =SUM(G50:G52) -> 30 | H53: =SUM(H50:H52) -> 1500000 | I53: =SUM(I50:I52) -> 72 | J53: =SUM(J50:J52) -> 72 | K53: =SUM(K50:K52) -> 144000 | L53: =SUM(L50:L52) -> 135936 | M53: =SUM(M50:M52) -> 8064
C54: TOTAL 3DIM | E54: =E42+E49 -> 0 | F54: =F42+F49+F53 -> 12 | G54: =G42+G49+G53 -> 140 | H54: =H42+H49+H53 -> 7000000 | I54: =I42+I49+I53 -> 113 | J54: =J42+J49+J53 -> 156 | K54: =K42+K49+K53 -> 312000 | L54: =L42+L49+L53 -> 294528 | M54: =M42+M49+M53 -> 17472

Sheet Detail1
A1: Details for Sum of Expected No of Promoters - Region: West 1
A3: Weeks | B3: Region | C3: Area/Location | D3: Agency Supervisor | E3: Commenced? | F3: Expected No of Promoters | G3: Actual Manning | H3: %Ach. | I3: Man Days | J3: Target Consumer days | K3: Actual Consumer Days | L3: No of Drop Points Created | M3: Target Hollandia Evap Milk 120g | N3: Actual Hollandia Evap Milk 120g | O3: Cash Expected | P3: Cash Paid | Q3: TARGET PER REGION | R3: ACTUAL PER REGION | S3: Column1 | T3: Target Volume | U3: Total Volume
B4: West 1 | C4: Ilorin | D4: SEGUN OLORUNTOBA | E4: YES | F4: 0 | G4: 0 | H4: 0 | I4: 0 | J4: 0 | K4: 0 | L4: 0 | M4: 0 | N4: 0 | O4: 0 | P4: 0 | Q4: 0 | R4: 0 | T4: 0 | U4: 0
B5: West 1 | C5: Oshogbo | D5: KOLADE TEMITOPE | E5: YES | F5: 0 | G5: 0 | H5: 0 | I5: 0 | J5: 0 | K5: 0 | L5: 0 | M5: 0 | N5: 0 | O5: 0 | P5: 0 | Q5: 0 | R5: 0 | T5: 0 | U5: 0
B6: West 1 | C6: Ibadan 2 | D6: ALABI OPEYEMI | E6: YES | F6: 0 | G6: 0 | H6: 0 | I6: 0 | J6: 0 | K6: 0 | L6: 0 | M6: 0 | N6: 0 | O6: 0 | P6: 0 | Q6: 0 | R6: 0 | T6: 0 | U6: 0
B7: West 1 | C7: Ibadan 1 | D7: OWOLABI TOLULOPE | E7: YES | F7: 0 | G7: 0 | H7: 0 | I7: 0 | J7: 0 | K7: 0 | L7: 0 | M7: 0 | N7: 0 | O7: 0 | P7: 0 | Q7: 0 | R7: 0 | T7: 0 | U7: 0

Sheet Detail2
A1: Details for Sum of Actual Manning - Region: West 1
A3: Weeks | B3: Region | C3: Area/Location | D3: Agency Supervisor | E3: Commenced? | F3: Expected No of Promoters | G3: Actual Manning | H3: %Ach. | I3: Man Days | J3: Target Consumer days | K3: Actual Consumer Days | L3: No of Drop Points Created | M3: Target Hollandia Evap Milk 120g | N3: Actual Hollandia Evap Milk 120g | O3: Cash Expected | P3: Cash Paid | Q3: TARGET PER REGION | R3: ACTUAL PER REGION | S3: Column1 | T3: Target Volume | U3: Total Volume
B4: West 1 | C4: Ilorin | D4: SEGUN OLORUNTOBA | E4: YES | F4: 0 | G4: 0 | H4: 0 | I4: 0 | J4: 0 | K4: 0 | L4: 0 | M4: 0 | N4: 0 | O4: 0 | P4: 0 | Q4: 0 | R4: 0 | T4: 0 | U4: 0
B5: West 1 | C5: Oshogbo | D5: KOLADE TEMITOPE | E5: YES | F5: 0 | G5: 0 | H5: 0 | I5: 0 | J5: 0 | K5: 0 | L5: 0 | M5: 0 | N5: 0 | O5: 0 | P5: 0 | Q5: 0 | R5: 0 | T5: 0 | U5: 0
B6: West 1 | C6: Ibadan 2 | D6: ALABI OPEYEMI | E6: YES | F6: 0 | G6: 0 | H6: 0 | I6: 0 | J6: 0 | K6: 0 | L6: 0 | M6: 0 | N6: 0 | O6: 0 | P6: 0 | Q6: 0 | R6: 0 | T6: 0 | U6: 0
B7: West 1 | C7: Ibadan 1 | D7: OWOLABI TOLULOPE | E7: YES | F7: 0 | G7: 0 | H7: 0 | I7: 0 | J7: 0 | K7: 0 | L7: 0 | M7: 0 | N7: 0 | O7: 0 | P7: 0 | Q7: 0 | R7: 0 | T7: 0 | U7: 0

Sheet Sheet6
A3: Row Labels | B3: Sum of cases
A4: Ado-Ekiti | B4: 197
A5: Akure | B5: 70
A6: Asaba | B6: 72
A7: Benin | B7: 97
A8: Calabar | B8: 77
A9: Enugu | B9: 62
A10: uyo | B10: 80
A11: Grand Total | B11: 655

Sheet Sheet4
B1: Calabar | C1: Akpan Enoidem | D1: yes | E1: 12 | F1: 12 | H1: 1 | I1: 720 | K1: 41 | L1: 41 | N1: 82000 | O1: 82000
B2: Ado-Ekiti | C2: Akigbolu Isiaka | D2: yes | E2: 12 | F2: 12 | H2: 1 | I2: 720 | K2: 60 | L2: 60 | N2: 120000 | O2: 120000
B3: uyo | C3: Victor Umeh | D3: yes | E3: 12 | F3: 12 | H3: 1 | I3: 720 | K3: 48 | L3: 48 | N3: 96000 | O3: 96000
B4: Calabar | C4: Akpan Enoidem | D4: YES | E4: 12 | F4: 12 | H4: 1 | I4: 720 | K4: 36 | L4: 36 | N4: 72000 | O4: 72000
B5: Ado-Ekiti | C5: Akigbolu Isiaka | D5: yes | E5: 12 | F5: 12 | H5: 1 | I5: 720 | K5: 72 | L5: 72 | N5: 144000 | O5: 144000
B6: Enugu | C6: Mudia | D6: yes | E6: 12 | F6: 12 | H6: 1 | I6: 720 | K6: 62 | L6: 62 | N6: 124630 | O6: 117651
B7: Asaba | C7: IFEANYI CHIADIKABIA | D7: yes | E7: 12 | F7: 12 | H7: 1 | I7: 720 | K7: 72 | L7: 72 | N7: 144000 | O7: 135935
B8: uyo | C8: Victor Umeh | E8: 12 | F8: 12 | H8: 1 | I8: 720 | K8: 32 | L8: 32 | N8: 64000 | O8: 60416
B9: Ado-Ekiti | C9: AKINGBOLU ISIAKA OPEYEMI | E9: 12 | F9: 12 | H9: 1 | I9: 720 | K9: 65 | L9: 65 | N9: 130000 | O9: 122720
B10: Benin | C10: JAMES OLUWASEGUN | E10: 12 | F10: 12 | H10: 1 | I10: 720 | K10: 97 | L10: 97 | N10: 194000 | O10: 183136
B11: Akure | C11: JEROME | E11: 12 | F11: 12 | H11: 1 | I11: 720 | K11: 70 | L11: 70 | N11: 140000 | O11: 132160

Sheet ATD >
L1: Daily sales target per BA | M1: 21
I3: Promoters Update | L3: Man Days | M3: No of Work Days | N3: Hollandia Evap Milk 120g | Q3: Cash Reconciliation | T3: Sales Performance
C4: S/N | D4: Region | E4: Area/Location | F4: Agency Supervisor | G4: Commenced? | H4: Date of Commencement | I4: Expected No of Promoters | J4: Actual Manning | K4: %Ach. | Q4: Cash Reconciliation | T4: PER REGION
N5: Target | O5: Actual | P5: %Ach. | Q5: Expected | R5: Paid | S5: Variance | T5: TARGET | U5: ACTUAL | V5: %ACD
C6: 1 | D6: East 1 | E6: Enugu | K6: =IFERROR(J6/I6,0) -> 0 | L6: =SUMIF(Total!G:G,'ATD >'!E6,Total!K:K) -> 0 | M6: =SUMIF(Total!G:G,'ATD >'!E6,Total!M:M) -> 0 | N6: =I6*M6*$M$1 -> 0 | O6: =SUMIF(Total!G:G,'ATD >'!E6,Total!P:P) -> 0 | P6: =IFERROR(O6/N6,0) -> 0 | Q6: =O6*2000 -> 0 | R6: =SUMIF(Total!G:G,'ATD >'!E6,Total!T:T) -> 0 | S6: =Q6-R6 -> 0 | T6: =I6*M6*2000*21 -> 0 | U6: =R6 -> 0 | V6: =IFERROR(U6/T6,0) -> 0
C7: 2 | D7: East 1 | E7: Abakaliki | K7: =IFERROR(J7/I7,0) -> 0 | L7: =SUMIF(Total!G:G,'ATD >'!E7,Total!K:K) -> 0 | M7: =SUMIF(Total!G:G,'ATD >'!E7,Total!M:M) -> 0 | N7: =I7*M7*$M$1 -> 0 | O7: =SUMIF(Total!G:G,'ATD >'!E7,Total!P:P) -> 0 | P7: =IFERROR(O7/N7,0) -> 0 | Q7: =O7*2000 -> 0 | R7: =SUMIF(Total!G:G,'ATD >'!E7,Total!T:T) -> 0 | S7: =Q7-R7 -> 0 | T7: =I7*M7*2000*21 -> 0 | U7: =R7 -> 0 | V7: =IFERROR(U7/T7,0) -> 0
C8: 3 | D8: East 1 | E8: Onitsha | K8: =IFERROR(J8/I8,0) -> 0 | L8: =SUMIF(Total!G:G,'ATD >'!E8,Total!K:K) -> 120 | M8: =SUMIF(Total!G:G,'ATD >'!E8,Total!M:M) -> 10 | N8: =I8*M8*$M$1 -> 0 | O8: =SUMIF(Total!G:G,'ATD >'!E8,Total!P:P) -> 1477 | P8: =IFERROR(O8/N8,0) -> 0 | Q8: =O8*2000 -> 2954000 | R8: =SUMIF(Total!G:G,'ATD >'!E8,Total!T:T) -> 2792792 | S8: =Q8-R8 -> 161208 | T8: =I8*M8*2000*21 -> 0 | U8: =R8 -> 2792792 | V8: =IFERROR(U8/T8,0) -> 0
C9: 4 | D9: East 1 | E9: Asaba | K9: =IFERROR(J9/I9,0) -> 0 | L9: =SUMIF(Total!G:G,'ATD >'!E9,Total!K:K) -> 108 | M9: =SUMIF(Total!G:G,'ATD >'!E9,Total!M:M) -> 9 | N9: =I9*M9*$M$1 -> 0 | O9: =SUMIF(Total!G:G,'ATD >'!E9,Total!P:P) -> 674 | P9: =IFERROR(O9/N9,0) -> 0 | Q9: =O9*2000 -> 1348000 | R9: =SUMIF(Total!G:G,'ATD >'!E9,Total!T:T) -> 1272512 | S9: =Q9-R9 -> 75488 | T9: =I9*M9*2000*21 -> 0 | U9: =R9 -> 1272512 | V9: =IFERROR(U9/T9,0) -> 0
C10: 5 | D10: East 1 | E10: Owerri | K10: =IFERROR(J10/I10,0) -> 0 | L10: =SUMIF(Total!G:G,'ATD >'!E10,Total!K:K) -> 192 | M10: =SUMIF(Total!G:G,'ATD >'!E10,Total!M:M) -> 16 | N10: =I10*M10*$M$1 -> 0 | O10: =SUMIF(Total!G:G,'ATD >'!E10,Total!P:P) -> 3399 | P10: =IFERROR(O10/N10,0) -> 0 | Q10: =O10*2000 -> 6798000 | R10: =SUMIF(Total!G:G,'ATD >'!E10,Total!T:T) -> 6476896 | S10: =Q10-R10 -> 321104 | T10: =I10*M10*2000*21 -> 0 | U10: =R10 -> 6476896 | V10: =IFERROR(U10/T10,0) -> 0
C11: 6 | D11: East 2 | E11: Aba | K11: =IFERROR(J11/I11,0) -> 0 | L11: =SUMIF(Total!G:G,'ATD >'!E11,Total!K:K) -> 12 | M11: =SUMIF(Total!G:G,'ATD >'!E11,Total!M:M) -> 1 | N11: =I11*M11*$M$1 -> 0 | O11: =SUMIF(Total!G:G,'ATD >'!E11,Total!P:P) -> 53 | P11: =IFERROR(O11/N11,0) -> 0 | Q11: =O11*2000 -> 106000 | R11: =SUMIF(Total!G:G,'ATD >'!E11,Total!T:T) -> 100064 | S11: =Q11-R11 -> 5936 | T11: =I11*M11*2000*21 -> 0 | U11: =R11 -> 100064 | V11: =IFERROR(U11/T11,0) -> 0
C12: 7 | D12: East 2 | E12: PHC 1 | K12: =IFERROR(J12/I12,0) -> 0 | L12: =SUMIF(Total!G:G,'ATD >'!E12,Total!K:K) -> 168 | M12: =SUMIF(Total!G:G,'ATD >'!E12,Total!M:M) -> 14 | N12: =I12*M12*$M$1 -> 0 | O12: =SUMIF(Total!G:G,'ATD >'!E12,Total!P:P) -> 2337 | P12: =IFERROR(O12/N12,0) -> 0 | Q12: =O12*2000 -> 4674000 | R12: =SUMIF(Total!G:G,'ATD >'!E12,Total!T:T) -> 4440480 | S12: =Q12-R12 -> 233520 | T12: =I12*M12*2000*21 -> 0 | U12: =R12 -> 4440480 | V12: =IFERROR(U12/T12,0) -> 0
C13: 8 | D13: East 2 | E13: PHC 2 | K13: =IFERROR(J13/I13,0) -> 0 | L13: =SUMIF(Total!G:G,'ATD >'!E13,Total!K:K) -> 0 | M13: =SUMIF(Total!G:G,'ATD >'!E13,Total!M:M) -> 0 | N13: =I13*M13*$M$1 -> 0 | O13: =SUMIF(Total!G:G,'ATD >'!E13,Total!P:P) -> 0 | P13: =IFERROR(O13/N13,0) -> 0 | Q13: =O13*2000 -> 0 | R13: =SUMIF(Total!G:G,'ATD >'!E13,Total!T:T) -> 0 | S13: =Q13-R13 -> 0 | T13: =I13*M13*2000*21 -> 0 | U13: =R13 -> 0 | V13: =IFERROR(U13/T13,0) -> 0
C14: 9 | D14: East 2 | E14: Bayelsa | K14: =IFERROR(J14/I14,0) -> 0 | L14: =SUMIF(Total!G:G,'ATD >'!E14,Total!K:K) -> 120 | M14: =SUMIF(Total!G:G,'ATD >'!E14,Total!M:M) -> 10 | N14: =I14*M14*$M$1 -> 0 | O14: =SUMIF(Total!G:G,'ATD >'!E14,Total!P:P) -> 2240 | P14: =IFERROR(O14/N14,0) -> 0 | Q14: =O14*2000 -> 4480000 | R14: =SUMIF(Total!G:G,'ATD >'!E14,Total!T:T) -> 4265211 | S14: =Q14-R14 -> 214789 | T14: =I14*M14*2000*21 -> 0 | U14: =R14 -> 4265211 | V14: =IFERROR(U14/T14,0) -> 0
C15: 10 | D15: East 2 | E15: Uyo | F15: Victor Umeh | G15: yes | H15: 46246 | I15: 12 | J15: 12 | K15: =IFERROR(J15/I15,0) -> 1 | L15: =SUMIF(Total!G:G,'ATD >'!E15,Total!K:K) -> 168 | M15: =SUMIF(Total!G:G,'ATD >'!E15,Total!M:M) -> 14 | N15: =I15*M15*$M$1 -> 3528 | O15: =SUMIF(Total!G:G,'ATD >'!E15,Total!P:P) -> 1756 | P15: =IFERROR(O15/N15,0) -> 0.49773243 | Q15: =O15*2000 -> 3512000 | R15: =SUMIF(Total!G:G,'ATD >'!E15,Total!T:T) -> 3315328 | S15: =Q15-R15 -> 196672 | T15: =I15*M15*2000*21 -> 7056000 | U15: =R15 -> 3315328 | V15: =IFERROR(U15/T15,0) -> 0.46985941
C16: 11 | D16: East 2 | E16: Calabar | F16: ENOIDEM AKPAN | G16: Yes | H16: 46245 | I16: 12 | J16: 12 | K16: =IFERROR(J16/I16,0) -> 1 | L16: =SUMIF(Total!G:G,'ATD >'!E16,Total!K:K) -> 144 | M16: =SUMIF(Total!G:G,'ATD >'!E16,Total!M:M) -> 12 | N16: =I16*M16*$M$1 -> 3024 | O16: =SUMIF(Total!G:G,'ATD >'!E16,Total!P:P) -> 1326 | P16: =IFERROR(O16/N16,0) -> 0.43849206 | Q16: =O16*2000 -> 2652000 | R16: =SUMIF(Total!G:G,'ATD >'!E16,Total!T:T) -> 2513980 | S16: =Q16-R16 -> 138020 | T16: =I16*M16*2000*21 -> 6048000 | U16: =R16 -> 2513980 | V16: =IFERROR(U16/T16,0) -> 0.4156713
C17: 12 | D17: West 1 | E17: Ibadan 1 | K17: =IFERROR(J17/I17,0) -> 0 | L17: =SUMIF(Total!G:G,'ATD >'!E17,Total!K:K) -> 0 | M17: =SUMIF(Total!G:G,'ATD >'!E17,Total!M:M) -> 0 | N17: =I17*M17*$M$1 -> 0 | O17: =SUMIF(Total!G:G,'ATD >'!E17,Total!P:P) -> 0 | P17: =IFERROR(O17/N17,0) -> 0 | Q17: =O17*2000 -> 0 | R17: =SUMIF(Total!G:G,'ATD >'!E17,Total!T:T) -> 0 | S17: =Q17-R17 -> 0 | T17: =I17*M17*2000*21 -> 0 | U17: =R17 -> 0 | V17: =IFERROR(U17/T17,0) -> 0
C18: 13 | D18: West 1 | E18: Ibadan 2 | K18: =IFERROR(J18/I18,0) -> 0 | L18: =SUMIF(Total!G:G,'ATD >'!E18,Total!K:K) -> 0 | M18: =SUMIF(Total!G:G,'ATD >'!E18,Total!M:M) -> 0 | N18: =I18*M18*$M$1 -> 0 | O18: =SUMIF(Total!G:G,'ATD >'!E18,Total!P:P) -> 0 | P18: =IFERROR(O18/N18,0) -> 0 | Q18: =O18*2000 -> 0 | R18: =SUMIF(Total!G:G,'ATD >'!E18,Total!T:T) -> 0 | S18: =Q18-R18 -> 0 | T18: =I18*M18*2000*21 -> 0 | U18: =R18 -> 0 | V18: =IFERROR(U18/T18,0) -> 0
C19: 14 | D19: West 1 | E19: Oshogbo | K19: =IFERROR(J19/I19,0) -> 0 | L19: =SUMIF(Total!G:G,'ATD >'!E19,Total!K:K) -> 0 | M19: =SUMIF(Total!G:G,'ATD >'!E19,Total!M:M) -> 0 | N19: =I19*M19*$M$1 -> 0 | O19: =SUMIF(Total!G:G,'ATD >'!E19,Total!P:P) -> 0 | P19: =IFERROR(O19/N19,0) -> 0 | Q19: =O19*2000 -> 0 | R19: =SUMIF(Total!G:G,'ATD >'!E19,Total!T:T) -> 0 | S19: =Q19-R19 -> 0 | T19: =I19*M19*2000*21 -> 0 | U19: =R19 -> 0 | V19: =IFERROR(U19/T19,0) -> 0
C20: 15 | D20: West 1 | E20: Ilorin | K20: =IFERROR(J20/I20,0) -> 0 | L20: =SUMIF(Total!G:G,'ATD >'!E20,Total!K:K) -> 0 | M20: =SUMIF(Total!G:G,'ATD >'!E20,Total!M:M) -> 0 | N20: =I20*M20*$M$1 -> 0 | O20: =SUMIF(Total!G:G,'ATD >'!E20,Total!P:P) -> 0 | P20: =IFERROR(O20/N20,0) -> 0 | Q20: =O20*2000 -> 0 | R20: =SUMIF(Total!G:G,'ATD >'!E20,Total!T:T) -> 0 | S20: =Q20-R20 -> 0 | T20: =I20*M20*2000*21 -> 0 | U20: =R20 -> 0 | V20: =IFERROR(U20/T20,0) -> 0
C21: 16 | D21: West 2 | E21: Benin 1 | K21: =IFERROR(J21/I21,0) -> 0 | L21: =SUMIF(Total!G:G,'ATD >'!E21,Total!K:K) -> 0 | M21: =SUMIF(Total!G:G,'ATD >'!E21,Total!M:M) -> 0 | N21: =I21*M21*$M$1 -> 0 | O21: =SUMIF(Total!G:G,'ATD >'!E21,Total!P:P) -> 0 | P21: =IFERROR(O21/N21,0) -> 0 | Q21: =O21*2000 -> 0 | R21: =SUMIF(Total!G:G,'ATD >'!E21,Total!T:T) -> 0 | S21: =Q21-R21 -> 0 | T21: =I21*M21*2000*21 -> 0 | U21: =R21 -> 0 | V21: =IFERROR(U21/T21,0) -> 0
C22: 17 | D22: West 2 | E22: Benin 2 | K22: =IFERROR(J22/I22,0) -> 0 | L22: =SUMIF(Total!G:G,'ATD >'!E22,Total!K:K) -> 0 | M22: =SUMIF(Total!G:G,'ATD >'!E22,Total!M:M) -> 0 | N22: =I22*M22*$M$1 -> 0 | O22: =SUMIF(Total!G:G,'ATD >'!E22,Total!P:P) -> 0 | P22: =IFERROR(O22/N22,0) -> 0 | Q22: =O22*2000 -> 0 | R22: =SUMIF(Total!G:G,'ATD >'!E22,Total!T:T) -> 0 | S22: =Q22-R22 -> 0 | T22: =I22*M22*2000*21 -> 0 | U22: =R22 -> 0 | V22: =IFERROR(U22/T22,0) -> 0
C23: 18 | D23: West 2 | E23: Akure 1 | K23: =IFERROR(J23/I23,0) -> 0 | L23: =SUMIF(Total!G:G,'ATD >'!E23,Total!K:K) -> 0 | M23: =SUMIF(Total!G:G,'ATD >'!E23,Total!M:M) -> 0 | N23: =I23*M23*$M$1 -> 0 | O23: =SUMIF(Total!G:G,'ATD >'!E23,Total!P:P) -> 0 | P23: =IFERROR(O23/N23,0) -> 0 | Q23: =O23*2000 -> 0 | R23: =SUMIF(Total!G:G,'ATD >'!E23,Total!T:T) -> 0 | S23: =Q23-R23 -> 0 | T23: =I23*M23*2000*21 -> 0 | U23: =R23 -> 0 | V23: =IFERROR(U23/T23,0) -> 0
C24: 19 | D24: West 2 | E24: Ado-Ekiti | F24: Akingbolu Isiaka | G24: Yes | H24: 46245 | I24: 12 | J24: 12 | K24: =IFERROR(J24/I24,0) -> 1 | L24: =SUMIF(Total!G:G,'ATD >'!E24,Total!K:K) -> 144 | M24: =SUMIF(Total!G:G,'ATD >'!E24,Total!M:M) -> 12 | N24: =I24*M24*$M$1 -> 3024 | O24: =SUMIF(Total!G:G,'ATD >'!E24,Total!P:P) -> 1686 | P24: =IFERROR(O24/N24,0) -> 0.55753968 | Q24: =O24*2000 -> 3372000 | R24: =SUMIF(Total!G:G,'ATD >'!E24,Total!T:T) -> 3220296 | S24: =Q24-R24 -> 151704 | T24: =I24*M24*2000*21 -> 6048000 | U24: =R24 -> 3220296 | V24: =IFERROR(U24/T24,0) -> 0.53245635
C25: 20 | D25: West 2 | E25: Warri | K25: =IFERROR(J25/I25,0) -> 0 | L25: =SUMIF(Total!G:G,'ATD >'!E25,Total!K:K) -> 156 | M25: =SUMIF(Total!G:G,'ATD >'!E25,Total!M:M) -> 13 | N25: =I25*M25*$M$1 -> 0 | O25: =SUMIF(Total!G:G,'ATD >'!E25,Total!P:P) -> 2550 | P25: =IFERROR(O25/N25,0) -> 0 | Q25: =O25*2000 -> 5100000 | R25: =SUMIF(Total!G:G,'ATD >'!E25,Total!T:T) -> 4852412 | S25: =Q25-R25 -> 247588 | T25: =I25*M25*2000*21 -> 0 | U25: =R25 -> 4852412 | V25: =IFERROR(U25/T25,0) -> 0
C26: TOTAL | I26: =SUM(I6:I25) -> 36 | J26: =SUM(J6:J25) -> 36 | K26: =J26/I26 -> 1 | L26: =SUM(L6:L25) -> 1332 | M26: =SUM(M6:M25) -> 111 | N26: =SUM(N6:N25) -> 9576 | O26: =SUM(O6:O25) -> 17498 | P26: =O26/N26 -> 1.8272765 | Q26: =SUM(Q6:Q25) -> 34996000 | R26: =SUM(R6:R25) -> 33249971 | S26: =SUM(S6:S25) -> 1746029 | T26: =SUM(T6:T25) -> 19152000 | U26: =SUM(U6:U25) -> 33249971 | V26: =IFERROR(U26/T26,0) -> 1.7361096
I33: Promoters Update | Q33: Cash Reconciliation | T33: Sales Performance
G34: Region | I34: Expected No of Promoters | J34: Actual Manning | K34: %Ach. | L34: Man Days | M34: No of Work Days | N34: Hollandia Evap Milk 120g | Q34: Cash Reconciliation | T34: PER REGION
N35: Target | O35: Actual | P35: %Ach. | Q35: Expected | R35: Paid | S35: Variance | T35: TARGET | U35: ACTUAL | V35: %ACD
G36: East 1 | I36: =SUMIF($D$6:$D$25,$G36,I$6:I$25) -> 0 | J36: =SUMIF($D$6:$D$25,$G36,J$6:J$25) -> 0 | K36: =IFERROR(J36/I36,"") | L36: =SUMIF($D$6:$D$25,$G36,L$6:L$25) -> 420 | M36: =SUMIF($D$6:$D$25,$G36,M$6:M$25) -> 35 | N36: =SUMIF($D$6:$D$25,$G36,N$6:N$25) -> 0 | O36: =SUMIF($D$6:$D$25,$G36,O$6:O$25) -> 5550 | P36: =IFERROR(O36/N36,"") | Q36: =SUMIF($D$6:$D$25,$G36,Q$6:Q$25) -> 11100000 | R36: =SUMIF($D$6:$D$25,$G36,R$6:R$25) -> 10542200 | S36: =R36-Q36 -> -557800 | T36: =SUMIF($D$6:$D$25,$G36,T$6:T$25) -> 0 | U36: =SUMIF($D$6:$D$25,$G36,U$6:U$25) -> 10542200 | V36: =IFERROR(U36/T36,"")
G37: East 2 | I37: =SUMIF($D$6:$D$25,$G37,I$6:I$25) -> 24 | J37: =SUMIF($D$6:$D$25,$G37,J$6:J$25) -> 24 | K37: =IFERROR(J37/I37,"") -> 1 | L37: =SUMIF($D$6:$D$25,$G37,L$6:L$25) -> 612 | M37: =SUMIF($D$6:$D$25,$G37,M$6:M$25) -> 51 | N37: =SUMIF($D$6:$D$25,$G37,N$6:N$25) -> 6552 | O37: =SUMIF($D$6:$D$25,$G37,O$6:O$25) -> 7712 | P37: =IFERROR(O37/N37,"") -> 1.1770452 | Q37: =SUMIF($D$6:$D$25,$G37,Q$6:Q$25) -> 15424000 | R37: =SUMIF($D$6:$D$25,$G37,R$6:R$25) -> 14635063 | S37: =R37-Q37 -> -788937 | T37: =SUMIF($D$6:$D$25,$G37,T$6:T$25) -> 13104000 | U37: =SUMIF($D$6:$D$25,$G37,U$6:U$25) -> 14635063 | V37: =IFERROR(U37/T37,"") -> 1.1168394
G38: West 1 | I38: =SUMIF($D$6:$D$25,$G38,I$6:I$25) -> 0 | J38: =SUMIF($D$6:$D$25,$G38,J$6:J$25) -> 0 | K38: =IFERROR(J38/I38,"") | L38: =SUMIF($D$6:$D$25,$G38,L$6:L$25) -> 0 | M38: =SUMIF($D$6:$D$25,$G38,M$6:M$25) -> 0 | N38: =SUMIF($D$6:$D$25,$G38,N$6:N$25) -> 0 | O38: =SUMIF($D$6:$D$25,$G38,O$6:O$25) -> 0 | P38: =IFERROR(O38/N38,"") | Q38: =SUMIF($D$6:$D$25,$G38,Q$6:Q$25) -> 0 | R38: =SUMIF($D$6:$D$25,$G38,R$6:R$25) -> 0 | S38: =R38-Q38 -> 0 | T38: =SUMIF($D$6:$D$25,$G38,T$6:T$25) -> 0 | U38: =SUMIF($D$6:$D$25,$G38,U$6:U$25) -> 0 | V38: =IFERROR(U38/T38,"")
G39: West 2 | I39: =SUMIF($D$6:$D$25,$G39,I$6:I$25) -> 12 | J39: =SUMIF($D$6:$D$25,$G39,J$6:J$25) -> 12 | K39: =IFERROR(J39/I39,"") -> 1 | L39: =SUMIF($D$6:$D$25,$G39,L$6:L$25) -> 300 | M39: =SUMIF($D$6:$D$25,$G39,M$6:M$25) -> 25 | N39: =SUMIF($D$6:$D$25,$G39,N$6:N$25) -> 3024 | O39: =SUMIF($D$6:$D$25,$G39,O$6:O$25) -> 4236 | P39: =IFERROR(O39/N39,"") -> 1.4007937 | Q39: =SUMIF($D$6:$D$25,$G39,Q$6:Q$25) -> 8472000 | R39: =SUMIF($D$6:$D$25,$G39,R$6:R$25) -> 8072708 | S39: =R39-Q39 -> -399292 | T39: =SUMIF($D$6:$D$25,$G39,T$6:T$25) -> 6048000 | U39: =SUMIF($D$6:$D$25,$G39,U$6:U$25) -> 8072708 | V39: =IFERROR(U39/T39,"") -> 1.3347731
G40: TOTAL | I40: =SUM(I36:I39) -> 36 | J40: =SUM(J36:J39) -> 36 | K40: =IFERROR(J40/I40,"") -> 1 | M40: =SUMIF($D$6:$D$25,$G40,M$6:M$25) -> 0 | N40: =SUM(N36:N39) -> 9576 | O40: =SUM(O36:O39) -> 17498 | P40: =O40/N40 -> 1.8272765 | Q40: =SUM(Q36:Q39) -> 34996000 | R40: =SUM(R36:R39) -> 33249971 | S40: =SUM(S36:S39) -> -1746029 | T40: =SUM(T36:T39) -> 19152000 | U40: =SUM(U36:U39) -> 33249971 | V40: =IFERROR(U40/T40,"") -> 1.7361096

Sheet REGIONAL PTD
J4: Cash Reconciliation | M4: Sales Performance
C5: SIN | D5: Region | E5: Area/Location | F5: No of Work Days | G5: Hollandia Evap Milk 120g | J5: Cash Reconciliation | M5: PER REGION
G6: Target | H6: Actual | I6: %Ach. | J6: Expected | K6: Paid | L6: Variance | M6: TARGET | N6: ACTUAL | O6: %ACD
C7: ='ATD >'!C6 -> 1 | D7: ='ATD >'!D6 -> East 1 | E7: ='ATD >'!E6 -> Enugu | F7: =SUMIF('ATD >'!E:E,'REGIONAL PTD'!E7,'ATD >'!M:M) -> 0 | G7: =SUMIF('ATD >'!E:E,'REGIONAL PTD'!E7,'ATD >'!N:N) -> 0 | H7: =SUMIF('ATD >'!E:E,'REGIONAL PTD'!E7,'ATD >'!O:O) -> 0 | I7: =SUMIF('ATD >'!E:E,'REGIONAL PTD'!E7,'ATD >'!P:P) -> 0 | J7: =SUMIF('ATD >'!E:E,'REGIONAL PTD'!E7,'ATD >'!Q:Q) -> 0 | K7: =SUMIF('ATD >'!E:E,'REGIONAL PTD'!E7,'ATD >'!R:R) -> 0 | L7: =SUMIF('ATD >'!E:E,'REGIONAL PTD'!E7,'ATD >'!S:S) -> 0 | M7: =SUMIF('ATD >'!E:E,'REGIONAL PTD'!E7,'ATD >'!T:T) -> 0 | N7: =SUMIF('ATD >'!E:E,'REGIONAL PTD'!E7,'ATD >'!U:U) -> 0 | O7: =SUMIF('ATD >'!E:E,'REGIONAL PTD'!E7,'ATD >'!V:V) -> 0
C8: ='ATD >'!C7 -> 2 | D8: ='ATD >'!D7 -> East 1 | E8: ='ATD >'!E7 -> Abakaliki | F8: =SUMIF('ATD >'!E:E,'REGIONAL PTD'!E8,'ATD >'!M:M) -> 0 | G8: =SUMIF('ATD >'!E:E,'REGIONAL PTD'!E8,'ATD >'!N:N) -> 0 | H8: =SUMIF('ATD >'!E:E,'REGIONAL PTD'!E8,'ATD >'!O:O) -> 0 | I8: =SUMIF('ATD >'!E:E,'REGIONAL PTD'!E8,'ATD >'!P:P) -> 0 | J8: =SUMIF('ATD >'!E:E,'REGIONAL PTD'!E8,'ATD >'!Q:Q) -> 0 | K8: =SUMIF('ATD >'!E:E,'REGIONAL PTD'!E8,'ATD >'!R:R) -> 0 | L8: =SUMIF('ATD >'!E:E,'REGIONAL PTD'!E8,'ATD >'!S:S) -> 0 | M8: =SUMIF('ATD >'!E:E,'REGIONAL PTD'!E8,'ATD >'!T:T) -> 0 | N8: =SUMIF('ATD >'!E:E,'REGIONAL PTD'!E8,'ATD >'!U:U) -> 0 | O8: =SUMIF('ATD >'!E:E,'REGIONAL PTD'!E8,'ATD >'!V:V) -> 0
C9: ='ATD >'!C8 -> 3 | D9: ='ATD >'!D8 -> East 1 | E9: ='ATD >'!E8 -> Onitsha | F9: =SUMIF('ATD >'!E:E,'REGIONAL PTD'!E9,'ATD >'!M:M) -> 10 | G9: =SUMIF('ATD >'!E:E,'REGIONAL PTD'!E9,'ATD >'!N:N) -> 0 | H9: =SUMIF('ATD >'!E:E,'REGIONAL PTD'!E9,'ATD >'!O:O) -> 1477 | I9: =SUMIF('ATD >'!E:E,'REGIONAL PTD'!E9,'ATD >'!P:P) -> 0 | J9: =SUMIF('ATD >'!E:E,'REGIONAL PTD'!E9,'ATD >'!Q:Q) -> 2954000 | K9: =SUMIF('ATD >'!E:E,'REGIONAL PTD'!E9,'ATD >'!R:R) -> 2792792 | L9: =SUMIF('ATD >'!E:E,'REGIONAL PTD'!E9,'ATD >'!S:S) -> 161208 | M9: =SUMIF('ATD >'!E:E,'REGIONAL PTD'!E9,'ATD >'!T:T) -> 0 | N9: =SUMIF('ATD >'!E:E,'REGIONAL PTD'!E9,'ATD >'!U:U) -> 2792792 | O9: =SUMIF('ATD >'!E:E,'REGIONAL PTD'!E9,'ATD >'!V:V) -> 0
C10: ='ATD >'!C9 -> 4 | D10: ='ATD >'!D9 -> East 1 | E10: ='ATD >'!E9 -> Asaba | F10: =SUMIF('ATD >'!E:E,'REGIONAL PTD'!E10,'ATD >'!M:M) -> 9 | G10: =SUMIF('ATD >'!E:E,'REGIONAL PTD'!E10,'ATD >'!N:N) -> 0 | H10: =SUMIF('ATD >'!E:E,'REGIONAL PTD'!E10,'ATD >'!O:O) -> 674 | I10: =SUMIF('ATD >'!E:E,'REGIONAL PTD'!E10,'ATD >'!P:P) -> 0 | J10: =SUMIF('ATD >'!E:E,'REGIONAL PTD'!E10,'ATD >'!Q:Q) -> 1348000 | K10: =SUMIF('ATD >'!E:E,'REGIONAL PTD'!E10,'ATD >'!R:R) -> 1272512 | L10: =SUMIF('ATD >'!E:E,'REGIONAL PTD'!E10,'ATD >'!S:S) -> 75488 | M10: =SUMIF('ATD >'!E:E,'REGIONAL PTD'!E10,'ATD >'!T:T) -> 0 | N10: =SUMIF('ATD >'!E:E,'REGIONAL PTD'!E10,'ATD >'!U:U) -> 1272512 | O10: =SUMIF('ATD >'!E:E,'REGIONAL PTD'!E10,'ATD >'!V:V) -> 0
C11: ='ATD >'!C10 -> 5 | D11: ='ATD >'!D10 -> East 1 | E11: ='ATD >'!E10 -> Owerri | F11: =SUMIF('ATD >'!E:E,'REGIONAL PTD'!E11,'ATD >'!M:M) -> 16 | G11: =SUMIF('ATD >'!E:E,'REGIONAL PTD'!E11,'ATD >'!N:N) -> 0 | H11: =SUMIF('ATD >'!E:E,'REGIONAL PTD'!E11,'ATD >'!O:O) -> 3399 | I11: =SUMIF('ATD >'!E:E,'REGIONAL PTD'!E11,'ATD >'!P:P) -> 0 | J11: =SUMIF('ATD >'!E:E,'REGIONAL PTD'!E11,'ATD >'!Q:Q) -> 6798000 | K11: =SUMIF('ATD >'!E:E,'REGIONAL PTD'!E11,'ATD >'!R:R) -> 6476896 | L11: =SUMIF('ATD >'!E:E,'REGIONAL PTD'!E11,'ATD >'!S:S) -> 321104 | M11: =SUMIF('ATD >'!E:E,'REGIONAL PTD'!E11,'ATD >'!T:T) -> 0 | N11: =SUMIF('ATD >'!E:E,'REGIONAL PTD'!E11,'ATD >'!U:U) -> 6476896 | O11: =SUMIF('ATD >'!E:E,'REGIONAL PTD'!E11,'ATD >'!V:V) -> 0
C12: Total | G12: =SUM(G7:G11) -> 0 | H12: =SUM(H7:H11) -> 5550 | I12: =SUM(I7:I11) -> 0 | J12: =SUM(J7:J11) -> 11100000 | K12: =SUM(K7:K11) -> 10542200 | L12: =SUM(L7:L11) -> 557800 | M12: =SUM(M7:M11) -> 0 | N12: =SUM(N7:N11) -> 10542200 | O12: =N12/M12 -> #DIV/0!
J17: Cash Reconciliation | M17: Sales Performance
C18: SIN | D18: Region | E18: Area/Location | F18: No of Work Days | G18: Hollandia Evap Milk 120g | J18: Cash Reconciliation | M18: PER REGION
G19: Target | H19: Actual | I19: %Ach. | J19: Expected | K19: Paid | L19: Variance | M19: TARGET | N19: ACTUAL | O19: %ACD
C20: 1 | D20: ='ATD >'!D11 -> East 2 | E20: ='ATD >'!E11 -> Aba | F20: =SUMIF('ATD >'!E:E,'REGIONAL PTD'!E20,'ATD >'!M:M) -> 1 | G20: =SUMIF('ATD >'!E:E,E20,'ATD >'!N:N) -> 0 | H20: =SUMIF('ATD >'!E:E,'REGIONAL PTD'!E20,'ATD >'!O:O) -> 53 | I20: =SUMIF('ATD >'!E:E,'REGIONAL PTD'!E20,'ATD >'!P:P) -> 0 | J20: =SUMIF('ATD >'!E:E,'REGIONAL PTD'!E20,'ATD >'!Q:Q) -> 106000 | K20: =SUMIF('ATD >'!E:E,'REGIONAL PTD'!E20,'ATD >'!R:R) -> 100064 | L20: =SUMIF('ATD >'!E:E,'REGIONAL PTD'!E20,'ATD >'!S:S) -> 5936 | M20: =SUMIF('ATD >'!E:E,'REGIONAL PTD'!E20,'ATD >'!T:T) -> 0 | N20: =SUMIF('ATD >'!E:E,'REGIONAL PTD'!E20,'ATD >'!U:U) -> 100064 | O20: =SUMIF('ATD >'!E:E,'REGIONAL PTD'!E20,'ATD >'!V:V) -> 0
C21: 2 | D21: ='ATD >'!D12 -> East 2 | E21: ='ATD >'!E12 -> PHC 1 | F21: =SUMIF('ATD >'!E:E,'REGIONAL PTD'!E21,'ATD >'!M:M) -> 14 | G21: =SUMIF('ATD >'!E:E,E21,'ATD >'!N:N) -> 0 | H21: =SUMIF('ATD >'!E:E,'REGIONAL PTD'!E21,'ATD >'!O:O) -> 2337 | I21: =SUMIF('ATD >'!E:E,'REGIONAL PTD'!E21,'ATD >'!P:P) -> 0 | J21: =SUMIF('ATD >'!E:E,'REGIONAL PTD'!E21,'ATD >'!Q:Q) -> 4674000 | K21: =SUMIF('ATD >'!E:E,'REGIONAL PTD'!E21,'ATD >'!R:R) -> 4440480 | L21: =SUMIF('ATD >'!E:E,'REGIONAL PTD'!E21,'ATD >'!S:S) -> 233520 | M21: =SUMIF('ATD >'!E:E,'REGIONAL PTD'!E21,'ATD >'!T:T) -> 0 | N21: =SUMIF('ATD >'!E:E,'REGIONAL PTD'!E21,'ATD >'!U:U) -> 4440480 | O21: =SUMIF('ATD >'!E:E,'REGIONAL PTD'!E21,'ATD >'!V:V) -> 0
C22: 3 | D22: ='ATD >'!D13 -> East 2 | E22: ='ATD >'!E13 -> PHC 2 | F22: =SUMIF('ATD >'!E:E,'REGIONAL PTD'!E22,'ATD >'!M:M) -> 0 | G22: =SUMIF('ATD >'!E:E,E22,'ATD >'!N:N) -> 0 | H22: =SUMIF('ATD >'!E:E,'REGIONAL PTD'!E22,'ATD >'!O:O) -> 0 | I22: =SUMIF('ATD >'!E:E,'REGIONAL PTD'!E22,'ATD >'!P:P) -> 0 | J22: =SUMIF('ATD >'!E:E,'REGIONAL PTD'!E22,'ATD >'!Q:Q) -> 0 | K22: =SUMIF('ATD >'!E:E,'REGIONAL PTD'!E22,'ATD >'!R:R) -> 0 | L22: =SUMIF('ATD >'!E:E,'REGIONAL PTD'!E22,'ATD >'!S:S) -> 0 | M22: =SUMIF('ATD >'!E:E,'REGIONAL PTD'!E22,'ATD >'!T:T) -> 0 | N22: =SUMIF('ATD >'!E:E,'REGIONAL PTD'!E22,'ATD >'!U:U) -> 0 | O22: =SUMIF('ATD >'!E:E,'REGIONAL PTD'!E22,'ATD >'!V:V) -> 0
C23: 4 | D23: ='ATD >'!D14 -> East 2 | E23: ='ATD >'!E14 -> Bayelsa | F23: =SUMIF('ATD >'!E:E,'REGIONAL PTD'!E23,'ATD >'!M:M) -> 10 | G23: =SUMIF('ATD >'!E:E,E23,'ATD >'!N:N) -> 0 | H23: =SUMIF('ATD >'!E:E,'REGIONAL PTD'!E23,'ATD >'!O:O) -> 2240 | I23: =SUMIF('ATD >'!E:E,'REGIONAL PTD'!E23,'ATD >'!P:P) -> 0 | J23: =SUMIF('ATD >'!E:E,'REGIONAL PTD'!E23,'ATD >'!Q:Q) -> 4480000 | K23: =SUMIF('ATD >'!E:E,'REGIONAL PTD'!E23,'ATD >'!R:R) -> 4265211 | L23: =SUMIF('ATD >'!E:E,'REGIONAL PTD'!E23,'ATD >'!S:S) -> 214789 | M23: =SUMIF('ATD >'!E:E,'REGIONAL PTD'!E23,'ATD >'!T:T) -> 0 | N23: =SUMIF('ATD >'!E:E,'REGIONAL PTD'!E23,'ATD >'!U:U) -> 4265211 | O23: =SUMIF('ATD >'!E:E,'REGIONAL PTD'!E23,'ATD >'!V:V) -> 0
C24: 5 | D24: ='ATD >'!D15 -> East 2 | E24: ='ATD >'!E15 -> Uyo | F24: =SUMIF('ATD >'!E:E,'REGIONAL PTD'!E24,'ATD >'!M:M) -> 14 | G24: =SUMIF('ATD >'!E:E,E24,'ATD >'!N:N) -> 3528 | H24: =SUMIF('ATD >'!E:E,'REGIONAL PTD'!E24,'ATD >'!O:O) -> 1756 | I24: =SUMIF('ATD >'!E:E,'REGIONAL PTD'!E24,'ATD >'!P:P) -> 0.49773243 | J24: =SUMIF('ATD >'!E:E,'REGIONAL PTD'!E24,'ATD >'!Q:Q) -> 3512000 | K24: =SUMIF('ATD >'!E:E,'REGIONAL PTD'!E24,'ATD >'!R:R) -> 3315328 | L24: =SUMIF('ATD >'!E:E,'REGIONAL PTD'!E24,'ATD >'!S:S) -> 196672 | M24: =SUMIF('ATD >'!E:E,'REGIONAL PTD'!E24,'ATD >'!T:T) -> 7056000 | N24: =SUMIF('ATD >'!E:E,'REGIONAL PTD'!E24,'ATD >'!U:U) -> 3315328 | O24: =SUMIF('ATD >'!E:E,'REGIONAL PTD'!E24,'ATD >'!V:V) -> 0.46985941
C25: 6 | D25: ='ATD >'!D16 -> East 2 | E25: ='ATD >'!E16 -> Calabar | F25: =SUMIF('ATD >'!E:E,'REGIONAL PTD'!E25,'ATD >'!M:M) -> 12 | G25: =SUMIF('ATD >'!E:E,E25,'ATD >'!N:N) -> 3024 | H25: =SUMIF('ATD >'!E:E,'REGIONAL PTD'!E25,'ATD >'!O:O) -> 1326 | I25: =SUMIF('ATD >'!E:E,'REGIONAL PTD'!E25,'ATD >'!P:P) -> 0.43849206 | J25: =SUMIF('ATD >'!E:E,'REGIONAL PTD'!E25,'ATD >'!Q:Q) -> 2652000 | K25: =SUMIF('ATD >'!E:E,'REGIONAL PTD'!E25,'ATD >'!R:R) -> 2513980 | L25: =SUMIF('ATD >'!E:E,'REGIONAL PTD'!E25,'ATD >'!S:S) -> 138020 | M25: =SUMIF('ATD >'!E:E,'REGIONAL PTD'!E25,'ATD >'!T:T) -> 6048000 | N25: =SUMIF('ATD >'!E:E,'REGIONAL PTD'!E25,'ATD >'!U:U) -> 2513980 | O25: =SUMIF('ATD >'!E:E,'REGIONAL PTD'!E25,'ATD >'!V:V) -> 0.4156713
C26: Total | G26: =SUM(G21:G25) -> 6552 | H26: =SUM(H21:H25) -> 7659 | I26: =SUM(I21:I25) -> 0.93622449 | J26: =SUM(J21:J25) -> 15318000 | K26: =SUM(K21:K25) -> 14534999 | L26: =SUM(L21:L25) -> 783001 | M26: =SUM(M21:M25) -> 13104000 | N26: =SUM(N21:N25) -> 14534999 | O26: =N26/M26 -> 1.1092032
J32: Cash Reconciliation | M32: Sales Performance
C33: SIN | D33: Region | E33: Area/Location | F33: No of Work Days | G33: Hollandia Evap Milk 120g | J33: Cash Reconciliation | M33: PER REGION
G34: Target | H34: Actual | I34: %Ach. | J34: Expected | K34: Paid | L34: Variance | M34: TARGET | N34: ACTUAL | O34: %ACD
C35: 1 | D35: ='ATD >'!D17 -> West 1 | E35: ='ATD >'!E17 -> Ibadan 1 | F35: =SUMIF('ATD >'!E:E,'REGIONAL PTD'!E35,'ATD >'!M:M) -> 0 | G35: =SUMIF('ATD >'!E:E,E35,'ATD >'!N:N) -> 0 | H35: =SUMIF('ATD >'!E:E,'REGIONAL PTD'!E35,'ATD >'!O:O) -> 0 | I35: =SUMIF('ATD >'!E:E,'REGIONAL PTD'!E35,'ATD >'!P:P) -> 0 | J35: =SUMIF('ATD >'!E:E,'REGIONAL PTD'!E35,'ATD >'!Q:Q) -> 0 | K35: =SUMIF('ATD >'!E:E,'REGIONAL PTD'!E35,'ATD >'!R:R) -> 0 | L35: =SUMIF('ATD >'!E:E,'REGIONAL PTD'!E35,'ATD >'!S:S) -> 0 | M35: =SUMIF('ATD >'!E:E,'REGIONAL PTD'!E35,'ATD >'!T:T) -> 0 | N35: =SUMIF('ATD >'!E:E,'REGIONAL PTD'!E35,'ATD >'!U:U) -> 0 | O35: =SUMIF('ATD >'!E:E,'REGIONAL PTD'!E35,'ATD >'!V:V) -> 0
C36: 2 | D36: ='ATD >'!D18 -> West 1 | E36: ='ATD >'!E18 -> Ibadan 2 | F36: =SUMIF('ATD >'!E:E,'REGIONAL PTD'!E36,'ATD >'!M:M) -> 0 | G36: =SUMIF('ATD >'!E:E,E36,'ATD >'!N:N) -> 0 | H36: =SUMIF('ATD >'!E:E,'REGIONAL PTD'!E36,'ATD >'!O:O) -> 0 | I36: =SUMIF('ATD >'!E:E,'REGIONAL PTD'!E36,'ATD >'!P:P) -> 0 | J36: =SUMIF('ATD >'!E:E,'REGIONAL PTD'!E36,'ATD >'!Q:Q) -> 0 | K36: =SUMIF('ATD >'!E:E,'REGIONAL PTD'!E36,'ATD >'!R:R) -> 0 | L36: =SUMIF('ATD >'!E:E,'REGIONAL PTD'!E36,'ATD >'!S:S) -> 0 | M36: =SUMIF('ATD >'!E:E,'REGIONAL PTD'!E36,'ATD >'!T:T) -> 0 | N36: =SUMIF('ATD >'!E:E,'REGIONAL PTD'!E36,'ATD >'!U:U) -> 0 | O36: =SUMIF('ATD >'!E:E,'REGIONAL PTD'!E36,'ATD >'!V:V) -> 0
C37: 3 | D37: ='ATD >'!D19 -> West 1 | E37: ='ATD >'!E19 -> Oshogbo | F37: =SUMIF('ATD >'!E:E,'REGIONAL PTD'!E37,'ATD >'!M:M) -> 0 | G37: =SUMIF('ATD >'!E:E,E37,'ATD >'!N:N) -> 0 | H37: =SUMIF('ATD >'!E:E,'REGIONAL PTD'!E37,'ATD >'!O:O) -> 0 | I37: =SUMIF('ATD >'!E:E,'REGIONAL PTD'!E37,'ATD >'!P:P) -> 0 | J37: =SUMIF('ATD >'!E:E,'REGIONAL PTD'!E37,'ATD >'!Q:Q) -> 0 | K37: =SUMIF('ATD >'!E:E,'REGIONAL PTD'!E37,'ATD >'!R:R) -> 0 | L37: =SUMIF('ATD >'!E:E,'REGIONAL PTD'!E37,'ATD >'!S:S) -> 0 | M37: =SUMIF('ATD >'!E:E,'REGIONAL PTD'!E37,'ATD >'!T:T) -> 0 | N37: =SUMIF('ATD >'!E:E,'REGIONAL PTD'!E37,'ATD >'!U:U) -> 0 | O37: =SUMIF('ATD >'!E:E,'REGIONAL PTD'!E37,'ATD >'!V:V) -> 0
C38: 4 | D38: ='ATD >'!D20 -> West 1 | E38: ='ATD >'!E20 -> Ilorin | F38: =SUMIF('ATD >'!E:E,'REGIONAL PTD'!E38,'ATD >'!M:M) -> 0 | G38: =SUMIF('ATD >'!E:E,E38,'ATD >'!N:N) -> 0 | H38: =SUMIF('ATD >'!E:E,'REGIONAL PTD'!E38,'ATD >'!O:O) -> 0 | I38: =SUMIF('ATD >'!E:E,'REGIONAL PTD'!E38,'ATD >'!P:P) -> 0 | J38: =SUMIF('ATD >'!E:E,'REGIONAL PTD'!E38,'ATD >'!Q:Q) -> 0 | K38: =SUMIF('ATD >'!E:E,'REGIONAL PTD'!E38,'ATD >'!R:R) -> 0 | L38: =SUMIF('ATD >'!E:E,'REGIONAL PTD'!E38,'ATD >'!S:S) -> 0 | M38: =SUMIF('ATD >'!E:E,'REGIONAL PTD'!E38,'ATD >'!T:T) -> 0 | N38: =SUMIF('ATD >'!E:E,'REGIONAL PTD'!E38,'ATD >'!U:U) -> 0 | O38: =SUMIF('ATD >'!E:E,'REGIONAL PTD'!E38,'ATD >'!V:V) -> 0
C39: Total | G39: =SUM(G34:G38) -> 0 | H39: =SUM(H34:H38) -> 0 | I39: =SUM(I34:I38) -> 0 | J39: =SUM(J34:J38) -> 0 | K39: =SUM(K34:K38) -> 0 | L39: =SUM(L34:L38) -> 0 | M39: =SUM(M34:M38) -> 0 | N39: =SUM(N34:N38) -> 0 | O39: =N39/M39 -> #DIV/0!
J45: Cash Reconciliation | M45: Sales Performance
C46: SIN | D46: Region | E46: Area/Location | F46: No of Work Days | G46: Hollandia Evap Milk 120g | J46: Cash Reconciliation | M46: PER REGION
G47: Target | H47: Actual | I47: %Ach. | J47: Expected | K47: Paid | L47: Variance | M47: TARGET | N47: ACTUAL | O47: %ACD
C48: 1 | D48: ='ATD >'!D21 -> West 2 | E48: ='ATD >'!E21 -> Benin 1 | F48: =SUMIF('ATD >'!E:E,'REGIONAL PTD'!E48,'ATD >'!M:M) -> 0 | G48: =SUMIF('ATD >'!E:E,E48,'ATD >'!N:N) -> 0 | H48: =SUMIF('ATD >'!E:E,'REGIONAL PTD'!E48,'ATD >'!O:O) -> 0 | I48: =SUMIF('ATD >'!E:E,'REGIONAL PTD'!E48,'ATD >'!P:P) -> 0 | J48: =SUMIF('ATD >'!E:E,'REGIONAL PTD'!E48,'ATD >'!Q:Q) -> 0 | K48: =SUMIF('ATD >'!E:E,'REGIONAL PTD'!E48,'ATD >'!R:R) -> 0 | L48: =SUMIF('ATD >'!E:E,'REGIONAL PTD'!E48,'ATD >'!S:S) -> 0 | M48: =SUMIF('ATD >'!E:E,'REGIONAL PTD'!E48,'ATD >'!T:T) -> 0 | N48: =SUMIF('ATD >'!E:E,'REGIONAL PTD'!E48,'ATD >'!U:U) -> 0 | O48: =SUMIF('ATD >'!E:E,'REGIONAL PTD'!E48,'ATD >'!V:V) -> 0
C49: 2 | D49: ='ATD >'!D22 -> West 2 | E49: ='ATD >'!E22 -> Benin 2 | F49: =SUMIF('ATD >'!E:E,'REGIONAL PTD'!E49,'ATD >'!M:M) -> 0 | G49: =SUMIF('ATD >'!E:E,E49,'ATD >'!N:N) -> 0 | H49: =SUMIF('ATD >'!E:E,'REGIONAL PTD'!E49,'ATD >'!O:O) -> 0 | I49: =SUMIF('ATD >'!E:E,'REGIONAL PTD'!E49,'ATD >'!P:P) -> 0 | J49: =SUMIF('ATD >'!E:E,'REGIONAL PTD'!E49,'ATD >'!Q:Q) -> 0 | K49: =SUMIF('ATD >'!E:E,'REGIONAL PTD'!E49,'ATD >'!R:R) -> 0 | L49: =SUMIF('ATD >'!E:E,'REGIONAL PTD'!E49,'ATD >'!S:S) -> 0 | M49: =SUMIF('ATD >'!E:E,'REGIONAL PTD'!E49,'ATD >'!T:T) -> 0 | N49: =SUMIF('ATD >'!E:E,'REGIONAL PTD'!E49,'ATD >'!U:U) -> 0 | O49: =SUMIF('ATD >'!E:E,'REGIONAL PTD'!E49,'ATD >'!V:V) -> 0
C50: 3 | D50: ='ATD >'!D23 -> West 2 | E50: ='ATD >'!E23 -> Akure 1 | F50: =SUMIF('ATD >'!E:E,'REGIONAL PTD'!E50,'ATD >'!M:M) -> 0 | G50: =SUMIF('ATD >'!E:E,E50,'ATD >'!N:N) -> 0 | H50: =SUMIF('ATD >'!E:E,'REGIONAL PTD'!E50,'ATD >'!O:O) -> 0 | I50: =SUMIF('ATD >'!E:E,'REGIONAL PTD'!E50,'ATD >'!P:P) -> 0 | J50: =SUMIF('ATD >'!E:E,'REGIONAL PTD'!E50,'ATD >'!Q:Q) -> 0 | K50: =SUMIF('ATD >'!E:E,'REGIONAL PTD'!E50,'ATD >'!R:R) -> 0 | L50: =SUMIF('ATD >'!E:E,'REGIONAL PTD'!E50,'ATD >'!S:S) -> 0 | M50: =SUMIF('ATD >'!E:E,'REGIONAL PTD'!E50,'ATD >'!T:T) -> 0 | N50: =SUMIF('ATD >'!E:E,'REGIONAL PTD'!E50,'ATD >'!U:U) -> 0 | O50: =SUMIF('ATD >'!E:E,'REGIONAL PTD'!E50,'ATD >'!V:V) -> 0
C51: 4 | D51: ='ATD >'!D24 -> West 2 | E51: ='ATD >'!E24 -> Ado-Ekiti | F51: =SUMIF('ATD >'!E:E,'REGIONAL PTD'!E51,'ATD >'!M:M) -> 12 | G51: =SUMIF('ATD >'!E:E,E51,'ATD >'!N:N) -> 3024 | H51: =SUMIF('ATD >'!E:E,'REGIONAL PTD'!E51,'ATD >'!O:O) -> 1686 | I51: =SUMIF('ATD >'!E:E,'REGIONAL PTD'!E51,'ATD >'!P:P) -> 0.55753968 | J51: =SUMIF('ATD >'!E:E,'REGIONAL PTD'!E51,'ATD >'!Q:Q) -> 3372000 | K51: =SUMIF('ATD >'!E:E,'REGIONAL PTD'!E51,'ATD >'!R:R) -> 3220296 | L51: =SUMIF('ATD >'!E:E,'REGIONAL PTD'!E51,'ATD >'!S:S) -> 151704 | M51: =SUMIF('ATD >'!E:E,'REGIONAL PTD'!E51,'ATD >'!T:T) -> 6048000 | N51: =SUMIF('ATD >'!E:E,'REGIONAL PTD'!E51,'ATD >'!U:U) -> 3220296 | O51: =SUMIF('ATD >'!E:E,'REGIONAL PTD'!E51,'ATD >'!V:V) -> 0.53245635
C52: 5 | D52: ='ATD >'!D25 -> West 2 | E52: ='ATD >'!E25 -> Warri | F52: =SUMIF('ATD >'!E:E,'REGIONAL PTD'!E52,'ATD >'!M:M) -> 13 | G52: =SUMIF('ATD >'!E:E,E52,'ATD >'!N:N) -> 0 | H52: =SUMIF('ATD >'!E:E,'REGIONAL PTD'!E52,'ATD >'!O:O) -> 2550 | I52: =SUMIF('ATD >'!E:E,'REGIONAL PTD'!E52,'ATD >'!P:P) -> 0 | J52: =SUMIF('ATD >'!E:E,'REGIONAL PTD'!E52,'ATD >'!Q:Q) -> 5100000 | K52: =SUMIF('ATD >'!E:E,'REGIONAL PTD'!E52,'ATD >'!R:R) -> 4852412 | L52: =SUMIF('ATD >'!E:E,'REGIONAL PTD'!E52,'ATD >'!S:S) -> 247588 | M52: =SUMIF('ATD >'!E:E,'REGIONAL PTD'!E52,'ATD >'!T:T) -> 0 | N52: =SUMIF('ATD >'!E:E,'REGIONAL PTD'!E52,'ATD >'!U:U) -> 4852412 | O52: =SUMIF('ATD >'!E:E,'REGIONAL PTD'!E52,'ATD >'!V:V) -> 0
C53: Total | G53: =SUM(G48:G52) -> 3024 | H53: =SUM(H48:H52) -> 4236 | I53: =SUM(I48:I52) -> 0.55753968 | J53: =SUM(J48:J52) -> 8472000 | K53: =SUM(K48:K52) -> 8072708 | L53: =SUM(L48:L52) -> 399292 | M53: =SUM(M48:M52) -> 6048000 | N53: =SUM(N48:N52) -> 8072708 | O53: =N53/M53 -> 1.3347731

Sheet NEW ATD PER TEAM
C2: Start Date
C3: 45547
B5: DTC Report
G6: Promoters Update | K6: Sales Report | Z6: Cash Reconciliation | AC6: Sales Performance
B7: SIN | C7: Region | D7: Location | E7: Area | F7: Agency Supervisor | G7: Expected No of Promoters | H7: Actual Manning | I7: %Ach | J7: MAN DAYS | K7: Capri-sun 200ml x 40ml | N7: Hollandia Evap Milk 120g | Q7: Hollandia Yoghurt 90ml | T7: Hollandia Yoghurt Plain 315ml | W7: Exotic PC 315ml | Z7: Cash Reconciliation | AC7: PER REGION
C8: East 1 | K8: Target | L8: Actual | M8: %Ach. | N8: Target | O8: Actual | P8: %Ach. | Q8: Target | R8: Actual | S8: %Ach. | T8: Target | U8: Actual | V8: %Ach. | W8: Target | X8: Actual | Y8: %Ach. | Z8: Expected | AA8: Paid | AB8: Variance | AC8: TARGET | AD8: ACTUAL | AE8: %ACD
D9: Enugu | F9: JUDITH NKECHI OBIESIE
B10: 1 | D10: Team 1 | E10: Uydi-Market | G10: 8 | H10: 7 | I10: =IFERROR(H10/G10,"") -> 0.875 | J10: =SUMIF('[1]Total 2'!$I:$I,_xlfn.TEXTJOIN(" ",TRUE,'NEW ATD PER TEAM'!$D$9,'NEW ATD PER TEAM'!$D10),'[1]Total 2'!L:L) -> #VALUE! | K10: =J10*68/40 -> #VALUE! | L10: =SUMIF('[1]Total 2'!$I:$I,_xlfn.TEXTJOIN(" ",TRUE,'NEW ATD PER TEAM'!$D$9,'NEW ATD PER TEAM'!$D10),'[1]Total 2'!O:O) -> #VALUE! | M10: =IFERROR(L10/K10,0) -> 0 | N10: =J10*68/24 -> #VALUE! | O10: =SUMIF('[1]Total 2'!$I:$I,_xlfn.TEXTJOIN(" ",TRUE,'NEW ATD PER TEAM'!$D$9,'NEW ATD PER TEAM'!$D10),'[1]Total 2'!R:R) -> #VALUE! | P10: =IFERROR(O10/N10,0) -> 0 | Q10: =J10*68/24 -> #VALUE! | R10: =SUMIF('[1]Total 2'!$I:$I,_xlfn.TEXTJOIN(" ",TRUE,'NEW ATD PER TEAM'!$D$9,'NEW ATD PER TEAM'!$D10),'[1]Total 2'!U:U) -> #VALUE! | S10: =IFERROR(R10/Q10,0) -> 0 | T10: =J10*68/12 -> #VALUE! | U10: =SUMIF('[1]Total 2'!$I:$I,_xlfn.TEXTJOIN(" ",TRUE,'NEW ATD PER TEAM'!$D$9,'NEW ATD PER TEAM'!$D10),'[1]Total 2'!X:X) -> #VALUE! | V10: =IFERROR(U10/T10,0) -> 0 | W10: =J10*68/12 -> #VALUE! | X10: =SUMIF('[1]Total 2'!$I:$I,_xlfn.TEXTJOIN(" ",TRUE,'NEW ATD PER TEAM'!$D$9,'NEW ATD PER TEAM'!$D10),'[1]Total 2'!AA:AA) -> #VALUE! | Y10: =IFERROR(X10/W10,0) -> 0 | Z10: =SUMIF('[1]Total 2'!$I:$I,_xlfn.TEXTJOIN(" ",TRUE,'NEW ATD PER TEAM'!$D$9,'NEW ATD PER TEAM'!$D10),'[1]Total 2'!AC:AC) -> #VALUE! | AA10: =SUMIF('[1]Total 2'!$I:$I,_xlfn.TEXTJOIN(" ",TRUE,'NEW ATD PER TEAM'!$D$9,'NEW ATD PER TEAM'!$D10),'[1]Total 2'!AD:AD) -> #VALUE! | AB10: =SUMIF('[1]Total 2'!$I:$I,_xlfn.TEXTJOIN(" ",TRUE,'NEW ATD PER TEAM'!$D$9,'NEW ATD PER TEAM'!$D10),'[1]Total 2'!AE:AE) -> #VALUE! | AC10: =J10*1854*40 -> #VALUE! | AD10: =AA10 -> #VALUE! | AE10: =IFERROR(AD10/AC10,"")
B11: 2 | D11: Team 2 | E11: New Artisan Market | G11: 8 | H11: 4 | I11: =IFERROR(H11/G11,"") -> 0.5 | J11: =SUMIF('[1]Total 2'!$I:$I,_xlfn.TEXTJOIN(" ",TRUE,'NEW ATD PER TEAM'!$D$9,'NEW ATD PER TEAM'!$D11),'[1]Total 2'!L:L) -> #VALUE! | K11: =J11*68/40 -> #VALUE! | L11: =SUMIF('[1]Total 2'!$I:$I,_xlfn.TEXTJOIN(" ",TRUE,'NEW ATD PER TEAM'!$D$9,'NEW ATD PER TEAM'!$D11),'[1]Total 2'!O:O) -> #VALUE! | M11: =IFERROR(L11/K11,0) -> 0 | N11: =J11*68/24 -> #VALUE! | O11: =SUMIF('[1]Total 2'!$I:$I,_xlfn.TEXTJOIN(" ",TRUE,'NEW ATD PER TEAM'!$D$9,'NEW ATD PER TEAM'!$D11),'[1]Total 2'!R:R) -> #VALUE! | P11: =IFERROR(O11/N11,0) -> 0 | Q11: =J11*68/24 -> #VALUE! | R11: =SUMIF('[1]Total 2'!$I:$I,_xlfn.TEXTJOIN(" ",TRUE,'NEW ATD PER TEAM'!$D$9,'NEW ATD PER TEAM'!$D11),'[1]Total 2'!U:U) -> #VALUE! | S11: =IFERROR(R11/Q11,0) -> 0 | T11: =J11*68/12 -> #VALUE! | U11: =SUMIF('[1]Total 2'!$I:$I,_xlfn.TEXTJOIN(" ",TRUE,'NEW ATD PER TEAM'!$D$9,'NEW ATD PER TEAM'!$D11),'[1]Total 2'!X:X) -> #VALUE! | V11: =IFERROR(U11/T11,0) -> 0 | W11: =J11*68/12 -> #VALUE! | X11: =SUMIF('[1]Total 2'!$I:$I,_xlfn.TEXTJOIN(" ",TRUE,'NEW ATD PER TEAM'!$D$9,'NEW ATD PER TEAM'!$D11),'[1]Total 2'!AA:AA) -> #VALUE! | Y11: =IFERROR(X11/W11,0) -> 0 | Z11: =SUMIF('[1]Total 2'!$I:$I,_xlfn.TEXTJOIN(" ",TRUE,'NEW ATD PER TEAM'!$D$9,'NEW ATD PER TEAM'!$D11),'[1]Total 2'!AC:AC) -> #VALUE! | AA11: =SUMIF('[1]Total 2'!$I:$I,_xlfn.TEXTJOIN(" ",TRUE,'NEW ATD PER TEAM'!$D$9,'NEW ATD PER TEAM'!$D11),'[1]Total 2'!AD:AD) -> #VALUE! | AB11: =SUMIF('[1]Total 2'!$I:$I,_xlfn.TEXTJOIN(" ",TRUE,'NEW ATD PER TEAM'!$D$9,'NEW ATD PER TEAM'!$D11),'[1]Total 2'!AE:AE) -> #VALUE! | AC11: =J11*1854*40 -> #VALUE! | AD11: =AA11 -> #VALUE! | AE11: =IFERROR(AD11/AC11,"")
B12: 3 | D12: Team 3 | E12: Old Artisan Market | G12: 8 | H12: 3 | I12: =IFERROR(H12/G12,"") -> 0.375 | J12: =SUMIF('[1]Total 2'!$I:$I,_xlfn.TEXTJOIN(" ",TRUE,'NEW ATD PER TEAM'!$D$9,'NEW ATD PER TEAM'!$D12),'[1]Total 2'!L:L) -> #VALUE! | K12: =J12*68/40 -> #VALUE! | L12: =SUMIF('[1]Total 2'!$I:$I,_xlfn.TEXTJOIN(" ",TRUE,'NEW ATD PER TEAM'!$D$9,'NEW ATD PER TEAM'!$D12),'[1]Total 2'!O:O) -> #VALUE! | M12: =IFERROR(L12/K12,0) -> 0 | N12: =J12*68/24 -> #VALUE! | O12: =SUMIF('[1]Total 2'!$I:$I,_xlfn.TEXTJOIN(" ",TRUE,'NEW ATD PER TEAM'!$D$9,'NEW ATD PER TEAM'!$D12),'[1]Total 2'!R:R) -> #VALUE! | P12: =IFERROR(O12/N12,0) -> 0 | Q12: =J12*68/24 -> #VALUE! | R12: =SUMIF('[1]Total 2'!$I:$I,_xlfn.TEXTJOIN(" ",TRUE,'NEW ATD PER TEAM'!$D$9,'NEW ATD PER TEAM'!$D12),'[1]Total 2'!U:U) -> #VALUE! | S12: =IFERROR(R12/Q12,0) -> 0 | T12: =J12*68/12 -> #VALUE! | U12: =SUMIF('[1]Total 2'!$I:$I,_xlfn.TEXTJOIN(" ",TRUE,'NEW ATD PER TEAM'!$D$9,'NEW ATD PER TEAM'!$D12),'[1]Total 2'!X:X) -> #VALUE! | V12: =IFERROR(U12/T12,0) -> 0 | W12: =J12*68/12 -> #VALUE! | X12: =SUMIF('[1]Total 2'!$I:$I,_xlfn.TEXTJOIN(" ",TRUE,'NEW ATD PER TEAM'!$D$9,'NEW ATD PER TEAM'!$D12),'[1]Total 2'!AA:AA) -> #VALUE! | Y12: =IFERROR(X12/W12,0) -> 0 | Z12: =SUMIF('[1]Total 2'!$I:$I,_xlfn.TEXTJOIN(" ",TRUE,'NEW ATD PER TEAM'!$D$9,'NEW ATD PER TEAM'!$D12),'[1]Total 2'!AC:AC) -> #VALUE! | AA12: =SUMIF('[1]Total 2'!$I:$I,_xlfn.TEXTJOIN(" ",TRUE,'NEW ATD PER TEAM'!$D$9,'NEW ATD PER TEAM'!$D12),'[1]Total 2'!AD:AD) -> #VALUE! | AB12: =SUMIF('[1]Total 2'!$I:$I,_xlfn.TEXTJOIN(" ",TRUE,'NEW ATD PER TEAM'!$D$9,'NEW ATD PER TEAM'!$D12),'[1]Total 2'!AE:AE) -> #VALUE! | AC12: =J12*1854*40 -> #VALUE! | AD12: =AA12 -> #VALUE! | AE12: =IFERROR(AD12/AC12,"")
B13: 4 | D13: Team 4 | G13: 8 | I13: =IFERROR(H13/G13,"") -> 0 | J13: =SUMIF('[1]Total 2'!$I:$I,_xlfn.TEXTJOIN(" ",TRUE,'NEW ATD PER TEAM'!$D$9,'NEW ATD PER TEAM'!$D13),'[1]Total 2'!L:L) -> #VALUE! | K13: =J13*68/40 -> #VALUE! | L13: =SUMIF('[1]Total 2'!$I:$I,_xlfn.TEXTJOIN(" ",TRUE,'NEW ATD PER TEAM'!$D$9,'NEW ATD PER TEAM'!$D13),'[1]Total 2'!O:O) -> #VALUE! | M13: =IFERROR(L13/K13,0) -> 0 | N13: =J13*68/24 -> #VALUE! | O13: =SUMIF('[1]Total 2'!$I:$I,_xlfn.TEXTJOIN(" ",TRUE,'NEW ATD PER TEAM'!$D$9,'NEW ATD PER TEAM'!$D13),'[1]Total 2'!R:R) -> #VALUE! | P13: =IFERROR(O13/N13,0) -> 0 | Q13: =J13*68/24 -> #VALUE! | R13: =SUMIF('[1]Total 2'!$I:$I,_xlfn.TEXTJOIN(" ",TRUE,'NEW ATD PER TEAM'!$D$9,'NEW ATD PER TEAM'!$D13),'[1]Total 2'!U:U) -> #VALUE! | S13: =IFERROR(R13/Q13,0) -> 0 | T13: =J13*68/12 -> #VALUE! | U13: =SUMIF('[1]Total 2'!$I:$I,_xlfn.TEXTJOIN(" ",TRUE,'NEW ATD PER TEAM'!$D$9,'NEW ATD PER TEAM'!$D13),'[1]Total 2'!X:X) -> #VALUE! | V13: =IFERROR(U13/T13,0) -> 0 | W13: =J13*68/12 -> #VALUE! | X13: =SUMIF('[1]Total 2'!$I:$I,_xlfn.TEXTJOIN(" ",TRUE,'NEW ATD PER TEAM'!$D$9,'NEW ATD PER TEAM'!$D13),'[1]Total 2'!AA:AA) -> #VALUE! | Y13: =IFERROR(X13/W13,0) -> 0 | Z13: =SUMIF('[1]Total 2'!$I:$I,_xlfn.TEXTJOIN(" ",TRUE,'NEW ATD PER TEAM'!$D$9,'NEW ATD PER TEAM'!$D13),'[1]Total 2'!AC:AC) -> #VALUE! | AA13: =SUMIF('[1]Total 2'!$I:$I,_xlfn.TEXTJOIN(" ",TRUE,'NEW ATD PER TEAM'!$D$9,'NEW ATD PER TEAM'!$D13),'[1]Total 2'!AD:AD) -> #VALUE! | AB13: =SUMIF('[1]Total 2'!$I:$I,_xlfn.TEXTJOIN(" ",TRUE,'NEW ATD PER TEAM'!$D$9,'NEW ATD PER TEAM'!$D13),'[1]Total 2'!AE:AE) -> #VALUE! | AC13: =J13*1854*40 -> #VALUE! | AD13: =AA13 -> #VALUE! | AE13: =IFERROR(AD13/AC13,"")
E14: TOTAL | G14: =SUM(G10:G13) -> 32 | H14: =SUM(H10:H13) -> 14 | I14: =IFERROR(H14/G14,"") -> 0.4375 | J14: =SUM(J10:J13) -> #VALUE! | K14: =SUM(K10:K13) -> #VALUE! | L14: =SUM(L10:L13) -> #VALUE! | M14: =IFERROR(L14/K14,0) -> 0 | N14: =SUM(N10:N13) -> #VALUE! | O14: =SUM(O10:O13) -> #VALUE! | P14: =IFERROR(O14/N14,0) -> 0 | Q14: =SUM(Q10:Q13) -> #VALUE! | R14: =SUM(R10:R13) -> #VALUE! | S14: =IFERROR(R14/Q14,0) -> 0 | T14: =SUM(T10:T13) -> #VALUE! | U14: =SUM(U10:U13) -> #VALUE! | V14: =IFERROR(U14/T14,0) -> 0 | W14: =SUM(W10:W13) -> #VALUE! | X14: =SUM(X10:X13) -> #VALUE! | Y14: =IFERROR(X14/W14,0) -> 0 | Z14: =SUM(Z10:Z13) -> #VALUE! | AA14: =SUM(AA10:AA13) -> #VALUE! | AB14: =SUM(AB10:AB13) -> #VALUE! | AC14: =SUM(AC10:AC13) -> #VALUE! | AD14: =SUM(AD10:AD13) -> #VALUE! | AE14: =IFERROR(AD14/AC14,"")
D15: Abakaliki | F15: CHIMEZIE CHIKA
B16: 1 | D16: Team 1 | E16: Iboko | G16: 8 | H16: 5 | I16: =IFERROR(H16/G16,"") -> 0.625 | J16: =SUMIF('[1]Total 2'!$I:$I,_xlfn.TEXTJOIN(" ",TRUE,'NEW ATD PER TEAM'!$D$15,'NEW ATD PER TEAM'!$D16),'[1]Total 2'!L:L) -> #VALUE! | K16: =J16*68/40 -> #VALUE! | L16: =SUMIF('[1]Total 2'!$I:$I,_xlfn.TEXTJOIN(" ",TRUE,'NEW ATD PER TEAM'!$D$15,'NEW ATD PER TEAM'!$D16),'[1]Total 2'!O:O) -> #VALUE! | M16: =IFERROR(L16/K16,0) -> 0 | N16: =J16*68/24 -> #VALUE! | O16: =SUMIF('[1]Total 2'!$I:$I,_xlfn.TEXTJOIN(" ",TRUE,'NEW ATD PER TEAM'!$D$15,'NEW ATD PER TEAM'!$D16),'[1]Total 2'!R:R) -> #VALUE! | P16: =IFERROR(O16/N16,0) -> 0 | Q16: =J16*68/24 -> #VALUE! | R16: =SUMIF('[1]Total 2'!$I:$I,_xlfn.TEXTJOIN(" ",TRUE,'NEW ATD PER TEAM'!$D$15,'NEW ATD PER TEAM'!$D16),'[1]Total 2'!U:U) -> #VALUE! | S16: =IFERROR(R16/Q16,0) -> 0 | T16: =J16*68/12 -> #VALUE! | U16: =SUMIF('[1]Total 2'!$I:$I,_xlfn.TEXTJOIN(" ",TRUE,'NEW ATD PER TEAM'!$D$15,'NEW ATD PER TEAM'!$D16),'[1]Total 2'!X:X) -> #VALUE! | V16: =IFERROR(U16/T16,0) -> 0 | W16: =J16*68/12 -> #VALUE! | X16: =SUMIF('[1]Total 2'!$I:$I,_xlfn.TEXTJOIN(" ",TRUE,'NEW ATD PER TEAM'!$D$15,'NEW ATD PER TEAM'!$D16),'[1]Total 2'!AA:AA) -> #VALUE! | Y16: =IFERROR(X16/W16,0) -> 0 | Z16: =SUMIF('[1]Total 2'!$I:$I,_xlfn.TEXTJOIN(" ",TRUE,'NEW ATD PER TEAM'!$D$15,'NEW ATD PER TEAM'!$D16),'[1]Total 2'!AC:AC) -> #VALUE! | AA16: =SUMIF('[1]Total 2'!$I:$I,_xlfn.TEXTJOIN(" ",TRUE,'NEW ATD PER TEAM'!$D$15,'NEW ATD PER TEAM'!$D16),'[1]Total 2'!AD:AD) -> #VALUE! | AC16: =J16*1854*40 -> #VALUE! | AD16: =AA16 -> #VALUE! | AE16: =IFERROR(AD16/AC16,"")
B17: 2 | D17: Team 2 | E17: Ahia Ofu | G17: 8 | H17: 5 | I17: =IFERROR(H17/G17,"") -> 0.625 | J17: =SUMIF('[1]Total 2'!$I:$I,_xlfn.TEXTJOIN(" ",TRUE,'NEW ATD PER TEAM'!$D$15,'NEW ATD PER TEAM'!$D17),'[1]Total 2'!L:L) -> #VALUE! | K17: =J17*68/40 -> #VALUE! | L17: =SUMIF('[1]Total 2'!$I:$I,_xlfn.TEXTJOIN(" ",TRUE,'NEW ATD PER TEAM'!$D$15,'NEW ATD PER TEAM'!$D17),'[1]Total 2'!O:O) -> #VALUE! | M17: =IFERROR(L17/K17,0) -> 0 | N17: =J17*68/24 -> #VALUE! | O17: =SUMIF('[1]Total 2'!$I:$I,_xlfn.TEXTJOIN(" ",TRUE,'NEW ATD PER TEAM'!$D$15,'NEW ATD PER TEAM'!$D17),'[1]Total 2'!R:R) -> #VALUE! | P17: =IFERROR(O17/N17,0) -> 0 | Q17: =J17*68/24 -> #VALUE! | R17: =SUMIF('[1]Total 2'!$I:$I,_xlfn.TEXTJOIN(" ",TRUE,'NEW ATD PER TEAM'!$D$15,'NEW ATD PER TEAM'!$D17),'[1]Total 2'!U:U) -> #VALUE! | S17: =IFERROR(R17/Q17,0) -> 0 | T17: =J17*68/12 -> #VALUE! | U17: =SUMIF('[1]Total 2'!$I:$I,_xlfn.TEXTJOIN(" ",TRUE,'NEW ATD PER TEAM'!$D$15,'NEW ATD PER TEAM'!$D17),'[1]Total 2'!X:X) -> #VALUE! | V17: =IFERROR(U17/T17,0) -> 0 | W17: =J17*68/12 -> #VALUE! | X17: =SUMIF('[1]Total 2'!$I:$I,_xlfn.TEXTJOIN(" ",TRUE,'NEW ATD PER TEAM'!$D$15,'NEW ATD PER TEAM'!$D17),'[1]Total 2'!AA:AA) -> #VALUE! | Y17: =IFERROR(X17/W17,0) -> 0 | Z17: =SUMIF('[1]Total 2'!$I:$I,_xlfn.TEXTJOIN(" ",TRUE,'NEW ATD PER TEAM'!$D$15,'NEW ATD PER TEAM'!$D17),'[1]Total 2'!AC:AC) -> #VALUE! | AA17: =SUMIF('[1]Total 2'!$I:$I,_xlfn.TEXTJOIN(" ",TRUE,'NEW ATD PER TEAM'!$D$15,'NEW ATD PER TEAM'!$D17),'[1]Total 2'!AD:AD) -> #VALUE! | AC17: =J17*1854*40 -> #VALUE! | AD17: =AA17 -> #VALUE! | AE17: =IFERROR(AD17/AC17,"")
B18: 3 | D18: Team 3 | G18: 8 | I18: =IFERROR(H18/G18,"") -> 0 | J18: =SUMIF('[1]Total 2'!$I:$I,_xlfn.TEXTJOIN(" ",TRUE,'NEW ATD PER TEAM'!$D$15,'NEW ATD PER TEAM'!$D18),'[1]Total 2'!L:L) -> #VALUE! | K18: =J18*68/40 -> #VALUE! | L18: =SUMIF('[1]Total 2'!$I:$I,_xlfn.TEXTJOIN(" ",TRUE,'NEW ATD PER TEAM'!$D$15,'NEW ATD PER TEAM'!$D18),'[1]Total 2'!O:O) -> #VALUE! | M18: =IFERROR(L18/K18,0) -> 0 | N18: =J18*68/24 -> #VALUE! | O18: =SUMIF('[1]Total 2'!$I:$I,_xlfn.TEXTJOIN(" ",TRUE,'NEW ATD PER TEAM'!$D$15,'NEW ATD PER TEAM'!$D18),'[1]Total 2'!R:R) -> #VALUE! | P18: =IFERROR(O18/N18,0) -> 0 | Q18: =J18*68/24 -> #VALUE! | R18: =SUMIF('[1]Total 2'!$I:$I,_xlfn.TEXTJOIN(" ",TRUE,'NEW ATD PER TEAM'!$D$15,'NEW ATD PER TEAM'!$D18),'[1]Total 2'!U:U) -> #VALUE! | S18: =IFERROR(R18/Q18,0) -> 0 | T18: =J18*68/12 -> #VALUE! | U18: =SUMIF('[1]Total 2'!$I:$I,_xlfn.TEXTJOIN(" ",TRUE,'NEW ATD PER TEAM'!$D$15,'NEW ATD PER TEAM'!$D18),'[1]Total 2'!X:X) -> #VALUE! | V18: =IFERROR(U18/T18,0) -> 0 | W18: =J18*68/12 -> #VALUE! | X18: =SUMIF('[1]Total 2'!$I:$I,_xlfn.TEXTJOIN(" ",TRUE,'NEW ATD PER TEAM'!$D$15,'NEW ATD PER TEAM'!$D18),'[1]Total 2'!AA:AA) -> #VALUE! | Y18: =IFERROR(X18/W18,0) -> 0 | Z18: =SUMIF('[1]Total 2'!$I:$I,_xlfn.TEXTJOIN(" ",TRUE,'NEW ATD PER TEAM'!$D$15,'NEW ATD PER TEAM'!$D18),'[1]Total 2'!AC:AC) -> #VALUE! | AA18: =SUMIF('[1]Total 2'!$I:$I,_xlfn.TEXTJOIN(" ",TRUE,'NEW ATD PER TEAM'!$D$15,'NEW ATD PER TEAM'!$D18),'[1]Total 2'!AD:AD) -> #VALUE! | AC18: =J18*1854*40 -> #VALUE! | AD18: =AA18 -> #VALUE! | AE18: =IFERROR(AD18/AC18,"")
B19: 4 | D19: Team 4 | G19: 8 | I19: =IFERROR(H19/G19,"") -> 0 | J19: =SUMIF('[1]Total 2'!$I:$I,_xlfn.TEXTJOIN(" ",TRUE,'NEW ATD PER TEAM'!$D$15,'NEW ATD PER TEAM'!$D19),'[1]Total 2'!L:L) -> #VALUE! | K19: =J19*68/40 -> #VALUE! | L19: =SUMIF('[1]Total 2'!$I:$I,_xlfn.TEXTJOIN(" ",TRUE,'NEW ATD PER TEAM'!$D$15,'NEW ATD PER TEAM'!$D19),'[1]Total 2'!O:O) -> #VALUE! | M19: =IFERROR(L19/K19,0) -> 0 | N19: =J19*68/24 -> #VALUE! | O19: =SUMIF('[1]Total 2'!$I:$I,_xlfn.TEXTJOIN(" ",TRUE,'NEW ATD PER TEAM'!$D$15,'NEW ATD PER TEAM'!$D19),'[1]Total 2'!R:R) -> #VALUE! | P19: =IFERROR(O19/N19,0) -> 0 | Q19: =J19*68/24 -> #VALUE! | R19: =SUMIF('[1]Total 2'!$I:$I,_xlfn.TEXTJOIN(" ",TRUE,'NEW ATD PER TEAM'!$D$15,'NEW ATD PER TEAM'!$D19),'[1]Total 2'!U:U) -> #VALUE! | S19: =IFERROR(R19/Q19,0) -> 0 | T19: =J19*68/12 -> #VALUE! | U19: =SUMIF('[1]Total 2'!$I:$I,_xlfn.TEXTJOIN(" ",TRUE,'NEW ATD PER TEAM'!$D$15,'NEW ATD PER TEAM'!$D19),'[1]Total 2'!X:X) -> #VALUE! | V19: =IFERROR(U19/T19,0) -> 0 | W19: =J19*68/12 -> #VALUE! | X19: =SUMIF('[1]Total 2'!$I:$I,_xlfn.TEXTJOIN(" ",TRUE,'NEW ATD PER TEAM'!$D$15,'NEW ATD PER TEAM'!$D19),'[1]Total 2'!AA:AA) -> #VALUE! | Y19: =IFERROR(X19/W19,0) -> 0 | Z19: =SUMIF('[1]Total 2'!$I:$I,_xlfn.TEXTJOIN(" ",TRUE,'NEW ATD PER TEAM'!$D$15,'NEW ATD PER TEAM'!$D19),'[1]Total 2'!AC:AC) -> #VALUE! | AA19: =SUMIF('[1]Total 2'!$I:$I,_xlfn.TEXTJOIN(" ",TRUE,'NEW ATD PER TEAM'!$D$15,'NEW ATD PER TEAM'!$D19),'[1]Total 2'!AD:AD) -> #VALUE! | AC19: =J19*1854*40 -> #VALUE! | AD19: =AA19 -> #VALUE! | AE19: =IFERROR(AD19/AC19,"")
E20: TOTAL | G20: =SUM(G16:G19) -> 32 | H20: =SUM(H16:H19) -> 10 | I20: =IFERROR(H20/G20,"") -> 0.3125 | J20: =SUM(J16:J19) -> #VALUE! | K20: =SUM(K16:K19) -> #VALUE! | L20: =SUM(L16:L19) -> #VALUE! | M20: =IFERROR(L20/K20,0) -> 0 | N20: =SUM(N16:N19) -> #VALUE! | O20: =SUM(O16:O19) -> #VALUE! | P20: =IFERROR(O20/N20,0) -> 0 | Q20: =SUM(Q16:Q19) -> #VALUE! | R20: =SUM(R16:R19) -> #VALUE! | S20: =IFERROR(R20/Q20,0) -> 0 | T20: =SUM(T16:T19) -> #VALUE! | U20: =SUM(U16:U19) -> #VALUE! | V20: =IFERROR(U20/T20,0) -> 0 | W20: =SUM(W16:W19) -> #VALUE! | X20: =SUM(X16:X19) -> #VALUE! | Y20: =IFERROR(X20/W20,0) -> 0 | Z20: =SUM(Z16:Z19) -> #VALUE! | AA20: =SUM(AA16:AA19) -> #VALUE! | AB20: =SUM(AB16:AB19) -> 0 | AC20: =SUM(AC16:AC19) -> #VALUE! | AD20: =SUM(AD16:AD19) -> #VALUE! | AE20: =IFERROR(AD20/AC20,"")
D21: Onitsha | F21: SHANTEL MMESOMACHUKWU
B22: 1 | D22: Team 1 | G22: 8 | I22: =IFERROR(H22/G22,"") -> 0 | J22: =SUMIF('[1]Total 2'!$I:$I,_xlfn.TEXTJOIN(" ",TRUE,'NEW ATD PER TEAM'!$D$21,'NEW ATD PER TEAM'!$D22),'[1]Total 2'!L:L) -> #VALUE! | K22: =J22*68/40 -> #VALUE! | L22: =SUMIF('[1]Total 2'!$I:$I,_xlfn.TEXTJOIN(" ",TRUE,'NEW ATD PER TEAM'!$D$21,'NEW ATD PER TEAM'!$D22),'[1]Total 2'!O:O) -> #VALUE! | M22: =IFERROR(L22/K22,0) -> 0 | N22: =J22*68/24 -> #VALUE! | O22: =SUMIF('[1]Total 2'!$I:$I,_xlfn.TEXTJOIN(" ",TRUE,'NEW ATD PER TEAM'!$D$21,'NEW ATD PER TEAM'!$D22),'[1]Total 2'!R:R) -> #VALUE! | P22: =IFERROR(O22/N22,0) -> 0 | Q22: =J22*68/24 -> #VALUE! | R22: =SUMIF('[1]Total 2'!$I:$I,_xlfn.TEXTJOIN(" ",TRUE,'NEW ATD PER TEAM'!$D$21,'NEW ATD PER TEAM'!$D22),'[1]Total 2'!U:U) -> #VALUE! | S22: =IFERROR(R22/Q22,0) -> 0 | T22: =J22*68/12 -> #VALUE! | U22: =SUMIF('[1]Total 2'!$I:$I,_xlfn.TEXTJOIN(" ",TRUE,'NEW ATD PER TEAM'!$D$21,'NEW ATD PER TEAM'!$D22),'[1]Total 2'!X:X) -> #VALUE! | V22: =IFERROR(U22/T22,0) -> 0 | W22: =J22*68/12 -> #VALUE! | X22: =SUMIF('[1]Total 2'!$I:$I,_xlfn.TEXTJOIN(" ",TRUE,'NEW ATD PER TEAM'!$D$21,'NEW ATD PER TEAM'!$D22),'[1]Total 2'!AA:AA) -> #VALUE! | Y22: =IFERROR(X22/W22,0) -> 0 | Z22: =SUMIF('[1]Total 2'!$I:$I,_xlfn.TEXTJOIN(" ",TRUE,'NEW ATD PER TEAM'!$D$21,'NEW ATD PER TEAM'!$D22),'[1]Total 2'!AC:AC) -> #VALUE! | AA22: =SUMIF('[1]Total 2'!$I:$I,_xlfn.TEXTJOIN(" ",TRUE,'NEW ATD PER TEAM'!$D$21,'NEW ATD PER TEAM'!$D22),'[1]Total 2'!AD:AD) -> #VALUE! | AC22: =J22*1854*40 -> #VALUE! | AD22: =AA22 -> #VALUE! | AE22: =IFERROR(AD22/AC22,"")
B23: 2 | D23: Team 2 | G23: 8 | I23: =IFERROR(H23/G23,"") -> 0 | J23: =SUMIF('[1]Total 2'!$I:$I,_xlfn.TEXTJOIN(" ",TRUE,'NEW ATD PER TEAM'!$D$21,'NEW ATD PER TEAM'!$D23),'[1]Total 2'!L:L) -> #VALUE! | K23: =J23*68/40 -> #VALUE! | L23: =SUMIF('[1]Total 2'!$I:$I,_xlfn.TEXTJOIN(" ",TRUE,'NEW ATD PER TEAM'!$D$21,'NEW ATD PER TEAM'!$D23),'[1]Total 2'!O:O) -> #VALUE! | M23: =IFERROR(L23/K23,0) -> 0 | N23: =J23*68/24 -> #VALUE! | O23: =SUMIF('[1]Total 2'!$I:$I,_xlfn.TEXTJOIN(" ",TRUE,'NEW ATD PER TEAM'!$D$21,'NEW ATD PER TEAM'!$D23),'[1]Total 2'!R:R) -> #VALUE! | P23: =IFERROR(O23/N23,0) -> 0 | Q23: =J23*68/24 -> #VALUE! | R23: =SUMIF('[1]Total 2'!$I:$I,_xlfn.TEXTJOIN(" ",TRUE,'NEW ATD PER TEAM'!$D$21,'NEW ATD PER TEAM'!$D23),'[1]Total 2'!U:U) -> #VALUE! | S23: =IFERROR(R23/Q23,0) -> 0 | T23: =J23*68/12 -> #VALUE! | U23: =SUMIF('[1]Total 2'!$I:$I,_xlfn.TEXTJOIN(" ",TRUE,'NEW ATD PER TEAM'!$D$21,'NEW ATD PER TEAM'!$D23),'[1]Total 2'!X:X) -> #VALUE! | V23: =IFERROR(U23/T23,0) -> 0 | W23: =J23*68/12 -> #VALUE! | X23: =SUMIF('[1]Total 2'!$I:$I,_xlfn.TEXTJOIN(" ",TRUE,'NEW ATD PER TEAM'!$D$21,'NEW ATD PER TEAM'!$D23),'[1]Total 2'!AA:AA) -> #VALUE! | Y23: =IFERROR(X23/W23,0) -> 0 | Z23: =SUMIF('[1]Total 2'!$I:$I,_xlfn.TEXTJOIN(" ",TRUE,'NEW ATD PER TEAM'!$D$21,'NEW ATD PER TEAM'!$D23),'[1]Total 2'!AC:AC) -> #VALUE! | AA23: =SUMIF('[1]Total 2'!$I:$I,_xlfn.TEXTJOIN(" ",TRUE,'NEW ATD PER TEAM'!$D$21,'NEW ATD PER TEAM'!$D23),'[1]Total 2'!AD:AD) -> #VALUE! | AC23: =J23*1854*40 -> #VALUE! | AD23: =AA23 -> #VALUE! | AE23: =IFERROR(AD23/AC23,"")
B24: 3 | D24: Team 3 | G24: 8 | I24: =IFERROR(H24/G24,"") -> 0 | J24: =SUMIF('[1]Total 2'!$I:$I,_xlfn.TEXTJOIN(" ",TRUE,'NEW ATD PER TEAM'!$D$21,'NEW ATD PER TEAM'!$D24),'[1]Total 2'!L:L) -> #VALUE! | K24: =J24*68/40 -> #VALUE! | L24: =SUMIF('[1]Total 2'!$I:$I,_xlfn.TEXTJOIN(" ",TRUE,'NEW ATD PER TEAM'!$D$21,'NEW ATD PER TEAM'!$D24),'[1]Total 2'!O:O) -> #VALUE! | M24: =IFERROR(L24/K24,0) -> 0 | N24: =J24*68/24 -> #VALUE! | O24: =SUMIF('[1]Total 2'!$I:$I,_xlfn.TEXTJOIN(" ",TRUE,'NEW ATD PER TEAM'!$D$21,'NEW ATD PER TEAM'!$D24),'[1]Total 2'!R:R) -> #VALUE! | P24: =IFERROR(O24/N24,0) -> 0 | Q24: =J24*68/24 -> #VALUE! | R24: =SUMIF('[1]Total 2'!$I:$I,_xlfn.TEXTJOIN(" ",TRUE,'NEW ATD PER TEAM'!$D$21,'NEW ATD PER TEAM'!$D24),'[1]Total 2'!U:U) -> #VALUE! | S24: =IFERROR(R24/Q24,0) -> 0 | T24: =J24*68/12 -> #VALUE! | U24: =SUMIF('[1]Total 2'!$I:$I,_xlfn.TEXTJOIN(" ",TRUE,'NEW ATD PER TEAM'!$D$21,'NEW ATD PER TEAM'!$D24),'[1]Total 2'!X:X) -> #VALUE! | V24: =IFERROR(U24/T24,0) -> 0 | W24: =J24*68/12 -> #VALUE! | X24: =SUMIF('[1]Total 2'!$I:$I,_xlfn.TEXTJOIN(" ",TRUE,'NEW ATD PER TEAM'!$D$21,'NEW ATD PER TEAM'!$D24),'[1]Total 2'!AA:AA) -> #VALUE! | Y24: =IFERROR(X24/W24,0) -> 0 | Z24: =SUMIF('[1]Total 2'!$I:$I,_xlfn.TEXTJOIN(" ",TRUE,'NEW ATD PER TEAM'!$D$21,'NEW ATD PER TEAM'!$D24),'[1]Total 2'!AC:AC) -> #VALUE! | AA24: =SUMIF('[1]Total 2'!$I:$I,_xlfn.TEXTJOIN(" ",TRUE,'NEW ATD PER TEAM'!$D$21,'NEW ATD PER TEAM'!$D24),'[1]Total 2'!AD:AD) -> #VALUE! | AC24: =J24*1854*40 -> #VALUE! | AD24: =AA24 -> #VALUE! | AE24: =IFERROR(AD24/AC24,"")
B25: 4 | D25: Team 4 | G25: 8 | I25: =IFERROR(H25/G25,"") -> 0 | J25: =SUMIF('[1]Total 2'!$I:$I,_xlfn.TEXTJOIN(" ",TRUE,'NEW ATD PER TEAM'!$D$21,'NEW ATD PER TEAM'!$D25),'[1]Total 2'!L:L) -> #VALUE! | K25: =J25*68/40 -> #VALUE! | L25: =SUMIF('[1]Total 2'!$I:$I,_xlfn.TEXTJOIN(" ",TRUE,'NEW ATD PER TEAM'!$D$21,'NEW ATD PER TEAM'!$D25),'[1]Total 2'!O:O) -> #VALUE! | M25: =IFERROR(L25/K25,0) -> 0 | N25: =J25*68/24 -> #VALUE! | O25: =SUMIF('[1]Total 2'!$I:$I,_xlfn.TEXTJOIN(" ",TRUE,'NEW ATD PER TEAM'!$D$21,'NEW ATD PER TEAM'!$D25),'[1]Total 2'!R:R) -> #VALUE! | P25: =IFERROR(O25/N25,0) -> 0 | Q25: =J25*68/24 -> #VALUE! | R25: =SUMIF('[1]Total 2'!$I:$I,_xlfn.TEXTJOIN(" ",TRUE,'NEW ATD PER TEAM'!$D$21,'NEW ATD PER TEAM'!$D25),'[1]Total 2'!U:U) -> #VALUE! | S25: =IFERROR(R25/Q25,0) -> 0 | T25: =J25*68/12 -> #VALUE! | U25: =SUMIF('[1]Total 2'!$I:$I,_xlfn.TEXTJOIN(" ",TRUE,'NEW ATD PER TEAM'!$D$21,'NEW ATD PER TEAM'!$D25),'[1]Total 2'!X:X) -> #VALUE! | V25: =IFERROR(U25/T25,0) -> 0 | W25: =J25*68/12 -> #VALUE! | X25: =SUMIF('[1]Total 2'!$I:$I,_xlfn.TEXTJOIN(" ",TRUE,'NEW ATD PER TEAM'!$D$21,'NEW ATD PER TEAM'!$D25),'[1]Total 2'!AA:AA) -> #VALUE! | Y25: =IFERROR(X25/W25,0) -> 0 | Z25: =SUMIF('[1]Total 2'!$I:$I,_xlfn.TEXTJOIN(" ",TRUE,'NEW ATD PER TEAM'!$D$21,'NEW ATD PER TEAM'!$D25),'[1]Total 2'!AC:AC) -> #VALUE! | AA25: =SUMIF('[1]Total 2'!$I:$I,_xlfn.TEXTJOIN(" ",TRUE,'NEW ATD PER TEAM'!$D$21,'NEW ATD PER TEAM'!$D25),'[1]Total 2'!AD:AD) -> #VALUE! | AC25: =J25*1854*40 -> #VALUE! | AD25: =AA25 -> #VALUE! | AE25: =IFERROR(AD25/AC25,"")
E26: TOTAL | G26: =SUM(G22:G25) -> 32 | I26: =IFERROR(H26/G26,"") -> 0 | J26: =SUM(J22:J25) -> #VALUE! | K26: =SUM(K22:K25) -> #VALUE! | L26: =SUM(L22:L25) -> #VALUE! | M26: =IFERROR(L26/K26,0) -> 0 | N26: =SUM(N22:N25) -> #VALUE! | O26: =SUM(O22:O25) -> #VALUE! | P26: =IFERROR(O26/N26,0) -> 0 | Q26: =SUM(Q22:Q25) -> #VALUE! | R26: =SUM(R22:R25) -> #VALUE! | S26: =IFERROR(R26/Q26,0) -> 0 | T26: =SUM(T22:T25) -> #VALUE! | U26: =SUM(U22:U25) -> #VALUE! | V26: =IFERROR(U26/T26,0) -> 0 | W26: =SUM(W22:W25) -> #VALUE! | X26: =SUM(X22:X25) -> #VALUE! | Y26: =IFERROR(X26/W26,0) -> 0 | Z26: =SUM(Z22:Z25) -> #VALUE! | AA26: =SUM(AA22:AA25) -> #VALUE! | AB26: =SUM(AB22:AB25) -> 0 | AC26: =SUM(AC22:AC25) -> #VALUE! | AD26: =SUM(AD22:AD25) -> #VALUE! | AE26: =IFERROR(AD26/AC26,"")
D27: ASABA | F27: AYEGBUSI CHRISTIANA
B28: 1 | D28: Team 1 | E28: Asaba/Infant Jesus | G28: 8 | H28: 7 | I28: =IFERROR(H28/G28,"") -> 0.875 | J28: =SUMIF('[1]Total 2'!$I:$I,_xlfn.TEXTJOIN(" ",TRUE,'NEW ATD PER TEAM'!$D$27,'NEW ATD PER TEAM'!$D28),'[1]Total 2'!L:L) -> #VALUE! | K28: =J28*68/40 -> #VALUE! | L28: =SUMIF('[1]Total 2'!$I:$I,_xlfn.TEXTJOIN(" ",TRUE,'NEW ATD PER TEAM'!$D$27,'NEW ATD PER TEAM'!$D28),'[1]Total 2'!O:O) -> #VALUE! | M28: =IFERROR(L28/K28,0) -> 0 | N28: =J28*68/24 -> #VALUE! | O28: =SUMIF('[1]Total 2'!$I:$I,_xlfn.TEXTJOIN(" ",TRUE,'NEW ATD PER TEAM'!$D$27,'NEW ATD PER TEAM'!$D28),'[1]Total 2'!R:R) -> #VALUE! | P28: =IFERROR(O28/N28,0) -> 0 | Q28: =J28*68/24 -> #VALUE! | R28: =SUMIF('[1]Total 2'!$I:$I,_xlfn.TEXTJOIN(" ",TRUE,'NEW ATD PER TEAM'!$D$27,'NEW ATD PER TEAM'!$D28),'[1]Total 2'!U:U) -> #VALUE! | S28: =IFERROR(R28/Q28,0) -> 0 | T28: =J28*68/12 -> #VALUE! | U28: =SUMIF('[1]Total 2'!$I:$I,_xlfn.TEXTJOIN(" ",TRUE,'NEW ATD PER TEAM'!$D$27,'NEW ATD PER TEAM'!$D28),'[1]Total 2'!X:X) -> #VALUE! | V28: =IFERROR(U28/T28,0) -> 0 | W28: =J28*68/12 -> #VALUE! | X28: =SUMIF('[1]Total 2'!$I:$I,_xlfn.TEXTJOIN(" ",TRUE,'NEW ATD PER TEAM'!$D$27,'NEW ATD PER TEAM'!$D28),'[1]Total 2'!AA:AA) -> #VALUE! | Y28: =IFERROR(X28/W28,0) -> 0 | Z28: =SUMIF('[1]Total 2'!$I:$I,_xlfn.TEXTJOIN(" ",TRUE,'NEW ATD PER TEAM'!$D$27,'NEW ATD PER TEAM'!$D28),'[1]Total 2'!AC:AC) -> #VALUE! | AA28: =SUMIF('[1]Total 2'!$I:$I,_xlfn.TEXTJOIN(" ",TRUE,'NEW ATD PER TEAM'!$D$27,'NEW ATD PER TEAM'!$D28),'[1]Total 2'!AD:AD) -> #VALUE! | AC28: =J28*1854*40 -> #VALUE! | AD28: =AA28 -> #VALUE! | AE28: =IFERROR(AD28/AC28,"")
B29: 2 | D29: Team 2 | G29: 8 | I29: =IFERROR(H29/G29,"") -> 0 | J29: =SUMIF('[1]Total 2'!$I:$I,_xlfn.TEXTJOIN(" ",TRUE,'NEW ATD PER TEAM'!$D$27,'NEW ATD PER TEAM'!$D29),'[1]Total 2'!L:L) -> #VALUE! | K29: =J29*68/40 -> #VALUE! | L29: =SUMIF('[1]Total 2'!$I:$I,_xlfn.TEXTJOIN(" ",TRUE,'NEW ATD PER TEAM'!$D$27,'NEW ATD PER TEAM'!$D29),'[1]Total 2'!O:O) -> #VALUE! | M29: =IFERROR(L29/K29,0) -> 0 | N29: =J29*68/24 -> #VALUE! | O29: =SUMIF('[1]Total 2'!$I:$I,_xlfn.TEXTJOIN(" ",TRUE,'NEW ATD PER TEAM'!$D$27,'NEW ATD PER TEAM'!$D29),'[1]Total 2'!R:R) -> #VALUE! | P29: =IFERROR(O29/N29,0) -> 0 | Q29: =J29*68/24 -> #VALUE! | R29: =SUMIF('[1]Total 2'!$I:$I,_xlfn.TEXTJOIN(" ",TRUE,'NEW ATD PER TEAM'!$D$27,'NEW ATD PER TEAM'!$D29),'[1]Total 2'!U:U) -> #VALUE! | S29: =IFERROR(R29/Q29,0) -> 0 | T29: =J29*68/12 -> #VALUE! | U29: =SUMIF('[1]Total 2'!$I:$I,_xlfn.TEXTJOIN(" ",TRUE,'NEW ATD PER TEAM'!$D$27,'NEW ATD PER TEAM'!$D29),'[1]Total 2'!X:X) -> #VALUE! | V29: =IFERROR(U29/T29,0) -> 0 | W29: =J29*68/12 -> #VALUE! | X29: =SUMIF('[1]Total 2'!$I:$I,_xlfn.TEXTJOIN(" ",TRUE,'NEW ATD PER TEAM'!$D$27,'NEW ATD PER TEAM'!$D29),'[1]Total 2'!AA:AA) -> #VALUE! | Y29: =IFERROR(X29/W29,0) -> 0 | Z29: =SUMIF('[1]Total 2'!$I:$I,_xlfn.TEXTJOIN(" ",TRUE,'NEW ATD PER TEAM'!$D$27,'NEW ATD PER TEAM'!$D29),'[1]Total 2'!AC:AC) -> #VALUE! | AA29: =SUMIF('[1]Total 2'!$I:$I,_xlfn.TEXTJOIN(" ",TRUE,'NEW ATD PER TEAM'!$D$27,'NEW ATD PER TEAM'!$D29),'[1]Total 2'!AD:AD) -> #VALUE! | AC29: =J29*1854*40 -> #VALUE! | AD29: =AA29 -> #VALUE! | AE29: =IFERROR(AD29/AC29,"")
B30: 3 | D30: Team 3 | G30: 8 | I30: =IFERROR(H30/G30,"") -> 0 | J30: =SUMIF('[1]Total 2'!$I:$I,_xlfn.TEXTJOIN(" ",TRUE,'NEW ATD PER TEAM'!$D$27,'NEW ATD PER TEAM'!$D30),'[1]Total 2'!L:L) -> #VALUE! | K30: =J30*68/40 -> #VALUE! | L30: =SUMIF('[1]Total 2'!$I:$I,_xlfn.TEXTJOIN(" ",TRUE,'NEW ATD PER TEAM'!$D$27,'NEW ATD PER TEAM'!$D30),'[1]Total 2'!O:O) -> #VALUE! | M30: =IFERROR(L30/K30,0) -> 0 | N30: =J30*68/24 -> #VALUE! | O30: =SUMIF('[1]Total 2'!$I:$I,_xlfn.TEXTJOIN(" ",TRUE,'NEW ATD PER TEAM'!$D$27,'NEW ATD PER TEAM'!$D30),'[1]Total 2'!R:R) -> #VALUE! | P30: =IFERROR(O30/N30,0) -> 0 | Q30: =J30*68/24 -> #VALUE! | R30: =SUMIF('[1]Total 2'!$I:$I,_xlfn.TEXTJOIN(" ",TRUE,'NEW ATD PER TEAM'!$D$27,'NEW ATD PER TEAM'!$D30),'[1]Total 2'!U:U) -> #VALUE! | S30: =IFERROR(R30/Q30,0) -> 0 | T30: =J30*68/12 -> #VALUE! | U30: =SUMIF('[1]Total 2'!$I:$I,_xlfn.TEXTJOIN(" ",TRUE,'NEW ATD PER TEAM'!$D$27,'NEW ATD PER TEAM'!$D30),'[1]Total 2'!X:X) -> #VALUE! | V30: =IFERROR(U30/T30,0) -> 0 | W30: =J30*68/12 -> #VALUE! | X30: =SUMIF('[1]Total 2'!$I:$I,_xlfn.TEXTJOIN(" ",TRUE,'NEW ATD PER TEAM'!$D$27,'NEW ATD PER TEAM'!$D30),'[1]Total 2'!AA:AA) -> #VALUE! | Y30: =IFERROR(X30/W30,0) -> 0 | Z30: =SUMIF('[1]Total 2'!$I:$I,_xlfn.TEXTJOIN(" ",TRUE,'NEW ATD PER TEAM'!$D$27,'NEW ATD PER TEAM'!$D30),'[1]Total 2'!AC:AC) -> #VALUE! | AA30: =SUMIF('[1]Total 2'!$I:$I,_xlfn.TEXTJOIN(" ",TRUE,'NEW ATD PER TEAM'!$D$27,'NEW ATD PER TEAM'!$D30),'[1]Total 2'!AD:AD) -> #VALUE! | AC30: =J30*1854*40 -> #VALUE! | AD30: =AA30 -> #VALUE! | AE30: =IFERROR(AD30/AC30,"")
B31: 4 | D31: Team 4 | G31: 8 | I31: =IFERROR(H31/G31,"") -> 0 | J31: =SUMIF('[1]Total 2'!$I:$I,_xlfn.TEXTJOIN(" ",TRUE,'NEW ATD PER TEAM'!$D$27,'NEW ATD PER TEAM'!$D31),'[1]Total 2'!L:L) -> #VALUE! | K31: =J31*68/40 -> #VALUE! | L31: =SUMIF('[1]Total 2'!$I:$I,_xlfn.TEXTJOIN(" ",TRUE,'NEW ATD PER TEAM'!$D$27,'NEW ATD PER TEAM'!$D31),'[1]Total 2'!O:O) -> #VALUE! | M31: =IFERROR(L31/K31,0) -> 0 | N31: =J31*68/24 -> #VALUE! | O31: =SUMIF('[1]Total 2'!$I:$I,_xlfn.TEXTJOIN(" ",TRUE,'NEW ATD PER TEAM'!$D$27,'NEW ATD PER TEAM'!$D31),'[1]Total 2'!R:R) -> #VALUE! | P31: =IFERROR(O31/N31,0) -> 0 | Q31: =J31*68/24 -> #VALUE! | R31: =SUMIF('[1]Total 2'!$I:$I,_xlfn.TEXTJOIN(" ",TRUE,'NEW ATD PER TEAM'!$D$27,'NEW ATD PER TEAM'!$D31),'[1]Total 2'!U:U) -> #VALUE! | S31: =IFERROR(R31/Q31,0) -> 0 | T31: =J31*68/12 -> #VALUE! | U31: =SUMIF('[1]Total 2'!$I:$I,_xlfn.TEXTJOIN(" ",TRUE,'NEW ATD PER TEAM'!$D$27,'NEW ATD PER TEAM'!$D31),'[1]Total 2'!X:X) -> #VALUE! | V31: =IFERROR(U31/T31,0) -> 0 | W31: =J31*68/12 -> #VALUE! | X31: =SUMIF('[1]Total 2'!$I:$I,_xlfn.TEXTJOIN(" ",TRUE,'NEW ATD PER TEAM'!$D$27,'NEW ATD PER TEAM'!$D31),'[1]Total 2'!AA:AA) -> #VALUE! | Y31: =IFERROR(X31/W31,0) -> 0 | Z31: =SUMIF('[1]Total 2'!$I:$I,_xlfn.TEXTJOIN(" ",TRUE,'NEW ATD PER TEAM'!$D$27,'NEW ATD PER TEAM'!$D31),'[1]Total 2'!AC:AC) -> #VALUE! | AA31: =SUMIF('[1]Total 2'!$I:$I,_xlfn.TEXTJOIN(" ",TRUE,'NEW ATD PER TEAM'!$D$27,'NEW ATD PER TEAM'!$D31),'[1]Total 2'!AD:AD) -> #VALUE! | AC31: =J31*1854*40 -> #VALUE! | AD31: =AA31 -> #VALUE! | AE31: =IFERROR(AD31/AC31,"")
E32: TOTAL | G32: =SUM(G28:G31) -> 32 | H32: =SUM(H28:H31) -> 7 | I32: =IFERROR(H32/G32,"") -> 0.21875 | J32: =SUM(J28:J31) -> #VALUE! | K32: =SUM(K28:K31) -> #VALUE! | L32: =SUM(L28:L31) -> #VALUE! | M32: =IFERROR(L32/K32,0) -> 0 | N32: =SUM(N28:N31) -> #VALUE! | O32: =SUM(O28:O31) -> #VALUE! | P32: =IFERROR(O32/N32,0) -> 0 | Q32: =SUM(Q28:Q31) -> #VALUE! | R32: =SUM(R28:R31) -> #VALUE! | S32: =IFERROR(R32/Q32,0) -> 0 | T32: =SUM(T28:T31) -> #VALUE! | U32: =SUM(U28:U31) -> #VALUE! | V32: =IFERROR(U32/T32,0) -> 0 | W32: =SUM(W28:W31) -> #VALUE! | X32: =SUM(X28:X31) -> #VALUE! | Y32: =IFERROR(X32/W32,0) -> 0 | Z32: =SUM(Z28:Z31) -> #VALUE! | AA32: =SUM(AA28:AA31) -> #VALUE! | AB32: =SUM(AB28:AB31) -> 0 | AC32: =SUM(AC28:AC31) -> #VALUE! | AD32: =SUM(AD28:AD31) -> #VALUE! | AE32: =IFERROR(AD32/AC32,"")
D33: OWERRI | F33: CHIDI BEST
B34: 1 | D34: Team 1 | E34: Orogwe and Oguaku | G34: 8 | H34: 7 | I34: =IFERROR(H34/G34,"") -> 0.875 | J34: =SUMIF('[1]Total 2'!$I:$I,_xlfn.TEXTJOIN(" ",TRUE,'NEW ATD PER TEAM'!$D$33,'NEW ATD PER TEAM'!$D34),'[1]Total 2'!L:L) -> #VALUE! | K34: =J34*68/40 -> #VALUE! | L34: =SUMIF('[1]Total 2'!$I:$I,_xlfn.TEXTJOIN(" ",TRUE,'NEW ATD PER TEAM'!$D$33,'NEW ATD PER TEAM'!$D34),'[1]Total 2'!O:O) -> #VALUE! | M34: =IFERROR(L34/K34,0) -> 0 | N34: =J34*68/24 -> #VALUE! | O34: =SUMIF('[1]Total 2'!$I:$I,_xlfn.TEXTJOIN(" ",TRUE,'NEW ATD PER TEAM'!$D$33,'NEW ATD PER TEAM'!$D34),'[1]Total 2'!R:R) -> #VALUE! | P34: =IFERROR(O34/N34,0) -> 0 | Q34: =J34*68/24 -> #VALUE! | R34: =SUMIF('[1]Total 2'!$I:$I,_xlfn.TEXTJOIN(" ",TRUE,'NEW ATD PER TEAM'!$D$33,'NEW ATD PER TEAM'!$D34),'[1]Total 2'!U:U) -> #VALUE! | S34: =IFERROR(R34/Q34,0) -> 0 | T34: =J34*68/12 -> #VALUE! | U34: =SUMIF('[1]Total 2'!$I:$I,_xlfn.TEXTJOIN(" ",TRUE,'NEW ATD PER TEAM'!$D$33,'NEW ATD PER TEAM'!$D34),'[1]Total 2'!X:X) -> #VALUE! | V34: =IFERROR(U34/T34,0) -> 0 | W34: =J34*68/12 -> #VALUE! | X34: =SUMIF('[1]Total 2'!$I:$I,_xlfn.TEXTJOIN(" ",TRUE,'NEW ATD PER TEAM'!$D$33,'NEW ATD PER TEAM'!$D34),'[1]Total 2'!AA:AA) -> #VALUE! | Y34: =IFERROR(X34/W34,0) -> 0 | Z34: =SUMIF('[1]Total 2'!$I:$I,_xlfn.TEXTJOIN(" ",TRUE,'NEW ATD PER TEAM'!$D$33,'NEW ATD PER TEAM'!$D34),'[1]Total 2'!AC:AC) -> #VALUE! | AA34: =SUMIF('[1]Total 2'!$I:$I,_xlfn.TEXTJOIN(" ",TRUE,'NEW ATD PER TEAM'!$D$33,'NEW ATD PER TEAM'!$D34),'[1]Total 2'!AD:AD) -> #VALUE! | AC34: =J34*1854*40 -> #VALUE! | AD34: =AA34 -> #VALUE! | AE34: =IFERROR(AD34/AC34,"")
B35: 2 | D35: Team 2 | E35: Amakaohi and Akwakuma Market | G35: 8 | H35: 7 | I35: =IFERROR(H35/G35,"") -> 0.875 | J35: =SUMIF('[1]Total 2'!$I:$I,_xlfn.TEXTJOIN(" ",TRUE,'NEW ATD PER TEAM'!$D$33,'NEW ATD PER TEAM'!$D35),'[1]Total 2'!L:L) -> #VALUE! | K35: =J35*68/40 -> #VALUE! | L35: =SUMIF('[1]Total 2'!$I:$I,_xlfn.TEXTJOIN(" ",TRUE,'NEW ATD PER TEAM'!$D$33,'NEW ATD PER TEAM'!$D35),'[1]Total 2'!O:O) -> #VALUE! | M35: =IFERROR(L35/K35,0) -> 0 | N35: =J35*68/24 -> #VALUE! | O35: =SUMIF('[1]Total 2'!$I:$I,_xlfn.TEXTJOIN(" ",TRUE,'NEW ATD PER TEAM'!$D$33,'NEW ATD PER TEAM'!$D35),'[1]Total 2'!R:R) -> #VALUE! | P35: =IFERROR(O35/N35,0) -> 0 | Q35: =J35*68/24 -> #VALUE! | R35: =SUMIF('[1]Total 2'!$I:$I,_xlfn.TEXTJOIN(" ",TRUE,'NEW ATD PER TEAM'!$D$33,'NEW ATD PER TEAM'!$D35),'[1]Total 2'!U:U) -> #VALUE! | S35: =IFERROR(R35/Q35,0) -> 0 | T35: =J35*68/12 -> #VALUE! | U35: =SUMIF('[1]Total 2'!$I:$I,_xlfn.TEXTJOIN(" ",TRUE,'NEW ATD PER TEAM'!$D$33,'NEW ATD PER TEAM'!$D35),'[1]Total 2'!X:X) -> #VALUE! | V35: =IFERROR(U35/T35,0) -> 0 | W35: =J35*68/12 -> #VALUE! | X35: =SUMIF('[1]Total 2'!$I:$I,_xlfn.TEXTJOIN(" ",TRUE,'NEW ATD PER TEAM'!$D$33,'NEW ATD PER TEAM'!$D35),'[1]Total 2'!AA:AA) -> #VALUE! | Y35: =IFERROR(X35/W35,0) -> 0 | Z35: =SUMIF('[1]Total 2'!$I:$I,_xlfn.TEXTJOIN(" ",TRUE,'NEW ATD PER TEAM'!$D$33,'NEW ATD PER TEAM'!$D35),'[1]Total 2'!AC:AC) -> #VALUE! | AA35: =SUMIF('[1]Total 2'!$I:$I,_xlfn.TEXTJOIN(" ",TRUE,'NEW ATD PER TEAM'!$D$33,'NEW ATD PER TEAM'!$D35),'[1]Total 2'!AD:AD) -> #VALUE! | AC35: =J35*1854*40 -> #VALUE! | AD35: =AA35 -> #VALUE! | AE35: =IFERROR(AD35/AC35,"")
B36: 3 | D36: Team 3 | E36: Nkwu Orji Market and Rochas Market | G36: 8 | I36: =IFERROR(H36/G36,"") -> 0 | J36: =SUMIF('[1]Total 2'!$I:$I,_xlfn.TEXTJOIN(" ",TRUE,'NEW ATD PER TEAM'!$D$33,'NEW ATD PER TEAM'!$D36),'[1]Total 2'!L:L) -> #VALUE! | K36: =J36*68/40 -> #VALUE! | L36: =SUMIF('[1]Total 2'!$I:$I,_xlfn.TEXTJOIN(" ",TRUE,'NEW ATD PER TEAM'!$D$33,'NEW ATD PER TEAM'!$D36),'[1]Total 2'!O:O) -> #VALUE! | M36: =IFERROR(L36/K36,0) -> 0 | N36: =J36*68/24 -> #VALUE! | O36: =SUMIF('[1]Total 2'!$I:$I,_xlfn.TEXTJOIN(" ",TRUE,'NEW ATD PER TEAM'!$D$33,'NEW ATD PER TEAM'!$D36),'[1]Total 2'!R:R) -> #VALUE! | P36: =IFERROR(O36/N36,0) -> 0 | Q36: =J36*68/24 -> #VALUE! | R36: =SUMIF('[1]Total 2'!$I:$I,_xlfn.TEXTJOIN(" ",TRUE,'NEW ATD PER TEAM'!$D$33,'NEW ATD PER TEAM'!$D36),'[1]Total 2'!U:U) -> #VALUE! | S36: =IFERROR(R36/Q36,0) -> 0 | T36: =J36*68/12 -> #VALUE! | U36: =SUMIF('[1]Total 2'!$I:$I,_xlfn.TEXTJOIN(" ",TRUE,'NEW ATD PER TEAM'!$D$33,'NEW ATD PER TEAM'!$D36),'[1]Total 2'!X:X) -> #VALUE! | V36: =IFERROR(U36/T36,0) -> 0 | W36: =J36*68/12 -> #VALUE! | X36: =SUMIF('[1]Total 2'!$I:$I,_xlfn.TEXTJOIN(" ",TRUE,'NEW ATD PER TEAM'!$D$33,'NEW ATD PER TEAM'!$D36),'[1]Total 2'!AA:AA) -> #VALUE! | Y36: =IFERROR(X36/W36,0) -> 0 | Z36: =SUMIF('[1]Total 2'!$I:$I,_xlfn.TEXTJOIN(" ",TRUE,'NEW ATD PER TEAM'!$D$33,'NEW ATD PER TEAM'!$D36),'[1]Total 2'!AC:AC) -> #VALUE! | AA36: =SUMIF('[1]Total 2'!$I:$I,_xlfn.TEXTJOIN(" ",TRUE,'NEW ATD PER TEAM'!$D$33,'NEW ATD PER TEAM'!$D36),'[1]Total 2'!AD:AD) -> #VALUE! | AC36: =J36*1854*40 -> #VALUE! | AD36: =AA36 -> #VALUE! | AE36: =IFERROR(AD36/AC36,"")
B37: 4 | D37: Team 4 | G37: 8 | I37: =IFERROR(H37/G37,"") -> 0 | J37: =SUMIF('[1]Total 2'!$I:$I,_xlfn.TEXTJOIN(" ",TRUE,'NEW ATD PER TEAM'!$D$33,'NEW ATD PER TEAM'!$D37),'[1]Total 2'!L:L) -> #VALUE! | K37: =J37*68/40 -> #VALUE! | L37: =SUMIF('[1]Total 2'!$I:$I,_xlfn.TEXTJOIN(" ",TRUE,'NEW ATD PER TEAM'!$D$33,'NEW ATD PER TEAM'!$D37),'[1]Total 2'!O:O) -> #VALUE! | M37: =IFERROR(L37/K37,0) -> 0 | N37: =J37*68/24 -> #VALUE! | O37: =SUMIF('[1]Total 2'!$I:$I,_xlfn.TEXTJOIN(" ",TRUE,'NEW ATD PER TEAM'!$D$33,'NEW ATD PER TEAM'!$D37),'[1]Total 2'!R:R) -> #VALUE! | P37: =IFERROR(O37/N37,0) -> 0 | Q37: =J37*68/24 -> #VALUE! | R37: =SUMIF('[1]Total 2'!$I:$I,_xlfn.TEXTJOIN(" ",TRUE,'NEW ATD PER TEAM'!$D$33,'NEW ATD PER TEAM'!$D37),'[1]Total 2'!U:U) -> #VALUE! | S37: =IFERROR(R37/Q37,0) -> 0 | T37: =J37*68/12 -> #VALUE! | U37: =SUMIF('[1]Total 2'!$I:$I,_xlfn.TEXTJOIN(" ",TRUE,'NEW ATD PER TEAM'!$D$33,'NEW ATD PER TEAM'!$D37),'[1]Total 2'!X:X) -> #VALUE! | V37: =IFERROR(U37/T37,0) -> 0 | W37: =J37*68/12 -> #VALUE! | X37: =SUMIF('[1]Total 2'!$I:$I,_xlfn.TEXTJOIN(" ",TRUE,'NEW ATD PER TEAM'!$D$33,'NEW ATD PER TEAM'!$D37),'[1]Total 2'!AA:AA) -> #VALUE! | Y37: =IFERROR(X37/W37,0) -> 0 | Z37: =SUMIF('[1]Total 2'!$I:$I,_xlfn.TEXTJOIN(" ",TRUE,'NEW ATD PER TEAM'!$D$33,'NEW ATD PER TEAM'!$D37),'[1]Total 2'!AC:AC) -> #VALUE! | AA37: =SUMIF('[1]Total 2'!$I:$I,_xlfn.TEXTJOIN(" ",TRUE,'NEW ATD PER TEAM'!$D$33,'NEW ATD PER TEAM'!$D37),'[1]Total 2'!AD:AD) -> #VALUE! | AC37: =J37*1854*40 -> #VALUE! | AD37: =AA37 -> #VALUE! | AE37: =IFERROR(AD37/AC37,"")
E38: TOTAL | G38: =SUM(G34:G37) -> 32 | H38: =SUM(H34:H37) -> 14 | I38: =IFERROR(H38/G38,"") -> 0.4375 | J38: =SUM(J34:J37) -> #VALUE! | K38: =SUM(K34:K37) -> #VALUE! | L38: =SUM(L34:L37) -> #VALUE! | M38: =IFERROR(L38/K38,0) -> 0 | N38: =SUM(N34:N37) -> #VALUE! | O38: =SUM(O34:O37) -> #VALUE! | P38: =IFERROR(O38/N38,0) -> 0 | Q38: =SUM(Q34:Q37) -> #VALUE! | R38: =SUM(R34:R37) -> #VALUE! | S38: =IFERROR(R38/Q38,0) -> 0 | T38: =SUM(T34:T37) -> #VALUE! | U38: =SUM(U34:U37) -> #VALUE! | V38: =IFERROR(U38/T38,0) -> 0 | W38: =SUM(W34:W37) -> #VALUE! | X38: =SUM(X34:X37) -> #VALUE! | Y38: =IFERROR(X38/W38,0) -> 0 | Z38: =SUM(Z34:Z37) -> #VALUE! | AA38: =SUM(AA34:AA37) -> #VALUE! | AB38: =SUM(AB34:AB37) -> 0 | AC38: =SUM(AC34:AC37) -> #VALUE! | AD38: =SUM(AD34:AD37) -> #VALUE! | AE38: =IFERROR(AD38/AC38,"")
C39: East 2 | D39: ABA | F39: IFEANYI MIRACLE
B40: 1 | D40: Team 1 | E40: Ndioru Market/ | G40: 8 | H40: 8 | I40: =IFERROR(H40/G40,"") -> 1 | J40: =SUMIF('[1]Total 2'!$I:$I,_xlfn.TEXTJOIN(" ",TRUE,'NEW ATD PER TEAM'!$D$39,'NEW ATD PER TEAM'!$D40),'[1]Total 2'!L:L) -> #VALUE! | K40: =J40*68/40 -> #VALUE! | L40: =SUMIF('[1]Total 2'!$I:$I,_xlfn.TEXTJOIN(" ",TRUE,'NEW ATD PER TEAM'!$D$39,'NEW ATD PER TEAM'!$D40),'[1]Total 2'!O:O) -> #VALUE! | M40: =IFERROR(L40/K40,0) -> 0 | N40: =J40*68/24 -> #VALUE! | O40: =SUMIF('[1]Total 2'!$I:$I,_xlfn.TEXTJOIN(" ",TRUE,'NEW ATD PER TEAM'!$D$39,'NEW ATD PER TEAM'!$D40),'[1]Total 2'!R:R) -> #VALUE! | P40: =IFERROR(O40/N40,0) -> 0 | Q40: =J40*68/24 -> #VALUE! | R40: =SUMIF('[1]Total 2'!$I:$I,_xlfn.TEXTJOIN(" ",TRUE,'NEW ATD PER TEAM'!$D$39,'NEW ATD PER TEAM'!$D40),'[1]Total 2'!U:U) -> #VALUE! | S40: =IFERROR(R40/Q40,0) -> 0 | T40: =J40*68/12 -> #VALUE! | U40: =SUMIF('[1]Total 2'!$I:$I,_xlfn.TEXTJOIN(" ",TRUE,'NEW ATD PER TEAM'!$D$39,'NEW ATD PER TEAM'!$D40),'[1]Total 2'!X:X) -> #VALUE! | V40: =IFERROR(U40/T40,0) -> 0 | W40: =J40*68/12 -> #VALUE! | X40: =SUMIF('[1]Total 2'!$I:$I,_xlfn.TEXTJOIN(" ",TRUE,'NEW ATD PER TEAM'!$D$39,'NEW ATD PER TEAM'!$D40),'[1]Total 2'!AA:AA) -> #VALUE! | Y40: =IFERROR(X40/W40,0) -> 0 | Z40: =SUMIF('[1]Total 2'!$I:$I,_xlfn.TEXTJOIN(" ",TRUE,'NEW ATD PER TEAM'!$D$39,'NEW ATD PER TEAM'!$D40),'[1]Total 2'!AC:AC) -> #VALUE! | AA40: =SUMIF('[1]Total 2'!$I:$I,_xlfn.TEXTJOIN(" ",TRUE,'NEW ATD PER TEAM'!$D$39,'NEW ATD PER TEAM'!$D40),'[1]Total 2'!AD:AD) -> #VALUE! | AC40: =J40*1854*40 -> #VALUE! | AD40: =AA40 -> #VALUE! | AE40: =IFERROR(AD40/AC40,"")
B41: 2 | D41: Team 2 | E41: Isi Gate/ | G41: 8 | H41: 8 | I41: =IFERROR(H41/G41,"") -> 1 | J41: =SUMIF('[1]Total 2'!$I:$I,_xlfn.TEXTJOIN(" ",TRUE,'NEW ATD PER TEAM'!$D$39,'NEW ATD PER TEAM'!$D41),'[1]Total 2'!L:L) -> #VALUE! | K41: =J41*68/40 -> #VALUE! | L41: =SUMIF('[1]Total 2'!$I:$I,_xlfn.TEXTJOIN(" ",TRUE,'NEW ATD PER TEAM'!$D$39,'NEW ATD PER TEAM'!$D41),'[1]Total 2'!O:O) -> #VALUE! | M41: =IFERROR(L41/K41,0) -> 0 | N41: =J41*68/24 -> #VALUE! | O41: =SUMIF('[1]Total 2'!$I:$I,_xlfn.TEXTJOIN(" ",TRUE,'NEW ATD PER TEAM'!$D$39,'NEW ATD PER TEAM'!$D41),'[1]Total 2'!R:R) -> #VALUE! | P41: =IFERROR(O41/N41,0) -> 0 | Q41: =J41*68/24 -> #VALUE! | R41: =SUMIF('[1]Total 2'!$I:$I,_xlfn.TEXTJOIN(" ",TRUE,'NEW ATD PER TEAM'!$D$39,'NEW ATD PER TEAM'!$D41),'[1]Total 2'!U:U) -> #VALUE! | S41: =IFERROR(R41/Q41,0) -> 0 | T41: =J41*68/12 -> #VALUE! | U41: =SUMIF('[1]Total 2'!$I:$I,_xlfn.TEXTJOIN(" ",TRUE,'NEW ATD PER TEAM'!$D$39,'NEW ATD PER TEAM'!$D41),'[1]Total 2'!X:X) -> #VALUE! | V41: =IFERROR(U41/T41,0) -> 0 | W41: =J41*68/12 -> #VALUE! | X41: =SUMIF('[1]Total 2'!$I:$I,_xlfn.TEXTJOIN(" ",TRUE,'NEW ATD PER TEAM'!$D$39,'NEW ATD PER TEAM'!$D41),'[1]Total 2'!AA:AA) -> #VALUE! | Y41: =IFERROR(X41/W41,0) -> 0 | Z41: =SUMIF('[1]Total 2'!$I:$I,_xlfn.TEXTJOIN(" ",TRUE,'NEW ATD PER TEAM'!$D$39,'NEW ATD PER TEAM'!$D41),'[1]Total 2'!AC:AC) -> #VALUE! | AA41: =SUMIF('[1]Total 2'!$I:$I,_xlfn.TEXTJOIN(" ",TRUE,'NEW ATD PER TEAM'!$D$39,'NEW ATD PER TEAM'!$D41),'[1]Total 2'!AD:AD) -> #VALUE! | AC41: =J41*1854*40 -> #VALUE! | AD41: =AA41 -> #VALUE! | AE41: =IFERROR(AD41/AC41,"")
B42: 3 | D42: Team 3 | G42: 8 | H42: 7 | I42: =IFERROR(H42/G42,"") -> 0.875 | J42: =SUMIF('[1]Total 2'!$I:$I,_xlfn.TEXTJOIN(" ",TRUE,'NEW ATD PER TEAM'!$D$39,'NEW ATD PER TEAM'!$D42),'[1]Total 2'!L:L) -> #VALUE! | K42: =J42*68/40 -> #VALUE! | L42: =SUMIF('[1]Total 2'!$I:$I,_xlfn.TEXTJOIN(" ",TRUE,'NEW ATD PER TEAM'!$D$39,'NEW ATD PER TEAM'!$D42),'[1]Total 2'!O:O) -> #VALUE! | M42: =IFERROR(L42/K42,0) -> 0 | N42: =J42*68/24 -> #VALUE! | O42: =SUMIF('[1]Total 2'!$I:$I,_xlfn.TEXTJOIN(" ",TRUE,'NEW ATD PER TEAM'!$D$39,'NEW ATD PER TEAM'!$D42),'[1]Total 2'!R:R) -> #VALUE! | P42: =IFERROR(O42/N42,0) -> 0 | Q42: =J42*68/24 -> #VALUE! | R42: =SUMIF('[1]Total 2'!$I:$I,_xlfn.TEXTJOIN(" ",TRUE,'NEW ATD PER TEAM'!$D$39,'NEW ATD PER TEAM'!$D42),'[1]Total 2'!U:U) -> #VALUE! | S42: =IFERROR(R42/Q42,0) -> 0 | T42: =J42*68/12 -> #VALUE! | U42: =SUMIF('[1]Total 2'!$I:$I,_xlfn.TEXTJOIN(" ",TRUE,'NEW ATD PER TEAM'!$D$39,'NEW ATD PER TEAM'!$D42),'[1]Total 2'!X:X) -> #VALUE! | V42: =IFERROR(U42/T42,0) -> 0 | W42: =J42*68/12 -> #VALUE! | X42: =SUMIF('[1]Total 2'!$I:$I,_xlfn.TEXTJOIN(" ",TRUE,'NEW ATD PER TEAM'!$D$39,'NEW ATD PER TEAM'!$D42),'[1]Total 2'!AA:AA) -> #VALUE! | Y42: =IFERROR(X42/W42,0) -> 0 | Z42: =SUMIF('[1]Total 2'!$I:$I,_xlfn.TEXTJOIN(" ",TRUE,'NEW ATD PER TEAM'!$D$39,'NEW ATD PER TEAM'!$D42),'[1]Total 2'!AC:AC) -> #VALUE! | AA42: =SUMIF('[1]Total 2'!$I:$I,_xlfn.TEXTJOIN(" ",TRUE,'NEW ATD PER TEAM'!$D$39,'NEW ATD PER TEAM'!$D42),'[1]Total 2'!AD:AD) -> #VALUE! | AC42: =J42*1854*40 -> #VALUE! | AD42: =AA42 -> #VALUE! | AE42: =IFERROR(AD42/AC42,"")
B43: 4 | D43: Team 4 | G43: 8 | I43: =IFERROR(H43/G43,"") -> 0 | J43: =SUMIF('[1]Total 2'!$I:$I,_xlfn.TEXTJOIN(" ",TRUE,'NEW ATD PER TEAM'!$D$39,'NEW ATD PER TEAM'!$D43),'[1]Total 2'!L:L) -> #VALUE! | K43: =J43*68/40 -> #VALUE! | L43: =SUMIF('[1]Total 2'!$I:$I,_xlfn.TEXTJOIN(" ",TRUE,'NEW ATD PER TEAM'!$D$39,'NEW ATD PER TEAM'!$D43),'[1]Total 2'!O:O) -> #VALUE! | M43: =IFERROR(L43/K43,0) -> 0 | N43: =J43*68/24 -> #VALUE! | O43: =SUMIF('[1]Total 2'!$I:$I,_xlfn.TEXTJOIN(" ",TRUE,'NEW ATD PER TEAM'!$D$39,'NEW ATD PER TEAM'!$D43),'[1]Total 2'!R:R) -> #VALUE! | P43: =IFERROR(O43/N43,0) -> 0 | Q43: =J43*68/24 -> #VALUE! | R43: =SUMIF('[1]Total 2'!$I:$I,_xlfn.TEXTJOIN(" ",TRUE,'NEW ATD PER TEAM'!$D$39,'NEW ATD PER TEAM'!$D43),'[1]Total 2'!U:U) -> #VALUE! | S43: =IFERROR(R43/Q43,0) -> 0 | T43: =J43*68/12 -> #VALUE! | U43: =SUMIF('[1]Total 2'!$I:$I,_xlfn.TEXTJOIN(" ",TRUE,'NEW ATD PER TEAM'!$D$39,'NEW ATD PER TEAM'!$D43),'[1]Total 2'!X:X) -> #VALUE! | V43: =IFERROR(U43/T43,0) -> 0 | W43: =J43*68/12 -> #VALUE! | X43: =SUMIF('[1]Total 2'!$I:$I,_xlfn.TEXTJOIN(" ",TRUE,'NEW ATD PER TEAM'!$D$39,'NEW ATD PER TEAM'!$D43),'[1]Total 2'!AA:AA) -> #VALUE! | Y43: =IFERROR(X43/W43,0) -> 0 | Z43: =SUMIF('[1]Total 2'!$I:$I,_xlfn.TEXTJOIN(" ",TRUE,'NEW ATD PER TEAM'!$D$39,'NEW ATD PER TEAM'!$D43),'[1]Total 2'!AC:AC) -> #VALUE! | AA43: =SUMIF('[1]Total 2'!$I:$I,_xlfn.TEXTJOIN(" ",TRUE,'NEW ATD PER TEAM'!$D$39,'NEW ATD PER TEAM'!$D43),'[1]Total 2'!AD:AD) -> #VALUE! | AC43: =J43*1854*40 -> #VALUE! | AD43: =AA43 -> #VALUE! | AE43: =IFERROR(AD43/AC43,"")
E44: TOTAL | G44: =SUM(G40:G43) -> 32 | H44: =SUM(H40:H43) -> 23 | I44: =IFERROR(H44/G44,"") -> 0.71875 | J44: =SUM(J40:J43) -> #VALUE! | K44: =SUM(K40:K43) -> #VALUE! | L44: =SUM(L40:L43) -> #VALUE! | M44: =IFERROR(L44/K44,0) -> 0 | N44: =SUM(N40:N43) -> #VALUE! | O44: =SUM(O40:O43) -> #VALUE! | P44: =IFERROR(O44/N44,0) -> 0 | Q44: =SUM(Q40:Q43) -> #VALUE! | R44: =SUM(R40:R43) -> #VALUE! | S44: =IFERROR(R44/Q44,0) -> 0 | T44: =SUM(T40:T43) -> #VALUE! | U44: =SUM(U40:U43) -> #VALUE! | V44: =IFERROR(U44/T44,0) -> 0 | W44: =SUM(W40:W43) -> #VALUE! | X44: =SUM(X40:X43) -> #VALUE! | Y44: =IFERROR(X44/W44,0) -> 0 | Z44: =SUM(Z40:Z43) -> #VALUE! | AA44: =SUM(AA40:AA43) -> #VALUE! | AB44: =SUM(AB40:AB43) -> 0 | AC44: =SUM(AC40:AC43) -> #VALUE! | AD44: =SUM(AD40:AD43) -> #VALUE! | AE44: =IFERROR(AD44/AC44,"")
D45: PHC 1 | F45: NZEH SANDRA
B46: 1 | D46: Team 1 | E46: School Road/Afam road | G46: 8 | H46: 11 | I46: =IFERROR(H46/G46,"") -> 1.375 | J46: =SUMIF('[1]Total 2'!$I:$I,_xlfn.TEXTJOIN(" ",TRUE,'NEW ATD PER TEAM'!$D$45,'NEW ATD PER TEAM'!$D46),'[1]Total 2'!L:L) -> #VALUE! | K46: =J46*68/40 -> #VALUE! | L46: =SUMIF('[1]Total 2'!$I:$I,_xlfn.TEXTJOIN(" ",TRUE,'NEW ATD PER TEAM'!$D$45,'NEW ATD PER TEAM'!$D46),'[1]Total 2'!O:O) -> #VALUE! | M46: =IFERROR(L46/K46,0) -> 0 | N46: =J46*68/24 -> #VALUE! | O46: =SUMIF('[1]Total 2'!$I:$I,_xlfn.TEXTJOIN(" ",TRUE,'NEW ATD PER TEAM'!$D$45,'NEW ATD PER TEAM'!$D46),'[1]Total 2'!R:R) -> #VALUE! | P46: =IFERROR(O46/N46,0) -> 0 | Q46: =J46*68/24 -> #VALUE! | R46: =SUMIF('[1]Total 2'!$I:$I,_xlfn.TEXTJOIN(" ",TRUE,'NEW ATD PER TEAM'!$D$45,'NEW ATD PER TEAM'!$D46),'[1]Total 2'!U:U) -> #VALUE! | S46: =IFERROR(R46/Q46,0) -> 0 | T46: =J46*68/12 -> #VALUE! | U46: =SUMIF('[1]Total 2'!$I:$I,_xlfn.TEXTJOIN(" ",TRUE,'NEW ATD PER TEAM'!$D$45,'NEW ATD PER TEAM'!$D46),'[1]Total 2'!X:X) -> #VALUE! | V46: =IFERROR(U46/T46,0) -> 0 | W46: =J46*68/12 -> #VALUE! | X46: =SUMIF('[1]Total 2'!$I:$I,_xlfn.TEXTJOIN(" ",TRUE,'NEW ATD PER TEAM'!$D$45,'NEW ATD PER TEAM'!$D46),'[1]Total 2'!AA:AA) -> #VALUE! | Y46: =IFERROR(X46/W46,0) -> 0 | Z46: =SUMIF('[1]Total 2'!$I:$I,_xlfn.TEXTJOIN(" ",TRUE,'NEW ATD PER TEAM'!$D$45,'NEW ATD PER TEAM'!$D46),'[1]Total 2'!AC:AC) -> #VALUE! | AA46: =SUMIF('[1]Total 2'!$I:$I,_xlfn.TEXTJOIN(" ",TRUE,'NEW ATD PER TEAM'!$D$45,'NEW ATD PER TEAM'!$D46),'[1]Total 2'!AD:AD) -> #VALUE! | AC46: =J46*1854*40 -> #VALUE! | AD46: =AA46 -> #VALUE! | AE46: =IFERROR(AD46/AC46,"")
B47: 2 | D47: Team 2 | E47: Trailer Park/Izuoma new layout | G47: 8 | H47: 11 | I47: =IFERROR(H47/G47,"") -> 1.375 | J47: =SUMIF('[1]Total 2'!$I:$I,_xlfn.TEXTJOIN(" ",TRUE,'NEW ATD PER TEAM'!$D$45,'NEW ATD PER TEAM'!$D47),'[1]Total 2'!L:L) -> #VALUE! | K47: =J47*68/40 -> #VALUE! | L47: =SUMIF('[1]Total 2'!$I:$I,_xlfn.TEXTJOIN(" ",TRUE,'NEW ATD PER TEAM'!$D$45,'NEW ATD PER TEAM'!$D47),'[1]Total 2'!O:O) -> #VALUE! | M47: =IFERROR(L47/K47,0) -> 0 | N47: =J47*68/24 -> #VALUE! | O47: =SUMIF('[1]Total 2'!$I:$I,_xlfn.TEXTJOIN(" ",TRUE,'NEW ATD PER TEAM'!$D$45,'NEW ATD PER TEAM'!$D47),'[1]Total 2'!R:R) -> #VALUE! | P47: =IFERROR(O47/N47,0) -> 0 | Q47: =J47*68/24 -> #VALUE! | R47: =SUMIF('[1]Total 2'!$I:$I,_xlfn.TEXTJOIN(" ",TRUE,'NEW ATD PER TEAM'!$D$45,'NEW ATD PER TEAM'!$D47),'[1]Total 2'!U:U) -> #VALUE! | S47: =IFERROR(R47/Q47,0) -> 0 | T47: =J47*68/12 -> #VALUE! | U47: =SUMIF('[1]Total 2'!$I:$I,_xlfn.TEXTJOIN(" ",TRUE,'NEW ATD PER TEAM'!$D$45,'NEW ATD PER TEAM'!$D47),'[1]Total 2'!X:X) -> #VALUE! | V47: =IFERROR(U47/T47,0) -> 0 | W47: =J47*68/12 -> #VALUE! | X47: =SUMIF('[1]Total 2'!$I:$I,_xlfn.TEXTJOIN(" ",TRUE,'NEW ATD PER TEAM'!$D$45,'NEW ATD PER TEAM'!$D47),'[1]Total 2'!AA:AA) -> #VALUE! | Y47: =IFERROR(X47/W47,0) -> 0 | Z47: =SUMIF('[1]Total 2'!$I:$I,_xlfn.TEXTJOIN(" ",TRUE,'NEW ATD PER TEAM'!$D$45,'NEW ATD PER TEAM'!$D47),'[1]Total 2'!AC:AC) -> #VALUE! | AA47: =SUMIF('[1]Total 2'!$I:$I,_xlfn.TEXTJOIN(" ",TRUE,'NEW ATD PER TEAM'!$D$45,'NEW ATD PER TEAM'!$D47),'[1]Total 2'!AD:AD) -> #VALUE! | AC47: =J47*1854*40 -> #VALUE! | AD47: =AA47 -> #VALUE! | AE47: =IFERROR(AD47/AC47,"")
B48: 3 | D48: Team 3 | G48: 8 | I48: =IFERROR(H48/G48,"") -> 0 | J48: =SUMIF('[1]Total 2'!$I:$I,_xlfn.TEXTJOIN(" ",TRUE,'NEW ATD PER TEAM'!$D$45,'NEW ATD PER TEAM'!$D48),'[1]Total 2'!L:L) -> #VALUE! | K48: =J48*68/40 -> #VALUE! | L48: =SUMIF('[1]Total 2'!$I:$I,_xlfn.TEXTJOIN(" ",TRUE,'NEW ATD PER TEAM'!$D$45,'NEW ATD PER TEAM'!$D48),'[1]Total 2'!O:O) -> #VALUE! | M48: =IFERROR(L48/K48,0) -> 0 | N48: =J48*68/24 -> #VALUE! | O48: =SUMIF('[1]Total 2'!$I:$I,_xlfn.TEXTJOIN(" ",TRUE,'NEW ATD PER TEAM'!$D$45,'NEW ATD PER TEAM'!$D48),'[1]Total 2'!R:R) -> #VALUE! | P48: =IFERROR(O48/N48,0) -> 0 | Q48: =J48*68/24 -> #VALUE! | R48: =SUMIF('[1]Total 2'!$I:$I,_xlfn.TEXTJOIN(" ",TRUE,'NEW ATD PER TEAM'!$D$45,'NEW ATD PER TEAM'!$D48),'[1]Total 2'!U:U) -> #VALUE! | S48: =IFERROR(R48/Q48,0) -> 0 | T48: =J48*68/12 -> #VALUE! | U48: =SUMIF('[1]Total 2'!$I:$I,_xlfn.TEXTJOIN(" ",TRUE,'NEW ATD PER TEAM'!$D$45,'NEW ATD PER TEAM'!$D48),'[1]Total 2'!X:X) -> #VALUE! | V48: =IFERROR(U48/T48,0) -> 0 | W48: =J48*68/12 -> #VALUE! | X48: =SUMIF('[1]Total 2'!$I:$I,_xlfn.TEXTJOIN(" ",TRUE,'NEW ATD PER TEAM'!$D$45,'NEW ATD PER TEAM'!$D48),'[1]Total 2'!AA:AA) -> #VALUE! | Y48: =IFERROR(X48/W48,0) -> 0 | Z48: =SUMIF('[1]Total 2'!$I:$I,_xlfn.TEXTJOIN(" ",TRUE,'NEW ATD PER TEAM'!$D$45,'NEW ATD PER TEAM'!$D48),'[1]Total 2'!AC:AC) -> #VALUE! | AA48: =SUMIF('[1]Total 2'!$I:$I,_xlfn.TEXTJOIN(" ",TRUE,'NEW ATD PER TEAM'!$D$45,'NEW ATD PER TEAM'!$D48),'[1]Total 2'!AD:AD) -> #VALUE! | AC48: =J48*1854*40 -> #VALUE! | AD48: =AA48 -> #VALUE! | AE48: =IFERROR(AD48/AC48,"")
B49: 4 | D49: Team 4 | G49: 8 | I49: =IFERROR(H49/G49,"") -> 0 | J49: =SUMIF('[1]Total 2'!$I:$I,_xlfn.TEXTJOIN(" ",TRUE,'NEW ATD PER TEAM'!$D$45,'NEW ATD PER TEAM'!$D49),'[1]Total 2'!L:L) -> #VALUE! | K49: =J49*68/40 -> #VALUE! | L49: =SUMIF('[1]Total 2'!$I:$I,_xlfn.TEXTJOIN(" ",TRUE,'NEW ATD PER TEAM'!$D$45,'NEW ATD PER TEAM'!$D49),'[1]Total 2'!O:O) -> #VALUE! | M49: =IFERROR(L49/K49,0) -> 0 | N49: =J49*68/24 -> #VALUE! | O49: =SUMIF('[1]Total 2'!$I:$I,_xlfn.TEXTJOIN(" ",TRUE,'NEW ATD PER TEAM'!$D$45,'NEW ATD PER TEAM'!$D49),'[1]Total 2'!R:R) -> #VALUE! | P49: =IFERROR(O49/N49,0) -> 0 | Q49: =J49*68/24 -> #VALUE! | R49: =SUMIF('[1]Total 2'!$I:$I,_xlfn.TEXTJOIN(" ",TRUE,'NEW ATD PER TEAM'!$D$45,'NEW ATD PER TEAM'!$D49),'[1]Total 2'!U:U) -> #VALUE! | S49: =IFERROR(R49/Q49,0) -> 0 | T49: =J49*68/12 -> #VALUE! | U49: =SUMIF('[1]Total 2'!$I:$I,_xlfn.TEXTJOIN(" ",TRUE,'NEW ATD PER TEAM'!$D$45,'NEW ATD PER TEAM'!$D49),'[1]Total 2'!X:X) -> #VALUE! | V49: =IFERROR(U49/T49,0) -> 0 | W49: =J49*68/12 -> #VALUE! | X49: =SUMIF('[1]Total 2'!$I:$I,_xlfn.TEXTJOIN(" ",TRUE,'NEW ATD PER TEAM'!$D$45,'NEW ATD PER TEAM'!$D49),'[1]Total 2'!AA:AA) -> #VALUE! | Y49: =IFERROR(X49/W49,0) -> 0 | Z49: =SUMIF('[1]Total 2'!$I:$I,_xlfn.TEXTJOIN(" ",TRUE,'NEW ATD PER TEAM'!$D$45,'NEW ATD PER TEAM'!$D49),'[1]Total 2'!AC:AC) -> #VALUE! | AA49: =SUMIF('[1]Total 2'!$I:$I,_xlfn.TEXTJOIN(" ",TRUE,'NEW ATD PER TEAM'!$D$45,'NEW ATD PER TEAM'!$D49),'[1]Total 2'!AD:AD) -> #VALUE! | AC49: =J49*1854*40 -> #VALUE! | AD49: =AA49 -> #VALUE! | AE49: =IFERROR(AD49/AC49,"")
E50: TOTAL | G50: =SUM(G46:G49) -> 32 | H50: =SUM(H46:H49) -> 22 | I50: =IFERROR(H50/G50,"") -> 0.6875 | J50: =SUM(J46:J49) -> #VALUE! | K50: =SUM(K46:K49) -> #VALUE! | L50: =SUM(L46:L49) -> #VALUE! | M50: =IFERROR(L50/K50,0) -> 0 | N50: =SUM(N46:N49) -> #VALUE! | O50: =SUM(O46:O49) -> #VALUE! | P50: =IFERROR(O50/N50,0) -> 0 | Q50: =SUM(Q46:Q49) -> #VALUE! | R50: =SUM(R46:R49) -> #VALUE! | S50: =IFERROR(R50/Q50,0) -> 0 | T50: =SUM(T46:T49) -> #VALUE! | U50: =SUM(U46:U49) -> #VALUE! | V50: =IFERROR(U50/T50,0) -> 0 | W50: =SUM(W46:W49) -> #VALUE! | X50: =SUM(X46:X49) -> #VALUE! | Y50: =IFERROR(X50/W50,0) -> 0 | Z50: =SUM(Z46:Z49) -> #VALUE! | AA50: =SUM(AA46:AA49) -> #VALUE! | AB50: =SUM(AB46:AB49) -> 0 | AC50: =SUM(AC46:AC49) -> #VALUE! | AD50: =SUM(AD46:AD49) -> #VALUE! | AE50: =IFERROR(AD50/AC50,"")
D51: PHC 2 | F51: Gods Choice
B52: 1 | D52: Team 1 | E52: Rumukalagbor/Marine Market | G52: 8 | I52: =IFERROR(H52/G52,"") -> 0 | J52: =SUMIF('[1]Total 2'!$I:$I,_xlfn.TEXTJOIN(" ",TRUE,'NEW ATD PER TEAM'!$D$51,'NEW ATD PER TEAM'!$D52),'[1]Total 2'!L:L) -> #VALUE! | K52: =J52*68/40 -> #VALUE! | L52: =SUMIF('[1]Total 2'!$I:$I,_xlfn.TEXTJOIN(" ",TRUE,'NEW ATD PER TEAM'!$D$51,'NEW ATD PER TEAM'!$D52),'[1]Total 2'!O:O) -> #VALUE! | M52: =IFERROR(L52/K52,0) -> 0 | N52: =J52*68/24 -> #VALUE! | O52: =SUMIF('[1]Total 2'!$I:$I,_xlfn.TEXTJOIN(" ",TRUE,'NEW ATD PER TEAM'!$D$51,'NEW ATD PER TEAM'!$D52),'[1]Total 2'!R:R) -> #VALUE! | P52: =IFERROR(O52/N52,0) -> 0 | Q52: =J52*68/24 -> #VALUE! | R52: =SUMIF('[1]Total 2'!$I:$I,_xlfn.TEXTJOIN(" ",TRUE,'NEW ATD PER TEAM'!$D$51,'NEW ATD PER TEAM'!$D52),'[1]Total 2'!U:U) -> #VALUE! | S52: =IFERROR(R52/Q52,0) -> 0 | T52: =J52*68/12 -> #VALUE! | U52: =SUMIF('[1]Total 2'!$I:$I,_xlfn.TEXTJOIN(" ",TRUE,'NEW ATD PER TEAM'!$D$51,'NEW ATD PER TEAM'!$D52),'[1]Total 2'!X:X) -> #VALUE! | V52: =IFERROR(U52/T52,0) -> 0 | W52: =J52*68/12 -> #VALUE! | X52: =SUMIF('[1]Total 2'!$I:$I,_xlfn.TEXTJOIN(" ",TRUE,'NEW ATD PER TEAM'!$D$51,'NEW ATD PER TEAM'!$D52),'[1]Total 2'!AA:AA) -> #VALUE! | Y52: =IFERROR(X52/W52,0) -> 0 | Z52: =SUMIF('[1]Total 2'!$I:$I,_xlfn.TEXTJOIN(" ",TRUE,'NEW ATD PER TEAM'!$D$51,'NEW ATD PER TEAM'!$D52),'[1]Total 2'!AC:AC) -> #VALUE! | AA52: =SUMIF('[1]Total 2'!$I:$I,_xlfn.TEXTJOIN(" ",TRUE,'NEW ATD PER TEAM'!$D$51,'NEW ATD PER TEAM'!$D52),'[1]Total 2'!AD:AD) -> #VALUE! | AC52: =J52*1854*40 -> #VALUE! | AD52: =AA52 -> #VALUE! | AE52: =IFERROR(AD52/AC52,"")
B53: 2 | D53: Team 2 | E53: Rumuigbo/Oyigbo Market | G53: 8 | I53: =IFERROR(H53/G53,"") -> 0 | J53: =SUMIF('[1]Total 2'!$I:$I,_xlfn.TEXTJOIN(" ",TRUE,'NEW ATD PER TEAM'!$D$51,'NEW ATD PER TEAM'!$D53),'[1]Total 2'!L:L) -> #VALUE! | K53: =J53*68/40 -> #VALUE! | L53: =SUMIF('[1]Total 2'!$I:$I,_xlfn.TEXTJOIN(" ",TRUE,'NEW ATD PER TEAM'!$D$51,'NEW ATD PER TEAM'!$D53),'[1]Total 2'!O:O) -> #VALUE! | M53: =IFERROR(L53/K53,0) -> 0 | N53: =J53*68/24 -> #VALUE! | O53: =SUMIF('[1]Total 2'!$I:$I,_xlfn.TEXTJOIN(" ",TRUE,'NEW ATD PER TEAM'!$D$51,'NEW ATD PER TEAM'!$D53),'[1]Total 2'!R:R) -> #VALUE! | P53: =IFERROR(O53/N53,0) -> 0 | Q53: =J53*68/24 -> #VALUE! | R53: =SUMIF('[1]Total 2'!$I:$I,_xlfn.TEXTJOIN(" ",TRUE,'NEW ATD PER TEAM'!$D$51,'NEW ATD PER TEAM'!$D53),'[1]Total 2'!U:U) -> #VALUE! | S53: =IFERROR(R53/Q53,0) -> 0 | T53: =J53*68/12 -> #VALUE! | U53: =SUMIF('[1]Total 2'!$I:$I,_xlfn.TEXTJOIN(" ",TRUE,'NEW ATD PER TEAM'!$D$51,'NEW ATD PER TEAM'!$D53),'[1]Total 2'!X:X) -> #VALUE! | V53: =IFERROR(U53/T53,0) -> 0 | W53: =J53*68/12 -> #VALUE! | X53: =SUMIF('[1]Total 2'!$I:$I,_xlfn.TEXTJOIN(" ",TRUE,'NEW ATD PER TEAM'!$D$51,'NEW ATD PER TEAM'!$D53),'[1]Total 2'!AA:AA) -> #VALUE! | Y53: =IFERROR(X53/W53,0) -> 0 | Z53: =SUMIF('[1]Total 2'!$I:$I,_xlfn.TEXTJOIN(" ",TRUE,'NEW ATD PER TEAM'!$D$51,'NEW ATD PER TEAM'!$D53),'[1]Total 2'!AC:AC) -> #VALUE! | AA53: =SUMIF('[1]Total 2'!$I:$I,_xlfn.TEXTJOIN(" ",TRUE,'NEW ATD PER TEAM'!$D$51,'NEW ATD PER TEAM'!$D53),'[1]Total 2'!AD:AD) -> #VALUE! | AC53: =J53*1854*40 -> #VALUE! | AD53: =AA53 -> #VALUE! | AE53: =IFERROR(AD53/AC53,"")
B54: 3 | D54: Team 3 | G54: 8 | I54: =IFERROR(H54/G54,"") -> 0 | J54: =SUMIF('[1]Total 2'!$I:$I,_xlfn.TEXTJOIN(" ",TRUE,'NEW ATD PER TEAM'!$D$51,'NEW ATD PER TEAM'!$D54),'[1]Total 2'!L:L) -> #VALUE! | K54: =J54*68/40 -> #VALUE! | L54: =SUMIF('[1]Total 2'!$I:$I,_xlfn.TEXTJOIN(" ",TRUE,'NEW ATD PER TEAM'!$D$51,'NEW ATD PER TEAM'!$D54),'[1]Total 2'!O:O) -> #VALUE! | M54: =IFERROR(L54/K54,0) -> 0 | N54: =J54*68/24 -> #VALUE! | O54: =SUMIF('[1]Total 2'!$I:$I,_xlfn.TEXTJOIN(" ",TRUE,'NEW ATD PER TEAM'!$D$51,'NEW ATD PER TEAM'!$D54),'[1]Total 2'!R:R) -> #VALUE! | P54: =IFERROR(O54/N54,0) -> 0 | Q54: =J54*68/24 -> #VALUE! | R54: =SUMIF('[1]Total 2'!$I:$I,_xlfn.TEXTJOIN(" ",TRUE,'NEW ATD PER TEAM'!$D$51,'NEW ATD PER TEAM'!$D54),'[1]Total 2'!U:U) -> #VALUE! | S54: =IFERROR(R54/Q54,0) -> 0 | T54: =J54*68/12 -> #VALUE! | U54: =SUMIF('[1]Total 2'!$I:$I,_xlfn.TEXTJOIN(" ",TRUE,'NEW ATD PER TEAM'!$D$51,'NEW ATD PER TEAM'!$D54),'[1]Total 2'!X:X) -> #VALUE! | V54: =IFERROR(U54/T54,0) -> 0 | W54: =J54*68/12 -> #VALUE! | X54: =SUMIF('[1]Total 2'!$I:$I,_xlfn.TEXTJOIN(" ",TRUE,'NEW ATD PER TEAM'!$D$51,'NEW ATD PER TEAM'!$D54),'[1]Total 2'!AA:AA) -> #VALUE! | Y54: =IFERROR(X54/W54,0) -> 0 | Z54: =SUMIF('[1]Total 2'!$I:$I,_xlfn.TEXTJOIN(" ",TRUE,'NEW ATD PER TEAM'!$D$51,'NEW ATD PER TEAM'!$D54),'[1]Total 2'!AC:AC) -> #VALUE! | AA54: =SUMIF('[1]Total 2'!$I:$I,_xlfn.TEXTJOIN(" ",TRUE,'NEW ATD PER TEAM'!$D$51,'NEW ATD PER TEAM'!$D54),'[1]Total 2'!AD:AD) -> #VALUE! | AC54: =J54*1854*40 -> #VALUE! | AD54: =AA54 -> #VALUE! | AE54: =IFERROR(AD54/AC54,"")
B55: 4 | D55: Team 4 | G55: 8 | I55: =IFERROR(H55/G55,"") -> 0 | J55: =SUMIF('[1]Total 2'!$I:$I,_xlfn.TEXTJOIN(" ",TRUE,'NEW ATD PER TEAM'!$D$51,'NEW ATD PER TEAM'!$D55),'[1]Total 2'!L:L) -> #VALUE! | K55: =J55*68/40 -> #VALUE! | L55: =SUMIF('[1]Total 2'!$I:$I,_xlfn.TEXTJOIN(" ",TRUE,'NEW ATD PER TEAM'!$D$51,'NEW ATD PER TEAM'!$D55),'[1]Total 2'!O:O) -> #VALUE! | M55: =IFERROR(L55/K55,0) -> 0 | N55: =J55*68/24 -> #VALUE! | O55: =SUMIF('[1]Total 2'!$I:$I,_xlfn.TEXTJOIN(" ",TRUE,'NEW ATD PER TEAM'!$D$51,'NEW ATD PER TEAM'!$D55),'[1]Total 2'!R:R) -> #VALUE! | P55: =IFERROR(O55/N55,0) -> 0 | Q55: =J55*68/24 -> #VALUE! | R55: =SUMIF('[1]Total 2'!$I:$I,_xlfn.TEXTJOIN(" ",TRUE,'NEW ATD PER TEAM'!$D$51,'NEW ATD PER TEAM'!$D55),'[1]Total 2'!U:U) -> #VALUE! | S55: =IFERROR(R55/Q55,0) -> 0 | T55: =J55*68/12 -> #VALUE! | U55: =SUMIF('[1]Total 2'!$I:$I,_xlfn.TEXTJOIN(" ",TRUE,'NEW ATD PER TEAM'!$D$51,'NEW ATD PER TEAM'!$D55),'[1]Total 2'!X:X) -> #VALUE! | V55: =IFERROR(U55/T55,0) -> 0 | W55: =J55*68/12 -> #VALUE! | X55: =SUMIF('[1]Total 2'!$I:$I,_xlfn.TEXTJOIN(" ",TRUE,'NEW ATD PER TEAM'!$D$51,'NEW ATD PER TEAM'!$D55),'[1]Total 2'!AA:AA) -> #VALUE! | Y55: =IFERROR(X55/W55,0) -> 0 | Z55: =SUMIF('[1]Total 2'!$I:$I,_xlfn.TEXTJOIN(" ",TRUE,'NEW ATD PER TEAM'!$D$51,'NEW ATD PER TEAM'!$D55),'[1]Total 2'!AC:AC) -> #VALUE! | AA55: =SUMIF('[1]Total 2'!$I:$I,_xlfn.TEXTJOIN(" ",TRUE,'NEW ATD PER TEAM'!$D$51,'NEW ATD PER TEAM'!$D55),'[1]Total 2'!AD:AD) -> #VALUE! | AC55: =J55*1854*40 -> #VALUE! | AD55: =AA55 -> #VALUE! | AE55: =IFERROR(AD55/AC55,"")
E56: TOTAL | G56: =SUM(G52:G55) -> 32 | H56: =SUM(H52:H55) -> 0 | I56: =IFERROR(H56/G56,"") -> 0 | J56: =SUM(J52:J55) -> #VALUE! | K56: =SUM(K52:K55) -> #VALUE! | L56: =SUM(L52:L55) -> #VALUE! | M56: =IFERROR(L56/K56,0) -> 0 | N56: =SUM(N52:N55) -> #VALUE! | O56: =SUM(O52:O55) -> #VALUE! | P56: =IFERROR(O56/N56,0) -> 0 | Q56: =SUM(Q52:Q55) -> #VALUE! | R56: =SUM(R52:R55) -> #VALUE! | S56: =IFERROR(R56/Q56,0) -> 0 | T56: =SUM(T52:T55) -> #VALUE! | U56: =SUM(U52:U55) -> #VALUE! | V56: =IFERROR(U56/T56,0) -> 0 | W56: =SUM(W52:W55) -> #VALUE! | X56: =SUM(X52:X55) -> #VALUE! | Y56: =IFERROR(X56/W56,0) -> 0 | Z56: =SUM(Z52:Z55) -> #VALUE! | AA56: =SUM(AA52:AA55) -> #VALUE! | AB56: =SUM(AB52:AB55) -> 0 | AC56: =SUM(AC52:AC55) -> #VALUE! | AD56: =SUM(AD52:AD55) -> #VALUE! | AE56: =IFERROR(AD56/AC56,"")
D57: BAYELSA | F57: Emmanuel
B58: 1 | D58: Team 1 | E58: Swali Market/Agudama Town Market | G58: 8 | I58: =IFERROR(H58/G58,"") -> 0 | J58: =SUMIF('[1]Total 2'!$I:$I,_xlfn.TEXTJOIN(" ",TRUE,'NEW ATD PER TEAM'!$D$57,'NEW ATD PER TEAM'!$D58),'[1]Total 2'!L:L) -> #VALUE! | K58: =J58*68/40 -> #VALUE! | L58: =SUMIF('[1]Total 2'!$I:$I,_xlfn.TEXTJOIN(" ",TRUE,'NEW ATD PER TEAM'!$D$57,'NEW ATD PER TEAM'!$D58),'[1]Total 2'!O:O) -> #VALUE! | M58: =IFERROR(L58/K58,0) -> 0 | N58: =J58*68/24 -> #VALUE! | O58: =SUMIF('[1]Total 2'!$I:$I,_xlfn.TEXTJOIN(" ",TRUE,'NEW ATD PER TEAM'!$D$57,'NEW ATD PER TEAM'!$D58),'[1]Total 2'!R:R) -> #VALUE! | P58: =IFERROR(O58/N58,0) -> 0 | Q58: =J58*68/24 -> #VALUE! | R58: =SUMIF('[1]Total 2'!$I:$I,_xlfn.TEXTJOIN(" ",TRUE,'NEW ATD PER TEAM'!$D$57,'NEW ATD PER TEAM'!$D58),'[1]Total 2'!U:U) -> #VALUE! | S58: =IFERROR(R58/Q58,0) -> 0 | T58: =J58*68/12 -> #VALUE! | U58: =SUMIF('[1]Total 2'!$I:$I,_xlfn.TEXTJOIN(" ",TRUE,'NEW ATD PER TEAM'!$D$57,'NEW ATD PER TEAM'!$D58),'[1]Total 2'!X:X) -> #VALUE! | V58: =IFERROR(U58/T58,0) -> 0 | W58: =J58*68/12 -> #VALUE! | X58: =SUMIF('[1]Total 2'!$I:$I,_xlfn.TEXTJOIN(" ",TRUE,'NEW ATD PER TEAM'!$D$57,'NEW ATD PER TEAM'!$D58),'[1]Total 2'!AA:AA) -> #VALUE! | Y58: =IFERROR(X58/W58,0) -> 0 | Z58: =SUMIF('[1]Total 2'!$I:$I,_xlfn.TEXTJOIN(" ",TRUE,'NEW ATD PER TEAM'!$D$57,'NEW ATD PER TEAM'!$D58),'[1]Total 2'!AC:AC) -> #VALUE! | AA58: =SUMIF('[1]Total 2'!$I:$I,_xlfn.TEXTJOIN(" ",TRUE,'NEW ATD PER TEAM'!$D$57,'NEW ATD PER TEAM'!$D58),'[1]Total 2'!AD:AD) -> #VALUE! | AC58: =J58*1854*40 -> #VALUE! | AD58: =AA58 -> #VALUE! | AE58: =IFERROR(AD58/AC58,"")
B59: 2 | D59: Team 2 | E59: Akaba Town/Yenizegene Town Market | G59: 8 | I59: =IFERROR(H59/G59,"") -> 0 | J59: =SUMIF('[1]Total 2'!$I:$I,_xlfn.TEXTJOIN(" ",TRUE,'NEW ATD PER TEAM'!$D$57,'NEW ATD PER TEAM'!$D59),'[1]Total 2'!L:L) -> #VALUE! | K59: =J59*68/40 -> #VALUE! | L59: =SUMIF('[1]Total 2'!$I:$I,_xlfn.TEXTJOIN(" ",TRUE,'NEW ATD PER TEAM'!$D$57,'NEW ATD PER TEAM'!$D59),'[1]Total 2'!O:O) -> #VALUE! | M59: =IFERROR(L59/K59,0) -> 0 | N59: =J59*68/24 -> #VALUE! | O59: =SUMIF('[1]Total 2'!$I:$I,_xlfn.TEXTJOIN(" ",TRUE,'NEW ATD PER TEAM'!$D$57,'NEW ATD PER TEAM'!$D59),'[1]Total 2'!R:R) -> #VALUE! | P59: =IFERROR(O59/N59,0) -> 0 | Q59: =J59*68/24 -> #VALUE! | R59: =SUMIF('[1]Total 2'!$I:$I,_xlfn.TEXTJOIN(" ",TRUE,'NEW ATD PER TEAM'!$D$57,'NEW ATD PER TEAM'!$D59),'[1]Total 2'!U:U) -> #VALUE! | S59: =IFERROR(R59/Q59,0) -> 0 | T59: =J59*68/12 -> #VALUE! | U59: =SUMIF('[1]Total 2'!$I:$I,_xlfn.TEXTJOIN(" ",TRUE,'NEW ATD PER TEAM'!$D$57,'NEW ATD PER TEAM'!$D59),'[1]Total 2'!X:X) -> #VALUE! | V59: =IFERROR(U59/T59,0) -> 0 | W59: =J59*68/12 -> #VALUE! | X59: =SUMIF('[1]Total 2'!$I:$I,_xlfn.TEXTJOIN(" ",TRUE,'NEW ATD PER TEAM'!$D$57,'NEW ATD PER TEAM'!$D59),'[1]Total 2'!AA:AA) -> #VALUE! | Y59: =IFERROR(X59/W59,0) -> 0 | Z59: =SUMIF('[1]Total 2'!$I:$I,_xlfn.TEXTJOIN(" ",TRUE,'NEW ATD PER TEAM'!$D$57,'NEW ATD PER TEAM'!$D59),'[1]Total 2'!AC:AC) -> #VALUE! | AA59: =SUMIF('[1]Total 2'!$I:$I,_xlfn.TEXTJOIN(" ",TRUE,'NEW ATD PER TEAM'!$D$57,'NEW ATD PER TEAM'!$D59),'[1]Total 2'!AD:AD) -> #VALUE! | AC59: =J59*1854*40 -> #VALUE! | AD59: =AA59 -> #VALUE! | AE59: =IFERROR(AD59/AC59,"")
B60: 3 | D60: Team 3 | G60: 8 | I60: =IFERROR(H60/G60,"") -> 0 | J60: =SUMIF('[1]Total 2'!$I:$I,_xlfn.TEXTJOIN(" ",TRUE,'NEW ATD PER TEAM'!$D$57,'NEW ATD PER TEAM'!$D60),'[1]Total 2'!L:L) -> #VALUE! | K60: =J60*68/40 -> #VALUE! | L60: =SUMIF('[1]Total 2'!$I:$I,_xlfn.TEXTJOIN(" ",TRUE,'NEW ATD PER TEAM'!$D$57,'NEW ATD PER TEAM'!$D60),'[1]Total 2'!O:O) -> #VALUE! | M60: =IFERROR(L60/K60,0) -> 0 | N60: =J60*68/24 -> #VALUE! | O60: =SUMIF('[1]Total 2'!$I:$I,_xlfn.TEXTJOIN(" ",TRUE,'NEW ATD PER TEAM'!$D$57,'NEW ATD PER TEAM'!$D60),'[1]Total 2'!R:R) -> #VALUE! | P60: =IFERROR(O60/N60,0) -> 0 | Q60: =J60*68/24 -> #VALUE! | R60: =SUMIF('[1]Total 2'!$I:$I,_xlfn.TEXTJOIN(" ",TRUE,'NEW ATD PER TEAM'!$D$57,'NEW ATD PER TEAM'!$D60),'[1]Total 2'!U:U) -> #VALUE! | S60: =IFERROR(R60/Q60,0) -> 0 | T60: =J60*68/12 -> #VALUE! | U60: =SUMIF('[1]Total 2'!$I:$I,_xlfn.TEXTJOIN(" ",TRUE,'NEW ATD PER TEAM'!$D$57,'NEW ATD PER TEAM'!$D60),'[1]Total 2'!X:X) -> #VALUE! | V60: =IFERROR(U60/T60,0) -> 0 | W60: =J60*68/12 -> #VALUE! | X60: =SUMIF('[1]Total 2'!$I:$I,_xlfn.TEXTJOIN(" ",TRUE,'NEW ATD PER TEAM'!$D$57,'NEW ATD PER TEAM'!$D60),'[1]Total 2'!AA:AA) -> #VALUE! | Y60: =IFERROR(X60/W60,0) -> 0 | Z60: =SUMIF('[1]Total 2'!$I:$I,_xlfn.TEXTJOIN(" ",TRUE,'NEW ATD PER TEAM'!$D$57,'NEW ATD PER TEAM'!$D60),'[1]Total 2'!AC:AC) -> #VALUE! | AA60: =SUMIF('[1]Total 2'!$I:$I,_xlfn.TEXTJOIN(" ",TRUE,'NEW ATD PER TEAM'!$D$57,'NEW ATD PER TEAM'!$D60),'[1]Total 2'!AD:AD) -> #VALUE! | AC60: =J60*1854*40 -> #VALUE! | AD60: =AA60 -> #VALUE! | AE60: =IFERROR(AD60/AC60,"")
B61: 4 | D61: Team 4 | G61: 8 | I61: =IFERROR(H61/G61,"") -> 0 | J61: =SUMIF('[1]Total 2'!$I:$I,_xlfn.TEXTJOIN(" ",TRUE,'NEW ATD PER TEAM'!$D$57,'NEW ATD PER TEAM'!$D61),'[1]Total 2'!L:L) -> #VALUE! | K61: =J61*68/40 -> #VALUE! | L61: =SUMIF('[1]Total 2'!$I:$I,_xlfn.TEXTJOIN(" ",TRUE,'NEW ATD PER TEAM'!$D$57,'NEW ATD PER TEAM'!$D61),'[1]Total 2'!O:O) -> #VALUE! | M61: =IFERROR(L61/K61,0) -> 0 | N61: =J61*68/24 -> #VALUE! | O61: =SUMIF('[1]Total 2'!$I:$I,_xlfn.TEXTJOIN(" ",TRUE,'NEW ATD PER TEAM'!$D$57,'NEW ATD PER TEAM'!$D61),'[1]Total 2'!R:R) -> #VALUE! | P61: =IFERROR(O61/N61,0) -> 0 | Q61: =J61*68/24 -> #VALUE! | R61: =SUMIF('[1]Total 2'!$I:$I,_xlfn.TEXTJOIN(" ",TRUE,'NEW ATD PER TEAM'!$D$57,'NEW ATD PER TEAM'!$D61),'[1]Total 2'!U:U) -> #VALUE! | S61: =IFERROR(R61/Q61,0) -> 0 | T61: =J61*68/12 -> #VALUE! | U61: =SUMIF('[1]Total 2'!$I:$I,_xlfn.TEXTJOIN(" ",TRUE,'NEW ATD PER TEAM'!$D$57,'NEW ATD PER TEAM'!$D61),'[1]Total 2'!X:X) -> #VALUE! | V61: =IFERROR(U61/T61,0) -> 0 | W61: =J61*68/12 -> #VALUE! | X61: =SUMIF('[1]Total 2'!$I:$I,_xlfn.TEXTJOIN(" ",TRUE,'NEW ATD PER TEAM'!$D$57,'NEW ATD PER TEAM'!$D61),'[1]Total 2'!AA:AA) -> #VALUE! | Y61: =IFERROR(X61/W61,0) -> 0 | Z61: =SUMIF('[1]Total 2'!$I:$I,_xlfn.TEXTJOIN(" ",TRUE,'NEW ATD PER TEAM'!$D$57,'NEW ATD PER TEAM'!$D61),'[1]Total 2'!AC:AC) -> #VALUE! | AA61: =SUMIF('[1]Total 2'!$I:$I,_xlfn.TEXTJOIN(" ",TRUE,'NEW ATD PER TEAM'!$D$57,'NEW ATD PER TEAM'!$D61),'[1]Total 2'!AD:AD) -> #VALUE! | AC61: =J61*1854*40 -> #VALUE! | AD61: =AA61 -> #VALUE! | AE61: =IFERROR(AD61/AC61,"")
E62: TOTAL | G62: =SUM(G58:G61) -> 32 | H62: =SUM(H58:H61) -> 0 | I62: =IFERROR(H62/G62,"") -> 0 | J62: =SUM(J58:J61) -> #VALUE! | K62: =SUM(K58:K61) -> #VALUE! | L62: =SUM(L58:L61) -> #VALUE! | M62: =IFERROR(L62/K62,0) -> 0 | N62: =SUM(N58:N61) -> #VALUE! | O62: =SUM(O58:O61) -> #VALUE! | P62: =IFERROR(O62/N62,0) -> 0 | Q62: =SUM(Q58:Q61) -> #VALUE! | R62: =SUM(R58:R61) -> #VALUE! | S62: =IFERROR(R62/Q62,0) -> 0 | T62: =SUM(T58:T61) -> #VALUE! | U62: =SUM(U58:U61) -> #VALUE! | V62: =IFERROR(U62/T62,0) -> 0 | W62: =SUM(W58:W61) -> #VALUE! | X62: =SUM(X58:X61) -> #VALUE! | Y62: =IFERROR(X62/W62,0) -> 0 | Z62: =SUM(Z58:Z61) -> #VALUE! | AA62: =SUM(AA58:AA61) -> #VALUE! | AB62: =SUM(AB58:AB61) -> 0 | AC62: =SUM(AC58:AC61) -> #VALUE! | AD62: =SUM(AD58:AD61) -> #VALUE! | AE62: =IFERROR(AD62/AC62,"")
D63: UYO | F63: IFEANYI ESTER AKPATI
B64: 1 | D64: Team 1 | E64: Urau Market/Akpan Andem Market | G64: 8 | H64: 4 | I64: =IFERROR(H64/G64,"") -> 0.5 | J64: =SUMIF('[1]Total 2'!$I:$I,_xlfn.TEXTJOIN(" ",TRUE,'NEW ATD PER TEAM'!$D$63,'NEW ATD PER TEAM'!$D64),'[1]Total 2'!L:L) -> #VALUE! | K64: =J64*68/40 -> #VALUE! | L64: =SUMIF('[1]Total 2'!$I:$I,_xlfn.TEXTJOIN(" ",TRUE,'NEW ATD PER TEAM'!$D$63,'NEW ATD PER TEAM'!$D64),'[1]Total 2'!O:O) -> #VALUE! | M64: =IFERROR(L64/K64,0) -> 0 | N64: =J64*68/24 -> #VALUE! | O64: =SUMIF('[1]Total 2'!$I:$I,_xlfn.TEXTJOIN(" ",TRUE,'NEW ATD PER TEAM'!$D$63,'NEW ATD PER TEAM'!$D64),'[1]Total 2'!R:R) -> #VALUE! | P64: =IFERROR(O64/N64,0) -> 0 | Q64: =J64*68/24 -> #VALUE! | R64: =SUMIF('[1]Total 2'!$I:$I,_xlfn.TEXTJOIN(" ",TRUE,'NEW ATD PER TEAM'!$D$63,'NEW ATD PER TEAM'!$D64),'[1]Total 2'!U:U) -> #VALUE! | S64: =IFERROR(R64/Q64,0) -> 0 | T64: =J64*68/12 -> #VALUE! | U64: =SUMIF('[1]Total 2'!$I:$I,_xlfn.TEXTJOIN(" ",TRUE,'NEW ATD PER TEAM'!$D$63,'NEW ATD PER TEAM'!$D64),'[1]Total 2'!X:X) -> #VALUE! | V64: =IFERROR(U64/T64,0) -> 0 | W64: =J64*68/12 -> #VALUE! | X64: =SUMIF('[1]Total 2'!$I:$I,_xlfn.TEXTJOIN(" ",TRUE,'NEW ATD PER TEAM'!$D$63,'NEW ATD PER TEAM'!$D64),'[1]Total 2'!AA:AA) -> #VALUE! | Y64: =IFERROR(X64/W64,0) -> 0 | Z64: =SUMIF('[1]Total 2'!$I:$I,_xlfn.TEXTJOIN(" ",TRUE,'NEW ATD PER TEAM'!$D$63,'NEW ATD PER TEAM'!$D64),'[1]Total 2'!AC:AC) -> #VALUE! | AA64: =SUMIF('[1]Total 2'!$I:$I,_xlfn.TEXTJOIN(" ",TRUE,'NEW ATD PER TEAM'!$D$63,'NEW ATD PER TEAM'!$D64),'[1]Total 2'!AD:AD) -> #VALUE! | AC64: =J64*1854*40 -> #VALUE! | AD64: =AA64 -> #VALUE! | AE64: =IFERROR(AD64/AC64,"")
B65: 2 | D65: Team 2 | E65: Ifa Market/Urua Mbakara | G65: 8 | H65: 4 | I65: =IFERROR(H65/G65,"") -> 0.5 | J65: =SUMIF('[1]Total 2'!$I:$I,_xlfn.TEXTJOIN(" ",TRUE,'NEW ATD PER TEAM'!$D$63,'NEW ATD PER TEAM'!$D65),'[1]Total 2'!L:L) -> #VALUE! | K65: =J65*68/40 -> #VALUE! | L65: =SUMIF('[1]Total 2'!$I:$I,_xlfn.TEXTJOIN(" ",TRUE,'NEW ATD PER TEAM'!$D$63,'NEW ATD PER TEAM'!$D65),'[1]Total 2'!O:O) -> #VALUE! | M65: =IFERROR(L65/K65,0) -> 0 | N65: =J65*68/24 -> #VALUE! | O65: =SUMIF('[1]Total 2'!$I:$I,_xlfn.TEXTJOIN(" ",TRUE,'NEW ATD PER TEAM'!$D$63,'NEW ATD PER TEAM'!$D65),'[1]Total 2'!R:R) -> #VALUE! | P65: =IFERROR(O65/N65,0) -> 0 | Q65: =J65*68/24 -> #VALUE! | R65: =SUMIF('[1]Total 2'!$I:$I,_xlfn.TEXTJOIN(" ",TRUE,'NEW ATD PER TEAM'!$D$63,'NEW ATD PER TEAM'!$D65),'[1]Total 2'!U:U) -> #VALUE! | S65: =IFERROR(R65/Q65,0) -> 0 | T65: =J65*68/12 -> #VALUE! | U65: =SUMIF('[1]Total 2'!$I:$I,_xlfn.TEXTJOIN(" ",TRUE,'NEW ATD PER TEAM'!$D$63,'NEW ATD PER TEAM'!$D65),'[1]Total 2'!X:X) -> #VALUE! | V65: =IFERROR(U65/T65,0) -> 0 | W65: =J65*68/12 -> #VALUE! | X65: =SUMIF('[1]Total 2'!$I:$I,_xlfn.TEXTJOIN(" ",TRUE,'NEW ATD PER TEAM'!$D$63,'NEW ATD PER TEAM'!$D65),'[1]Total 2'!AA:AA) -> #VALUE! | Y65: =IFERROR(X65/W65,0) -> 0 | Z65: =SUMIF('[1]Total 2'!$I:$I,_xlfn.TEXTJOIN(" ",TRUE,'NEW ATD PER TEAM'!$D$63,'NEW ATD PER TEAM'!$D65),'[1]Total 2'!AC:AC) -> #VALUE! | AA65: =SUMIF('[1]Total 2'!$I:$I,_xlfn.TEXTJOIN(" ",TRUE,'NEW ATD PER TEAM'!$D$63,'NEW ATD PER TEAM'!$D65),'[1]Total 2'!AD:AD) -> #VALUE! | AC65: =J65*1854*40 -> #VALUE! | AD65: =AA65 -> #VALUE! | AE65: =IFERROR(AD65/AC65,"")
B66: 3 | D66: Team 3 | G66: 8 | I66: =IFERROR(H66/G66,"") -> 0 | J66: =SUMIF('[1]Total 2'!$I:$I,_xlfn.TEXTJOIN(" ",TRUE,'NEW ATD PER TEAM'!$D$63,'NEW ATD PER TEAM'!$D66),'[1]Total 2'!L:L) -> #VALUE! | K66: =J66*68/40 -> #VALUE! | L66: =SUMIF('[1]Total 2'!$I:$I,_xlfn.TEXTJOIN(" ",TRUE,'NEW ATD PER TEAM'!$D$63,'NEW ATD PER TEAM'!$D66),'[1]Total 2'!O:O) -> #VALUE! | M66: =IFERROR(L66/K66,0) -> 0 | N66: =J66*68/24 -> #VALUE! | O66: =SUMIF('[1]Total 2'!$I:$I,_xlfn.TEXTJOIN(" ",TRUE,'NEW ATD PER TEAM'!$D$63,'NEW ATD PER TEAM'!$D66),'[1]Total 2'!R:R) -> #VALUE! | P66: =IFERROR(O66/N66,0) -> 0 | Q66: =J66*68/24 -> #VALUE! | R66: =SUMIF('[1]Total 2'!$I:$I,_xlfn.TEXTJOIN(" ",TRUE,'NEW ATD PER TEAM'!$D$63,'NEW ATD PER TEAM'!$D66),'[1]Total 2'!U:U) -> #VALUE! | S66: =IFERROR(R66/Q66,0) -> 0 | T66: =J66*68/12 -> #VALUE! | U66: =SUMIF('[1]Total 2'!$I:$I,_xlfn.TEXTJOIN(" ",TRUE,'NEW ATD PER TEAM'!$D$63,'NEW ATD PER TEAM'!$D66),'[1]Total 2'!X:X) -> #VALUE! | V66: =IFERROR(U66/T66,0) -> 0 | W66: =J66*68/12 -> #VALUE! | X66: =SUMIF('[1]Total 2'!$I:$I,_xlfn.TEXTJOIN(" ",TRUE,'NEW ATD PER TEAM'!$D$63,'NEW ATD PER TEAM'!$D66),'[1]Total 2'!AA:AA) -> #VALUE! | Y66: =IFERROR(X66/W66,0) -> 0 | Z66: =SUMIF('[1]Total 2'!$I:$I,_xlfn.TEXTJOIN(" ",TRUE,'NEW ATD PER TEAM'!$D$63,'NEW ATD PER TEAM'!$D66),'[1]Total 2'!AC:AC) -> #VALUE! | AA66: =SUMIF('[1]Total 2'!$I:$I,_xlfn.TEXTJOIN(" ",TRUE,'NEW ATD PER TEAM'!$D$63,'NEW ATD PER TEAM'!$D66),'[1]Total 2'!AD:AD) -> #VALUE! | AC66: =J66*1854*40 -> #VALUE! | AD66: =AA66 -> #VALUE! | AE66: =IFERROR(AD66/AC66,"")
B67: 4 | D67: Team 4 | G67: 8 | I67: =IFERROR(H67/G67,"") -> 0 | J67: =SUMIF('[1]Total 2'!$I:$I,_xlfn.TEXTJOIN(" ",TRUE,'NEW ATD PER TEAM'!$D$63,'NEW ATD PER TEAM'!$D67),'[1]Total 2'!L:L) -> #VALUE! | K67: =J67*68/40 -> #VALUE! | L67: =SUMIF('[1]Total 2'!$I:$I,_xlfn.TEXTJOIN(" ",TRUE,'NEW ATD PER TEAM'!$D$63,'NEW ATD PER TEAM'!$D67),'[1]Total 2'!O:O) -> #VALUE! | M67: =IFERROR(L67/K67,0) -> 0 | N67: =J67*68/24 -> #VALUE! | O67: =SUMIF('[1]Total 2'!$I:$I,_xlfn.TEXTJOIN(" ",TRUE,'NEW ATD PER TEAM'!$D$63,'NEW ATD PER TEAM'!$D67),'[1]Total 2'!R:R) -> #VALUE! | P67: =IFERROR(O67/N67,0) -> 0 | Q67: =J67*68/24 -> #VALUE! | R67: =SUMIF('[1]Total 2'!$I:$I,_xlfn.TEXTJOIN(" ",TRUE,'NEW ATD PER TEAM'!$D$63,'NEW ATD PER TEAM'!$D67),'[1]Total 2'!U:U) -> #VALUE! | S67: =IFERROR(R67/Q67,0) -> 0 | T67: =J67*68/12 -> #VALUE! | U67: =SUMIF('[1]Total 2'!$I:$I,_xlfn.TEXTJOIN(" ",TRUE,'NEW ATD PER TEAM'!$D$63,'NEW ATD PER TEAM'!$D67),'[1]Total 2'!X:X) -> #VALUE! | V67: =IFERROR(U67/T67,0) -> 0 | W67: =J67*68/12 -> #VALUE! | X67: =SUMIF('[1]Total 2'!$I:$I,_xlfn.TEXTJOIN(" ",TRUE,'NEW ATD PER TEAM'!$D$63,'NEW ATD PER TEAM'!$D67),'[1]Total 2'!AA:AA) -> #VALUE! | Y67: =IFERROR(X67/W67,0) -> 0 | Z67: =SUMIF('[1]Total 2'!$I:$I,_xlfn.TEXTJOIN(" ",TRUE,'NEW ATD PER TEAM'!$D$63,'NEW ATD PER TEAM'!$D67),'[1]Total 2'!AC:AC) -> #VALUE! | AA67: =SUMIF('[1]Total 2'!$I:$I,_xlfn.TEXTJOIN(" ",TRUE,'NEW ATD PER TEAM'!$D$63,'NEW ATD PER TEAM'!$D67),'[1]Total 2'!AD:AD) -> #VALUE! | AC67: =J67*1854*40 -> #VALUE! | AD67: =AA67 -> #VALUE! | AE67: =IFERROR(AD67/AC67,"")
E68: TOTAL | G68: =SUM(G64:G67) -> 32 | H68: =SUM(H64:H67) -> 8 | I68: =IFERROR(H68/G68,"") -> 0.25 | J68: =SUM(J64:J67) -> #VALUE! | K68: =SUM(K64:K67) -> #VALUE! | L68: =SUM(L64:L67) -> #VALUE! | M68: =IFERROR(L68/K68,0) -> 0 | N68: =SUM(N64:N67) -> #VALUE! | O68: =SUM(O64:O67) -> #VALUE! | P68: =IFERROR(O68/N68,0) -> 0 | Q68: =SUM(Q64:Q67) -> #VALUE! | R68: =SUM(R64:R67) -> #VALUE! | S68: =IFERROR(R68/Q68,0) -> 0 | T68: =SUM(T64:T67) -> #VALUE! | U68: =SUM(U64:U67) -> #VALUE! | V68: =IFERROR(U68/T68,0) -> 0 | W68: =SUM(W64:W67) -> #VALUE! | X68: =SUM(X64:X67) -> #VALUE! | Y68: =IFERROR(X68/W68,0) -> 0 | Z68: =SUM(Z64:Z67) -> #VALUE! | AA68: =SUM(AA64:AA67) -> #VALUE! | AB68: =SUM(AB64:AB67) -> 0 | AC68: =SUM(AC64:AC67) -> #VALUE! | AD68: =SUM(AD64:AD67) -> #VALUE! | AE68: =IFERROR(AD68/AC68,"")
D69: CALABAR | F69: ENOIDEM AKPAN
B70: 1 | D70: Team 1 | E70: Ekpo Abasi/Satelite Town & Edim Otop | G70: 8 | I70: =IFERROR(H70/G70,"") -> 0 | J70: =SUMIF('[1]Total 2'!$I:$I,_xlfn.TEXTJOIN(" ",TRUE,'NEW ATD PER TEAM'!$D$69,'NEW ATD PER TEAM'!$D70),'[1]Total 2'!L:L) -> #VALUE! | K70: =J70*68/40 -> #VALUE! | L70: =SUMIF('[1]Total 2'!$I:$I,_xlfn.TEXTJOIN(" ",TRUE,'NEW ATD PER TEAM'!$D$69,'NEW ATD PER TEAM'!$D70),'[1]Total 2'!O:O) -> #VALUE! | M70: =IFERROR(L70/K70,0) -> 0 | N70: =J70*68/24 -> #VALUE! | O70: =SUMIF('[1]Total 2'!$I:$I,_xlfn.TEXTJOIN(" ",TRUE,'NEW ATD PER TEAM'!$D$69,'NEW ATD PER TEAM'!$D70),'[1]Total 2'!R:R) -> #VALUE! | P70: =IFERROR(O70/N70,0) -> 0 | Q70: =J70*68/24 -> #VALUE! | R70: =SUMIF('[1]Total 2'!$I:$I,_xlfn.TEXTJOIN(" ",TRUE,'NEW ATD PER TEAM'!$D$69,'NEW ATD PER TEAM'!$D70),'[1]Total 2'!U:U) -> #VALUE! | S70: =IFERROR(R70/Q70,0) -> 0 | T70: =J70*68/12 -> #VALUE! | U70: =SUMIF('[1]Total 2'!$I:$I,_xlfn.TEXTJOIN(" ",TRUE,'NEW ATD PER TEAM'!$D$69,'NEW ATD PER TEAM'!$D70),'[1]Total 2'!X:X) -> #VALUE! | V70: =IFERROR(U70/T70,0) -> 0 | W70: =J70*68/12 -> #VALUE! | X70: =SUMIF('[1]Total 2'!$I:$I,_xlfn.TEXTJOIN(" ",TRUE,'NEW ATD PER TEAM'!$D$69,'NEW ATD PER TEAM'!$D70),'[1]Total 2'!AA:AA) -> #VALUE! | Y70: =IFERROR(X70/W70,0) -> 0 | Z70: =SUMIF('[1]Total 2'!$I:$I,_xlfn.TEXTJOIN(" ",TRUE,'NEW ATD PER TEAM'!$D$69,'NEW ATD PER TEAM'!$D70),'[1]Total 2'!AC:AC) -> #VALUE! | AA70: =SUMIF('[1]Total 2'!$I:$I,_xlfn.TEXTJOIN(" ",TRUE,'NEW ATD PER TEAM'!$D$69,'NEW ATD PER TEAM'!$D70),'[1]Total 2'!AD:AD) -> #VALUE! | AC70: =J70*1854*40 -> #VALUE! | AD70: =AA70 -> #VALUE! | AE70: =IFERROR(AD70/AC70,"")
B71: 2 | D71: Team 2 | E71: Etim Edem Market/Etim Edem Street & Goldie by Bedwell | G71: 8 | I71: =IFERROR(H71/G71,"") -> 0 | J71: =SUMIF('[1]Total 2'!$I:$I,_xlfn.TEXTJOIN(" ",TRUE,'NEW ATD PER TEAM'!$D$69,'NEW ATD PER TEAM'!$D71),'[1]Total 2'!L:L) -> #VALUE! | K71: =J71*68/40 -> #VALUE! | L71: =SUMIF('[1]Total 2'!$I:$I,_xlfn.TEXTJOIN(" ",TRUE,'NEW ATD PER TEAM'!$D$69,'NEW ATD PER TEAM'!$D71),'[1]Total 2'!O:O) -> #VALUE! | M71: =IFERROR(L71/K71,0) -> 0 | N71: =J71*68/24 -> #VALUE! | O71: =SUMIF('[1]Total 2'!$I:$I,_xlfn.TEXTJOIN(" ",TRUE,'NEW ATD PER TEAM'!$D$69,'NEW ATD PER TEAM'!$D71),'[1]Total 2'!R:R) -> #VALUE! | P71: =IFERROR(O71/N71,0) -> 0 | Q71: =J71*68/24 -> #VALUE! | R71: =SUMIF('[1]Total 2'!$I:$I,_xlfn.TEXTJOIN(" ",TRUE,'NEW ATD PER TEAM'!$D$69,'NEW ATD PER TEAM'!$D71),'[1]Total 2'!U:U) -> #VALUE! | S71: =IFERROR(R71/Q71,0) -> 0 | T71: =J71*68/12 -> #VALUE! | U71: =SUMIF('[1]Total 2'!$I:$I,_xlfn.TEXTJOIN(" ",TRUE,'NEW ATD PER TEAM'!$D$69,'NEW ATD PER TEAM'!$D71),'[1]Total 2'!X:X) -> #VALUE! | V71: =IFERROR(U71/T71,0) -> 0 | W71: =J71*68/12 -> #VALUE! | X71: =SUMIF('[1]Total 2'!$I:$I,_xlfn.TEXTJOIN(" ",TRUE,'NEW ATD PER TEAM'!$D$69,'NEW ATD PER TEAM'!$D71),'[1]Total 2'!AA:AA) -> #VALUE! | Y71: =IFERROR(X71/W71,0) -> 0 | Z71: =SUMIF('[1]Total 2'!$I:$I,_xlfn.TEXTJOIN(" ",TRUE,'NEW ATD PER TEAM'!$D$69,'NEW ATD PER TEAM'!$D71),'[1]Total 2'!AC:AC) -> #VALUE! | AA71: =SUMIF('[1]Total 2'!$I:$I,_xlfn.TEXTJOIN(" ",TRUE,'NEW ATD PER TEAM'!$D$69,'NEW ATD PER TEAM'!$D71),'[1]Total 2'!AD:AD) -> #VALUE! | AC71: =J71*1854*40 -> #VALUE! | AD71: =AA71 -> #VALUE! | AE71: =IFERROR(AD71/AC71,"")
B72: 3 | D72: Team 3 | E72: Marian | G72: 8 | I72: =IFERROR(H72/G72,"") -> 0 | J72: =SUMIF('[1]Total 2'!$I:$I,_xlfn.TEXTJOIN(" ",TRUE,'NEW ATD PER TEAM'!$D$69,'NEW ATD PER TEAM'!$D72),'[1]Total 2'!L:L) -> #VALUE! | K72: =J72*68/40 -> #VALUE! | L72: =SUMIF('[1]Total 2'!$I:$I,_xlfn.TEXTJOIN(" ",TRUE,'NEW ATD PER TEAM'!$D$69,'NEW ATD PER TEAM'!$D72),'[1]Total 2'!O:O) -> #VALUE! | M72: =IFERROR(L72/K72,0) -> 0 | N72: =J72*68/24 -> #VALUE! | O72: =SUMIF('[1]Total 2'!$I:$I,_xlfn.TEXTJOIN(" ",TRUE,'NEW ATD PER TEAM'!$D$69,'NEW ATD PER TEAM'!$D72),'[1]Total 2'!R:R) -> #VALUE! | P72: =IFERROR(O72/N72,0) -> 0 | Q72: =J72*68/24 -> #VALUE! | R72: =SUMIF('[1]Total 2'!$I:$I,_xlfn.TEXTJOIN(" ",TRUE,'NEW ATD PER TEAM'!$D$69,'NEW ATD PER TEAM'!$D72),'[1]Total 2'!U:U) -> #VALUE! | S72: =IFERROR(R72/Q72,0) -> 0 | T72: =J72*68/12 -> #VALUE! | U72: =SUMIF('[1]Total 2'!$I:$I,_xlfn.TEXTJOIN(" ",TRUE,'NEW ATD PER TEAM'!$D$69,'NEW ATD PER TEAM'!$D72),'[1]Total 2'!X:X) -> #VALUE! | V72: =IFERROR(U72/T72,0) -> 0 | W72: =J72*68/12 -> #VALUE! | X72: =SUMIF('[1]Total 2'!$I:$I,_xlfn.TEXTJOIN(" ",TRUE,'NEW ATD PER TEAM'!$D$69,'NEW ATD PER TEAM'!$D72),'[1]Total 2'!AA:AA) -> #VALUE! | Y72: =IFERROR(X72/W72,0) -> 0 | Z72: =SUMIF('[1]Total 2'!$I:$I,_xlfn.TEXTJOIN(" ",TRUE,'NEW ATD PER TEAM'!$D$69,'NEW ATD PER TEAM'!$D72),'[1]Total 2'!AC:AC) -> #VALUE! | AA72: =SUMIF('[1]Total 2'!$I:$I,_xlfn.TEXTJOIN(" ",TRUE,'NEW ATD PER TEAM'!$D$69,'NEW ATD PER TEAM'!$D72),'[1]Total 2'!AD:AD) -> #VALUE! | AC72: =J72*1854*40 -> #VALUE! | AD72: =AA72 -> #VALUE! | AE72: =IFERROR(AD72/AC72,"")
B73: 4 | D73: Team 4 | G73: 8 | I73: =IFERROR(H73/G73,"") -> 0 | J73: =SUMIF('[1]Total 2'!$I:$I,_xlfn.TEXTJOIN(" ",TRUE,'NEW ATD PER TEAM'!$D$69,'NEW ATD PER TEAM'!$D73),'[1]Total 2'!L:L) -> #VALUE! | K73: =J73*68/40 -> #VALUE! | L73: =SUMIF('[1]Total 2'!$I:$I,_xlfn.TEXTJOIN(" ",TRUE,'NEW ATD PER TEAM'!$D$69,'NEW ATD PER TEAM'!$D73),'[1]Total 2'!O:O) -> #VALUE! | M73: =IFERROR(L73/K73,0) -> 0 | N73: =J73*68/24 -> #VALUE! | O73: =SUMIF('[1]Total 2'!$I:$I,_xlfn.TEXTJOIN(" ",TRUE,'NEW ATD PER TEAM'!$D$69,'NEW ATD PER TEAM'!$D73),'[1]Total 2'!R:R) -> #VALUE! | P73: =IFERROR(O73/N73,0) -> 0 | Q73: =J73*68/24 -> #VALUE! | R73: =SUMIF('[1]Total 2'!$I:$I,_xlfn.TEXTJOIN(" ",TRUE,'NEW ATD PER TEAM'!$D$69,'NEW ATD PER TEAM'!$D73),'[1]Total 2'!U:U) -> #VALUE! | S73: =IFERROR(R73/Q73,0) -> 0 | T73: =J73*68/12 -> #VALUE! | U73: =SUMIF('[1]Total 2'!$I:$I,_xlfn.TEXTJOIN(" ",TRUE,'NEW ATD PER TEAM'!$D$69,'NEW ATD PER TEAM'!$D73),'[1]Total 2'!X:X) -> #VALUE! | V73: =IFERROR(U73/T73,0) -> 0 | W73: =J73*68/12 -> #VALUE! | X73: =SUMIF('[1]Total 2'!$I:$I,_xlfn.TEXTJOIN(" ",TRUE,'NEW ATD PER TEAM'!$D$69,'NEW ATD PER TEAM'!$D73),'[1]Total 2'!AA:AA) -> #VALUE! | Y73: =IFERROR(X73/W73,0) -> 0 | Z73: =SUMIF('[1]Total 2'!$I:$I,_xlfn.TEXTJOIN(" ",TRUE,'NEW ATD PER TEAM'!$D$69,'NEW ATD PER TEAM'!$D73),'[1]Total 2'!AC:AC) -> #VALUE! | AA73: =SUMIF('[1]Total 2'!$I:$I,_xlfn.TEXTJOIN(" ",TRUE,'NEW ATD PER TEAM'!$D$69,'NEW ATD PER TEAM'!$D73),'[1]Total 2'!AD:AD) -> #VALUE! | AC73: =J73*1854*40 -> #VALUE! | AD73: =AA73 -> #VALUE! | AE73: =IFERROR(AD73/AC73,"")
E74: TOTAL | G74: =SUM(G70:G73) -> 32 | H74: =SUM(H70:H73) -> 0 | I74: =IFERROR(H74/G74,"") -> 0 | J74: =SUM(J70:J73) -> #VALUE! | K74: =SUM(K70:K73) -> #VALUE! | L74: =SUM(L70:L73) -> #VALUE! | M74: =IFERROR(L74/K74,0) -> 0 | N74: =SUM(N70:N73) -> #VALUE! | O74: =SUM(O70:O73) -> #VALUE! | P74: =IFERROR(O74/N74,0) -> 0 | Q74: =SUM(Q70:Q73) -> #VALUE! | R74: =SUM(R70:R73) -> #VALUE! | S74: =IFERROR(R74/Q74,0) -> 0 | T74: =SUM(T70:T73) -> #VALUE! | U74: =SUM(U70:U73) -> #VALUE! | V74: =IFERROR(U74/T74,0) -> 0 | W74: =SUM(W70:W73) -> #VALUE! | X74: =SUM(X70:X73) -> #VALUE! | Y74: =IFERROR(X74/W74,0) -> 0 | Z74: =SUM(Z70:Z73) -> #VALUE! | AA74: =SUM(AA70:AA73) -> #VALUE! | AB74: =SUM(AB70:AB73) -> 0 | AC74: =SUM(AC70:AC73) -> #VALUE! | AD74: =SUM(AD70:AD73) -> #VALUE! | AE74: =IFERROR(AD74/AC74,"")
C75: West 1 | D75: IBADAN I | F75: OWOLABI TOLULOPE
B76: 1 | D76: Team 1 | E76: GBAGI/IWO ROAD | G76: 8 | H76: 4 | I76: =IFERROR(H76/G76,"") -> 0.5 | J76: =SUMIF('[1]Total 2'!$I:$I,_xlfn.TEXTJOIN(" ",TRUE,'NEW ATD PER TEAM'!$D$75,'NEW ATD PER TEAM'!$D76),'[1]Total 2'!L:L) -> #VALUE! | K76: =J76*68/40 -> #VALUE! | L76: =SUMIF('[1]Total 2'!$I:$I,_xlfn.TEXTJOIN(" ",TRUE,'NEW ATD PER TEAM'!$D$75,'NEW ATD PER TEAM'!$D76),'[1]Total 2'!O:O) -> #VALUE! | M76: =IFERROR(L76/K76,0) -> 0 | N76: =J76*68/24 -> #VALUE! | O76: =SUMIF('[1]Total 2'!$I:$I,_xlfn.TEXTJOIN(" ",TRUE,'NEW ATD PER TEAM'!$D$75,'NEW ATD PER TEAM'!$D76),'[1]Total 2'!R:R) -> #VALUE! | P76: =IFERROR(O76/N76,0) -> 0 | Q76: =J76*68/24 -> #VALUE! | R76: =SUMIF('[1]Total 2'!$I:$I,_xlfn.TEXTJOIN(" ",TRUE,'NEW ATD PER TEAM'!$D$75,'NEW ATD PER TEAM'!$D76),'[1]Total 2'!U:U) -> #VALUE! | S76: =IFERROR(R76/Q76,0) -> 0 | T76: =J76*68/12 -> #VALUE! | U76: =SUMIF('[1]Total 2'!$I:$I,_xlfn.TEXTJOIN(" ",TRUE,'NEW ATD PER TEAM'!$D$75,'NEW ATD PER TEAM'!$D76),'[1]Total 2'!X:X) -> #VALUE! | V76: =IFERROR(U76/T76,0) -> 0 | W76: =J76*68/12 -> #VALUE! | X76: =SUMIF('[1]Total 2'!$I:$I,_xlfn.TEXTJOIN(" ",TRUE,'NEW ATD PER TEAM'!$D$75,'NEW ATD PER TEAM'!$D76),'[1]Total 2'!AA:AA) -> #VALUE! | Y76: =IFERROR(X76/W76,0) -> 0 | Z76: =SUMIF('[1]Total 2'!$I:$I,_xlfn.TEXTJOIN(" ",TRUE,'NEW ATD PER TEAM'!$D$75,'NEW ATD PER TEAM'!$D76),'[1]Total 2'!AC:AC) -> #VALUE! | AA76: =SUMIF('[1]Total 2'!$I:$I,_xlfn.TEXTJOIN(" ",TRUE,'NEW ATD PER TEAM'!$D$75,'NEW ATD PER TEAM'!$D76),'[1]Total 2'!AD:AD) -> #VALUE! | AC76: =J76*1854*40 -> #VALUE! | AD76: =AA76 -> #VALUE! | AE76: =IFERROR(AD76/AC76,"")
B77: 2 | D77: Team 2 | E77: ITA MERIN/OLODO | G77: 8 | H77: 4 | I77: =IFERROR(H77/G77,"") -> 0.5 | J77: =SUMIF('[1]Total 2'!$I:$I,_xlfn.TEXTJOIN(" ",TRUE,'NEW ATD PER TEAM'!$D$75,'NEW ATD PER TEAM'!$D77),'[1]Total 2'!L:L) -> #VALUE! | K77: =J77*68/40 -> #VALUE! | L77: =SUMIF('[1]Total 2'!$I:$I,_xlfn.TEXTJOIN(" ",TRUE,'NEW ATD PER TEAM'!$D$75,'NEW ATD PER TEAM'!$D77),'[1]Total 2'!O:O) -> #VALUE! | M77: =IFERROR(L77/K77,0) -> 0 | N77: =J77*68/24 -> #VALUE! | O77: =SUMIF('[1]Total 2'!$I:$I,_xlfn.TEXTJOIN(" ",TRUE,'NEW ATD PER TEAM'!$D$75,'NEW ATD PER TEAM'!$D77),'[1]Total 2'!R:R) -> #VALUE! | P77: =IFERROR(O77/N77,0) -> 0 | Q77: =J77*68/24 -> #VALUE! | R77: =SUMIF('[1]Total 2'!$I:$I,_xlfn.TEXTJOIN(" ",TRUE,'NEW ATD PER TEAM'!$D$75,'NEW ATD PER TEAM'!$D77),'[1]Total 2'!U:U) -> #VALUE! | S77: =IFERROR(R77/Q77,0) -> 0 | T77: =J77*68/12 -> #VALUE! | U77: =SUMIF('[1]Total 2'!$I:$I,_xlfn.TEXTJOIN(" ",TRUE,'NEW ATD PER TEAM'!$D$75,'NEW ATD PER TEAM'!$D77),'[1]Total 2'!X:X) -> #VALUE! | V77: =IFERROR(U77/T77,0) -> 0 | W77: =J77*68/12 -> #VALUE! | X77: =SUMIF('[1]Total 2'!$I:$I,_xlfn.TEXTJOIN(" ",TRUE,'NEW ATD PER TEAM'!$D$75,'NEW ATD PER TEAM'!$D77),'[1]Total 2'!AA:AA) -> #VALUE! | Y77: =IFERROR(X77/W77,0) -> 0 | Z77: =SUMIF('[1]Total 2'!$I:$I,_xlfn.TEXTJOIN(" ",TRUE,'NEW ATD PER TEAM'!$D$75,'NEW ATD PER TEAM'!$D77),'[1]Total 2'!AC:AC) -> #VALUE! | AA77: =SUMIF('[1]Total 2'!$I:$I,_xlfn.TEXTJOIN(" ",TRUE,'NEW ATD PER TEAM'!$D$75,'NEW ATD PER TEAM'!$D77),'[1]Total 2'!AD:AD) -> #VALUE! | AC77: =J77*1854*40 -> #VALUE! | AD77: =AA77 -> #VALUE! | AE77: =IFERROR(AD77/AC77,"")
B78: 3 | D78: Team 3 | E78: EGBEDA/GBAGI | G78: 8 | H78: 4 | I78: =IFERROR(H78/G78,"") -> 0.5 | J78: =SUMIF('[1]Total 2'!$I:$I,_xlfn.TEXTJOIN(" ",TRUE,'NEW ATD PER TEAM'!$D$75,'NEW ATD PER TEAM'!$D78),'[1]Total 2'!L:L) -> #VALUE! | K78: =J78*68/40 -> #VALUE! | L78: =SUMIF('[1]Total 2'!$I:$I,_xlfn.TEXTJOIN(" ",TRUE,'NEW ATD PER TEAM'!$D$75,'NEW ATD PER TEAM'!$D78),'[1]Total 2'!O:O) -> #VALUE! | M78: =IFERROR(L78/K78,0) -> 0 | N78: =J78*68/24 -> #VALUE! | O78: =SUMIF('[1]Total 2'!$I:$I,_xlfn.TEXTJOIN(" ",TRUE,'NEW ATD PER TEAM'!$D$75,'NEW ATD PER TEAM'!$D78),'[1]Total 2'!R:R) -> #VALUE! | P78: =IFERROR(O78/N78,0) -> 0 | Q78: =J78*68/24 -> #VALUE! | R78: =SUMIF('[1]Total 2'!$I:$I,_xlfn.TEXTJOIN(" ",TRUE,'NEW ATD PER TEAM'!$D$75,'NEW ATD PER TEAM'!$D78),'[1]Total 2'!U:U) -> #VALUE! | S78: =IFERROR(R78/Q78,0) -> 0 | T78: =J78*68/12 -> #VALUE! | U78: =SUMIF('[1]Total 2'!$I:$I,_xlfn.TEXTJOIN(" ",TRUE,'NEW ATD PER TEAM'!$D$75,'NEW ATD PER TEAM'!$D78),'[1]Total 2'!X:X) -> #VALUE! | V78: =IFERROR(U78/T78,0) -> 0 | W78: =J78*68/12 -> #VALUE! | X78: =SUMIF('[1]Total 2'!$I:$I,_xlfn.TEXTJOIN(" ",TRUE,'NEW ATD PER TEAM'!$D$75,'NEW ATD PER TEAM'!$D78),'[1]Total 2'!AA:AA) -> #VALUE! | Y78: =IFERROR(X78/W78,0) -> 0 | Z78: =SUMIF('[1]Total 2'!$I:$I,_xlfn.TEXTJOIN(" ",TRUE,'NEW ATD PER TEAM'!$D$75,'NEW ATD PER TEAM'!$D78),'[1]Total 2'!AC:AC) -> #VALUE! | AA78: =SUMIF('[1]Total 2'!$I:$I,_xlfn.TEXTJOIN(" ",TRUE,'NEW ATD PER TEAM'!$D$75,'NEW ATD PER TEAM'!$D78),'[1]Total 2'!AD:AD) -> #VALUE! | AC78: =J78*1854*40 -> #VALUE! | AD78: =AA78 -> #VALUE! | AE78: =IFERROR(AD78/AC78,"")
B79: 4 | D79: Team 4 | E79: SANGO/UI/IYANA CHURCH | G79: 8 | H79: 4 | I79: =IFERROR(H79/G79,"") -> 0.5 | J79: =SUMIF('[1]Total 2'!$I:$I,_xlfn.TEXTJOIN(" ",TRUE,'NEW ATD PER TEAM'!$D$75,'NEW ATD PER TEAM'!$D79),'[1]Total 2'!L:L) -> #VALUE! | K79: =J79*68/40 -> #VALUE! | L79: =SUMIF('[1]Total 2'!$I:$I,_xlfn.TEXTJOIN(" ",TRUE,'NEW ATD PER TEAM'!$D$75,'NEW ATD PER TEAM'!$D79),'[1]Total 2'!O:O) -> #VALUE! | M79: =IFERROR(L79/K79,0) -> 0 | N79: =J79*68/24 -> #VALUE! | O79: =SUMIF('[1]Total 2'!$I:$I,_xlfn.TEXTJOIN(" ",TRUE,'NEW ATD PER TEAM'!$D$75,'NEW ATD PER TEAM'!$D79),'[1]Total 2'!R:R) -> #VALUE! | P79: =IFERROR(O79/N79,0) -> 0 | Q79: =J79*68/24 -> #VALUE! | R79: =SUMIF('[1]Total 2'!$I:$I,_xlfn.TEXTJOIN(" ",TRUE,'NEW ATD PER TEAM'!$D$75,'NEW ATD PER TEAM'!$D79),'[1]Total 2'!U:U) -> #VALUE! | S79: =IFERROR(R79/Q79,0) -> 0 | T79: =J79*68/12 -> #VALUE! | U79: =SUMIF('[1]Total 2'!$I:$I,_xlfn.TEXTJOIN(" ",TRUE,'NEW ATD PER TEAM'!$D$75,'NEW ATD PER TEAM'!$D79),'[1]Total 2'!X:X) -> #VALUE! | V79: =IFERROR(U79/T79,0) -> 0 | W79: =J79*68/12 -> #VALUE! | X79: =SUMIF('[1]Total 2'!$I:$I,_xlfn.TEXTJOIN(" ",TRUE,'NEW ATD PER TEAM'!$D$75,'NEW ATD PER TEAM'!$D79),'[1]Total 2'!AA:AA) -> #VALUE! | Y79: =IFERROR(X79/W79,0) -> 0 | Z79: =SUMIF('[1]Total 2'!$I:$I,_xlfn.TEXTJOIN(" ",TRUE,'NEW ATD PER TEAM'!$D$75,'NEW ATD PER TEAM'!$D79),'[1]Total 2'!AC:AC) -> #VALUE! | AA79: =SUMIF('[1]Total 2'!$I:$I,_xlfn.TEXTJOIN(" ",TRUE,'NEW ATD PER TEAM'!$D$75,'NEW ATD PER TEAM'!$D79),'[1]Total 2'!AD:AD) -> #VALUE! | AC79: =J79*1854*40 -> #VALUE! | AD79: =AA79 -> #VALUE! | AE79: =IFERROR(AD79/AC79,"")
E80: TOTAL | G80: =SUM(G76:G79) -> 32 | H80: =SUM(H76:H79) -> 16 | I80: =IFERROR(H80/G80,"") -> 0.5 | J80: =SUM(J76:J79) -> #VALUE! | K80: =SUM(K76:K79) -> #VALUE! | L80: =SUM(L76:L79) -> #VALUE! | M80: =IFERROR(L80/K80,0) -> 0 | N80: =SUM(N76:N79) -> #VALUE! | O80: =SUM(O76:O79) -> #VALUE! | P80: =IFERROR(O80/N80,0) -> 0 | Q80: =SUM(Q76:Q79) -> #VALUE! | R80: =SUM(R76:R79) -> #VALUE! | S80: =IFERROR(R80/Q80,0) -> 0 | T80: =SUM(T76:T79) -> #VALUE! | U80: =SUM(U76:U79) -> #VALUE! | V80: =IFERROR(U80/T80,0) -> 0 | W80: =SUM(W76:W79) -> #VALUE! | X80: =SUM(X76:X79) -> #VALUE! | Y80: =IFERROR(X80/W80,0) -> 0 | Z80: =SUM(Z76:Z79) -> #VALUE! | AA80: =SUM(AA76:AA79) -> #VALUE! | AC80: =SUM(AC76:AC79) -> #VALUE! | AD80: =SUM(AD76:AD79) -> #VALUE! | AE80: =IFERROR(AD80/AC80,"")
D81: IBADAN II | F81: ALABI OPEYEMI
B82: 1 | D82: Team 1 | E82: BODE | G82: 8 | H82: 4 | I82: =IFERROR(H82/G82,"") -> 0.5 | J82: =SUMIF('[1]Total 2'!$I:$I,_xlfn.TEXTJOIN(" ",TRUE,'NEW ATD PER TEAM'!$D$81,'NEW ATD PER TEAM'!$D82),'[1]Total 2'!L:L) -> #VALUE! | K82: =J82*68/40 -> #VALUE! | L82: =SUMIF('[1]Total 2'!$I:$I,_xlfn.TEXTJOIN(" ",TRUE,'NEW ATD PER TEAM'!$D$81,'NEW ATD PER TEAM'!$D82),'[1]Total 2'!O:O) -> #VALUE! | M82: =IFERROR(L82/K82,0) -> 0 | N82: =J82*68/24 -> #VALUE! | O82: =SUMIF('[1]Total 2'!$I:$I,_xlfn.TEXTJOIN(" ",TRUE,'NEW ATD PER TEAM'!$D$81,'NEW ATD PER TEAM'!$D82),'[1]Total 2'!R:R) -> #VALUE! | P82: =IFERROR(O82/N82,0) -> 0 | Q82: =J82*68/24 -> #VALUE! | R82: =SUMIF('[1]Total 2'!$I:$I,_xlfn.TEXTJOIN(" ",TRUE,'NEW ATD PER TEAM'!$D$81,'NEW ATD PER TEAM'!$D82),'[1]Total 2'!U:U) -> #VALUE! | S82: =IFERROR(R82/Q82,0) -> 0 | T82: =J82*68/12 -> #VALUE! | U82: =SUMIF('[1]Total 2'!$I:$I,_xlfn.TEXTJOIN(" ",TRUE,'NEW ATD PER TEAM'!$D$81,'NEW ATD PER TEAM'!$D82),'[1]Total 2'!X:X) -> #VALUE! | V82: =IFERROR(U82/T82,0) -> 0 | W82: =J82*68/12 -> #VALUE! | X82: =SUMIF('[1]Total 2'!$I:$I,_xlfn.TEXTJOIN(" ",TRUE,'NEW ATD PER TEAM'!$D$81,'NEW ATD PER TEAM'!$D82),'[1]Total 2'!AA:AA) -> #VALUE! | Y82: =IFERROR(X82/W82,0) -> 0 | Z82: =SUMIF('[1]Total 2'!$I:$I,_xlfn.TEXTJOIN(" ",TRUE,'NEW ATD PER TEAM'!$D$81,'NEW ATD PER TEAM'!$D82),'[1]Total 2'!AC:AC) -> #VALUE! | AA82: =SUMIF('[1]Total 2'!$I:$I,_xlfn.TEXTJOIN(" ",TRUE,'NEW ATD PER TEAM'!$D$81,'NEW ATD PER TEAM'!$D82),'[1]Total 2'!AD:AD) -> #VALUE! | AC82: =J82*1854*40 -> #VALUE! | AD82: =AA82 -> #VALUE! | AE82: =IFERROR(AD82/AC82,"")
B83: 2 | D83: Team 2 | E83: ODOONA | G83: 8 | H83: 4 | I83: =IFERROR(H83/G83,"") -> 0.5 | J83: =SUMIF('[1]Total 2'!$I:$I,_xlfn.TEXTJOIN(" ",TRUE,'NEW ATD PER TEAM'!$D$81,'NEW ATD PER TEAM'!$D83),'[1]Total 2'!L:L) -> #VALUE! | K83: =J83*68/40 -> #VALUE! | L83: =SUMIF('[1]Total 2'!$I:$I,_xlfn.TEXTJOIN(" ",TRUE,'NEW ATD PER TEAM'!$D$81,'NEW ATD PER TEAM'!$D83),'[1]Total 2'!O:O) -> #VALUE! | M83: =IFERROR(L83/K83,0) -> 0 | N83: =J83*68/24 -> #VALUE! | O83: =SUMIF('[1]Total 2'!$I:$I,_xlfn.TEXTJOIN(" ",TRUE,'NEW ATD PER TEAM'!$D$81,'NEW ATD PER TEAM'!$D83),'[1]Total 2'!R:R) -> #VALUE! | P83: =IFERROR(O83/N83,0) -> 0 | Q83: =J83*68/24 -> #VALUE! | R83: =SUMIF('[1]Total 2'!$I:$I,_xlfn.TEXTJOIN(" ",TRUE,'NEW ATD PER TEAM'!$D$81,'NEW ATD PER TEAM'!$D83),'[1]Total 2'!U:U) -> #VALUE! | S83: =IFERROR(R83/Q83,0) -> 0 | T83: =J83*68/12 -> #VALUE! | U83: =SUMIF('[1]Total 2'!$I:$I,_xlfn.TEXTJOIN(" ",TRUE,'NEW ATD PER TEAM'!$D$81,'NEW ATD PER TEAM'!$D83),'[1]Total 2'!X:X) -> #VALUE! | V83: =IFERROR(U83/T83,0) -> 0 | W83: =J83*68/12 -> #VALUE! | X83: =SUMIF('[1]Total 2'!$I:$I,_xlfn.TEXTJOIN(" ",TRUE,'NEW ATD PER TEAM'!$D$81,'NEW ATD PER TEAM'!$D83),'[1]Total 2'!AA:AA) -> #VALUE! | Y83: =IFERROR(X83/W83,0) -> 0 | Z83: =SUMIF('[1]Total 2'!$I:$I,_xlfn.TEXTJOIN(" ",TRUE,'NEW ATD PER TEAM'!$D$81,'NEW ATD PER TEAM'!$D83),'[1]Total 2'!AC:AC) -> #VALUE! | AA83: =SUMIF('[1]Total 2'!$I:$I,_xlfn.TEXTJOIN(" ",TRUE,'NEW ATD PER TEAM'!$D$81,'NEW ATD PER TEAM'!$D83),'[1]Total 2'!AD:AD) -> #VALUE! | AC83: =J83*1854*40 -> #VALUE! | AD83: =AA83 -> #VALUE! | AE83: =IFERROR(AD83/AC83,"")
B84: 3 | D84: Team 3 | E84: OKEADO | G84: 8 | H84: 4 | I84: =IFERROR(H84/G84,"") -> 0.5 | J84: =SUMIF('[1]Total 2'!$I:$I,_xlfn.TEXTJOIN(" ",TRUE,'NEW ATD PER TEAM'!$D$81,'NEW ATD PER TEAM'!$D84),'[1]Total 2'!L:L) -> #VALUE! | K84: =J84*68/40 -> #VALUE! | L84: =SUMIF('[1]Total 2'!$I:$I,_xlfn.TEXTJOIN(" ",TRUE,'NEW ATD PER TEAM'!$D$81,'NEW ATD PER TEAM'!$D84),'[1]Total 2'!O:O) -> #VALUE! | M84: =IFERROR(L84/K84,0) -> 0 | N84: =J84*68/24 -> #VALUE! | O84: =SUMIF('[1]Total 2'!$I:$I,_xlfn.TEXTJOIN(" ",TRUE,'NEW ATD PER TEAM'!$D$81,'NEW ATD PER TEAM'!$D84),'[1]Total 2'!R:R) -> #VALUE! | P84: =IFERROR(O84/N84,0) -> 0 | Q84: =J84*68/24 -> #VALUE! | R84: =SUMIF('[1]Total 2'!$I:$I,_xlfn.TEXTJOIN(" ",TRUE,'NEW ATD PER TEAM'!$D$81,'NEW ATD PER TEAM'!$D84),'[1]Total 2'!U:U) -> #VALUE! | S84: =IFERROR(R84/Q84,0) -> 0 | T84: =J84*68/12 -> #VALUE! | U84: =SUMIF('[1]Total 2'!$I:$I,_xlfn.TEXTJOIN(" ",TRUE,'NEW ATD PER TEAM'!$D$81,'NEW ATD PER TEAM'!$D84),'[1]Total 2'!X:X) -> #VALUE! | V84: =IFERROR(U84/T84,0) -> 0 | W84: =J84*68/12 -> #VALUE! | X84: =SUMIF('[1]Total 2'!$I:$I,_xlfn.TEXTJOIN(" ",TRUE,'NEW ATD PER TEAM'!$D$81,'NEW ATD PER TEAM'!$D84),'[1]Total 2'!AA:AA) -> #VALUE! | Y84: =IFERROR(X84/W84,0) -> 0 | Z84: =SUMIF('[1]Total 2'!$I:$I,_xlfn.TEXTJOIN(" ",TRUE,'NEW ATD PER TEAM'!$D$81,'NEW ATD PER TEAM'!$D84),'[1]Total 2'!AC:AC) -> #VALUE! | AA84: =SUMIF('[1]Total 2'!$I:$I,_xlfn.TEXTJOIN(" ",TRUE,'NEW ATD PER TEAM'!$D$81,'NEW ATD PER TEAM'!$D84),'[1]Total 2'!AD:AD) -> #VALUE! | AC84: =J84*1854*40 -> #VALUE! | AD84: =AA84 -> #VALUE! | AE84: =IFERROR(AD84/AC84,"")
B85: 4 | D85: Team 4 | E85: ALESHINLOYE | G85: 8 | H85: 4 | I85: =IFERROR(H85/G85,"") -> 0.5 | J85: =SUMIF('[1]Total 2'!$I:$I,_xlfn.TEXTJOIN(" ",TRUE,'NEW ATD PER TEAM'!$D$81,'NEW ATD PER TEAM'!$D85),'[1]Total 2'!L:L) -> #VALUE! | K85: =J85*68/40 -> #VALUE! | L85: =SUMIF('[1]Total 2'!$I:$I,_xlfn.TEXTJOIN(" ",TRUE,'NEW ATD PER TEAM'!$D$81,'NEW ATD PER TEAM'!$D85),'[1]Total 2'!O:O) -> #VALUE! | M85: =IFERROR(L85/K85,0) -> 0 | N85: =J85*68/24 -> #VALUE! | O85: =SUMIF('[1]Total 2'!$I:$I,_xlfn.TEXTJOIN(" ",TRUE,'NEW ATD PER TEAM'!$D$81,'NEW ATD PER TEAM'!$D85),'[1]Total 2'!R:R) -> #VALUE! | P85: =IFERROR(O85/N85,0) -> 0 | Q85: =J85*68/24 -> #VALUE! | R85: =SUMIF('[1]Total 2'!$I:$I,_xlfn.TEXTJOIN(" ",TRUE,'NEW ATD PER TEAM'!$D$81,'NEW ATD PER TEAM'!$D85),'[1]Total 2'!U:U) -> #VALUE! | S85: =IFERROR(R85/Q85,0) -> 0 | T85: =J85*68/12 -> #VALUE! | U85: =SUMIF('[1]Total 2'!$I:$I,_xlfn.TEXTJOIN(" ",TRUE,'NEW ATD PER TEAM'!$D$81,'NEW ATD PER TEAM'!$D85),'[1]Total 2'!X:X) -> #VALUE! | V85: =IFERROR(U85/T85,0) -> 0 | W85: =J85*68/12 -> #VALUE! | X85: =SUMIF('[1]Total 2'!$I:$I,_xlfn.TEXTJOIN(" ",TRUE,'NEW ATD PER TEAM'!$D$81,'NEW ATD PER TEAM'!$D85),'[1]Total 2'!AA:AA) -> #VALUE! | Y85: =IFERROR(X85/W85,0) -> 0 | Z85: =SUMIF('[1]Total 2'!$I:$I,_xlfn.TEXTJOIN(" ",TRUE,'NEW ATD PER TEAM'!$D$81,'NEW ATD PER TEAM'!$D85),'[1]Total 2'!AC:AC) -> #VALUE! | AA85: =SUMIF('[1]Total 2'!$I:$I,_xlfn.TEXTJOIN(" ",TRUE,'NEW ATD PER TEAM'!$D$81,'NEW ATD PER TEAM'!$D85),'[1]Total 2'!AD:AD) -> #VALUE! | AC85: =J85*1854*40 -> #VALUE! | AD85: =AA85 -> #VALUE! | AE85: =IFERROR(AD85/AC85,"")
E86: TOTAL | G86: =SUM(G82:G85) -> 32 | H86: =SUM(H82:H85) -> 16 | I86: =IFERROR(H86/G86,"") -> 0.5 | J86: =SUM(J82:J85) -> #VALUE! | K86: =SUM(K82:K85) -> #VALUE! | L86: =SUM(L82:L85) -> #VALUE! | M86: =IFERROR(L86/K86,0) -> 0 | N86: =SUM(N82:N85) -> #VALUE! | O86: =SUM(O82:O85) -> #VALUE! | P86: =IFERROR(O86/N86,0) -> 0 | Q86: =SUM(Q82:Q85) -> #VALUE! | R86: =SUM(R82:R85) -> #VALUE! | S86: =IFERROR(R86/Q86,0) -> 0 | T86: =SUM(T82:T85) -> #VALUE! | U86: =SUM(U82:U85) -> #VALUE! | V86: =IFERROR(U86/T86,0) -> 0 | W86: =SUM(W82:W85) -> #VALUE! | X86: =SUM(X82:X85) -> #VALUE! | Y86: =IFERROR(X86/W86,0) -> 0 | Z86: =SUM(Z82:Z85) -> #VALUE! | AA86: =SUM(AA82:AA85) -> #VALUE! | AC86: =SUM(AC82:AC85) -> #VALUE! | AD86: =SUM(AD82:AD85) -> #VALUE! | AE86: =IFERROR(AD86/AC86,"")
D87: OSHOGBO | F87: KOLADE TEMITOPE
B88: 1 | D88: Team 1 | E88: LAGERE (ILE-IFE) | G88: 8 | H88: 5 | I88: =IFERROR(H88/G88,"") -> 0.625 | J88: =SUMIF('[1]Total 2'!$I:$I,_xlfn.TEXTJOIN(" ",TRUE,'NEW ATD PER TEAM'!$D$87,'NEW ATD PER TEAM'!$D88),'[1]Total 2'!L:L) -> #VALUE! | K88: =J88*68/40 -> #VALUE! | L88: =SUMIF('[1]Total 2'!$I:$I,_xlfn.TEXTJOIN(" ",TRUE,'NEW ATD PER TEAM'!$D$87,'NEW ATD PER TEAM'!$D88),'[1]Total 2'!O:O) -> #VALUE! | M88: =IFERROR(L88/K88,0) -> 0 | N88: =J88*68/24 -> #VALUE! | O88: =SUMIF('[1]Total 2'!$I:$I,_xlfn.TEXTJOIN(" ",TRUE,'NEW ATD PER TEAM'!$D$87,'NEW ATD PER TEAM'!$D88),'[1]Total 2'!R:R) -> #VALUE! | P88: =IFERROR(O88/N88,0) -> 0 | Q88: =J88*68/24 -> #VALUE! | R88: =SUMIF('[1]Total 2'!$I:$I,_xlfn.TEXTJOIN(" ",TRUE,'NEW ATD PER TEAM'!$D$87,'NEW ATD PER TEAM'!$D88),'[1]Total 2'!U:U) -> #VALUE! | S88: =IFERROR(R88/Q88,0) -> 0 | T88: =J88*68/12 -> #VALUE! | U88: =SUMIF('[1]Total 2'!$I:$I,_xlfn.TEXTJOIN(" ",TRUE,'NEW ATD PER TEAM'!$D$87,'NEW ATD PER TEAM'!$D88),'[1]Total 2'!X:X) -> #VALUE! | V88: =IFERROR(U88/T88,0) -> 0 | W88: =J88*68/12 -> #VALUE! | X88: =SUMIF('[1]Total 2'!$I:$I,_xlfn.TEXTJOIN(" ",TRUE,'NEW ATD PER TEAM'!$D$87,'NEW ATD PER TEAM'!$D88),'[1]Total 2'!AA:AA) -> #VALUE! | Y88: =IFERROR(X88/W88,0) -> 0 | Z88: =SUMIF('[1]Total 2'!$I:$I,_xlfn.TEXTJOIN(" ",TRUE,'NEW ATD PER TEAM'!$D$87,'NEW ATD PER TEAM'!$D88),'[1]Total 2'!AC:AC) -> #VALUE! | AA88: =SUMIF('[1]Total 2'!$I:$I,_xlfn.TEXTJOIN(" ",TRUE,'NEW ATD PER TEAM'!$D$87,'NEW ATD PER TEAM'!$D88),'[1]Total 2'!AD:AD) -> #VALUE! | AC88: =J88*1854*40 -> #VALUE! | AD88: =AA88 -> #VALUE! | AE88: =IFERROR(AD88/AC88,"")
B89: 2 | D89: Team 2 | E89: ORISUMBARE(OSHOGBO) | G89: 8 | H89: 6 | I89: =IFERROR(H89/G89,"") -> 0.75 | J89: =SUMIF('[1]Total 2'!$I:$I,_xlfn.TEXTJOIN(" ",TRUE,'NEW ATD PER TEAM'!$D$87,'NEW ATD PER TEAM'!$D89),'[1]Total 2'!L:L) -> #VALUE! | K89: =J89*68/40 -> #VALUE! | L89: =SUMIF('[1]Total 2'!$I:$I,_xlfn.TEXTJOIN(" ",TRUE,'NEW ATD PER TEAM'!$D$87,'NEW ATD PER TEAM'!$D89),'[1]Total 2'!O:O) -> #VALUE! | M89: =IFERROR(L89/K89,0) -> 0 | N89: =J89*68/24 -> #VALUE! | O89: =SUMIF('[1]Total 2'!$I:$I,_xlfn.TEXTJOIN(" ",TRUE,'NEW ATD PER TEAM'!$D$87,'NEW ATD PER TEAM'!$D89),'[1]Total 2'!R:R) -> #VALUE! | P89: =IFERROR(O89/N89,0) -> 0 | Q89: =J89*68/24 -> #VALUE! | R89: =SUMIF('[1]Total 2'!$I:$I,_xlfn.TEXTJOIN(" ",TRUE,'NEW ATD PER TEAM'!$D$87,'NEW ATD PER TEAM'!$D89),'[1]Total 2'!U:U) -> #VALUE! | S89: =IFERROR(R89/Q89,0) -> 0 | T89: =J89*68/12 -> #VALUE! | U89: =SUMIF('[1]Total 2'!$I:$I,_xlfn.TEXTJOIN(" ",TRUE,'NEW ATD PER TEAM'!$D$87,'NEW ATD PER TEAM'!$D89),'[1]Total 2'!X:X) -> #VALUE! | V89: =IFERROR(U89/T89,0) -> 0 | W89: =J89*68/12 -> #VALUE! | X89: =SUMIF('[1]Total 2'!$I:$I,_xlfn.TEXTJOIN(" ",TRUE,'NEW ATD PER TEAM'!$D$87,'NEW ATD PER TEAM'!$D89),'[1]Total 2'!AA:AA) -> #VALUE! | Y89: =IFERROR(X89/W89,0) -> 0 | Z89: =SUMIF('[1]Total 2'!$I:$I,_xlfn.TEXTJOIN(" ",TRUE,'NEW ATD PER TEAM'!$D$87,'NEW ATD PER TEAM'!$D89),'[1]Total 2'!AC:AC) -> #VALUE! | AA89: =SUMIF('[1]Total 2'!$I:$I,_xlfn.TEXTJOIN(" ",TRUE,'NEW ATD PER TEAM'!$D$87,'NEW ATD PER TEAM'!$D89),'[1]Total 2'!AD:AD) -> #VALUE! | AC89: =J89*1854*40 -> #VALUE! | AD89: =AA89 -> #VALUE! | AE89: =IFERROR(AD89/AC89,"")
B90: 3 | D90: Team 3 | G90: 8 | I90: =IFERROR(H90/G90,"") -> 0 | J90: =SUMIF('[1]Total 2'!$I:$I,_xlfn.TEXTJOIN(" ",TRUE,'NEW ATD PER TEAM'!$D$87,'NEW ATD PER TEAM'!$D90),'[1]Total 2'!L:L) -> #VALUE! | K90: =J90*68/40 -> #VALUE! | L90: =SUMIF('[1]Total 2'!$I:$I,_xlfn.TEXTJOIN(" ",TRUE,'NEW ATD PER TEAM'!$D$87,'NEW ATD PER TEAM'!$D90),'[1]Total 2'!O:O) -> #VALUE! | M90: =IFERROR(L90/K90,0) -> 0 | N90: =J90*68/24 -> #VALUE! | O90: =SUMIF('[1]Total 2'!$I:$I,_xlfn.TEXTJOIN(" ",TRUE,'NEW ATD PER TEAM'!$D$87,'NEW ATD PER TEAM'!$D90),'[1]Total 2'!R:R) -> #VALUE! | P90: =IFERROR(O90/N90,0) -> 0 | Q90: =J90*68/24 -> #VALUE! | R90: =SUMIF('[1]Total 2'!$I:$I,_xlfn.TEXTJOIN(" ",TRUE,'NEW ATD PER TEAM'!$D$87,'NEW ATD PER TEAM'!$D90),'[1]Total 2'!U:U) -> #VALUE! | S90: =IFERROR(R90/Q90,0) -> 0 | T90: =J90*68/12 -> #VALUE! | U90: =SUMIF('[1]Total 2'!$I:$I,_xlfn.TEXTJOIN(" ",TRUE,'NEW ATD PER TEAM'!$D$87,'NEW ATD PER TEAM'!$D90),'[1]Total 2'!X:X) -> #VALUE! | V90: =IFERROR(U90/T90,0) -> 0 | W90: =J90*68/12 -> #VALUE! | X90: =SUMIF('[1]Total 2'!$I:$I,_xlfn.TEXTJOIN(" ",TRUE,'NEW ATD PER TEAM'!$D$87,'NEW ATD PER TEAM'!$D90),'[1]Total 2'!AA:AA) -> #VALUE! | Y90: =IFERROR(X90/W90,0) -> 0 | Z90: =SUMIF('[1]Total 2'!$I:$I,_xlfn.TEXTJOIN(" ",TRUE,'NEW ATD PER TEAM'!$D$87,'NEW ATD PER TEAM'!$D90),'[1]Total 2'!AC:AC) -> #VALUE! | AA90: =SUMIF('[1]Total 2'!$I:$I,_xlfn.TEXTJOIN(" ",TRUE,'NEW ATD PER TEAM'!$D$87,'NEW ATD PER TEAM'!$D90),'[1]Total 2'!AD:AD) -> #VALUE! | AC90: =J90*1854*40 -> #VALUE! | AD90: =AA90 -> #VALUE! | AE90: =IFERROR(AD90/AC90,"")
B91: 4 | D91: Team 4 | G91: 8 | I91: =IFERROR(H91/G91,"") -> 0 | J91: =SUMIF('[1]Total 2'!$I:$I,_xlfn.TEXTJOIN(" ",TRUE,'NEW ATD PER TEAM'!$D$87,'NEW ATD PER TEAM'!$D91),'[1]Total 2'!L:L) -> #VALUE! | K91: =J91*68/40 -> #VALUE! | L91: =SUMIF('[1]Total 2'!$I:$I,_xlfn.TEXTJOIN(" ",TRUE,'NEW ATD PER TEAM'!$D$87,'NEW ATD PER TEAM'!$D91),'[1]Total 2'!O:O) -> #VALUE! | M91: =IFERROR(L91/K91,0) -> 0 | N91: =J91*68/24 -> #VALUE! | O91: =SUMIF('[1]Total 2'!$I:$I,_xlfn.TEXTJOIN(" ",TRUE,'NEW ATD PER TEAM'!$D$87,'NEW ATD PER TEAM'!$D91),'[1]Total 2'!R:R) -> #VALUE! | P91: =IFERROR(O91/N91,0) -> 0 | Q91: =J91*68/24 -> #VALUE! | R91: =SUMIF('[1]Total 2'!$I:$I,_xlfn.TEXTJOIN(" ",TRUE,'NEW ATD PER TEAM'!$D$87,'NEW ATD PER TEAM'!$D91),'[1]Total 2'!U:U) -> #VALUE! | S91: =IFERROR(R91/Q91,0) -> 0 | T91: =J91*68/12 -> #VALUE! | U91: =SUMIF('[1]Total 2'!$I:$I,_xlfn.TEXTJOIN(" ",TRUE,'NEW ATD PER TEAM'!$D$87,'NEW ATD PER TEAM'!$D91),'[1]Total 2'!X:X) -> #VALUE! | V91: =IFERROR(U91/T91,0) -> 0 | W91: =J91*68/12 -> #VALUE! | X91: =SUMIF('[1]Total 2'!$I:$I,_xlfn.TEXTJOIN(" ",TRUE,'NEW ATD PER TEAM'!$D$87,'NEW ATD PER TEAM'!$D91),'[1]Total 2'!AA:AA) -> #VALUE! | Y91: =IFERROR(X91/W91,0) -> 0 | Z91: =SUMIF('[1]Total 2'!$I:$I,_xlfn.TEXTJOIN(" ",TRUE,'NEW ATD PER TEAM'!$D$87,'NEW ATD PER TEAM'!$D91),'[1]Total 2'!AC:AC) -> #VALUE! | AA91: =SUMIF('[1]Total 2'!$I:$I,_xlfn.TEXTJOIN(" ",TRUE,'NEW ATD PER TEAM'!$D$87,'NEW ATD PER TEAM'!$D91),'[1]Total 2'!AD:AD) -> #VALUE! | AC91: =J91*1854*40 -> #VALUE! | AD91: =AA91 -> #VALUE! | AE91: =IFERROR(AD91/AC91,"")
E92: TOTAL | G92: =SUM(G88:G91) -> 32 | H92: =SUM(H88:H91) -> 11 | I92: =IFERROR(H92/G92,"") -> 0.34375 | J92: =SUM(J88:J91) -> #VALUE! | K92: =SUM(K88:K91) -> #VALUE! | L92: =SUM(L88:L91) -> #VALUE! | M92: =IFERROR(L92/K92,0) -> 0 | N92: =SUM(N88:N91) -> #VALUE! | O92: =SUM(O88:O91) -> #VALUE! | P92: =IFERROR(O92/N92,0) -> 0 | Q92: =SUM(Q88:Q91) -> #VALUE! | R92: =SUM(R88:R91) -> #VALUE! | S92: =IFERROR(R92/Q92,0) -> 0 | T92: =SUM(T88:T91) -> #VALUE! | U92: =SUM(U88:U91) -> #VALUE! | V92: =IFERROR(U92/T92,0) -> 0 | W92: =SUM(W88:W91) -> #VALUE! | X92: =SUM(X88:X91) -> #VALUE! | Y92: =IFERROR(X92/W92,0) -> 0 | Z92: =SUM(Z88:Z91) -> #VALUE! | AA92: =SUM(AA88:AA91) -> #VALUE! | AC92: =SUM(AC88:AC91) -> #VALUE! | AD92: =SUM(AD88:AD91) -> #VALUE! | AE92: =IFERROR(AD92/AC92,"")
D93: ILORIN | F93: SEGUN OLORUNTOBA
B94: 1 | D94: Team 1 | E94: POST OFFICE/TANKE | G94: 8 | H94: 7 | I94: =IFERROR(H94/G94,"") -> 0.875 | J94: =SUMIF('[1]Total 2'!$I:$I,_xlfn.TEXTJOIN(" ",TRUE,'NEW ATD PER TEAM'!$D$93,'NEW ATD PER TEAM'!$D94),'[1]Total 2'!L:L) -> #VALUE! | K94: =J94*68/40 -> #VALUE! | L94: =SUMIF('[1]Total 2'!$I:$I,_xlfn.TEXTJOIN(" ",TRUE,'NEW ATD PER TEAM'!$D$93,'NEW ATD PER TEAM'!$D94),'[1]Total 2'!O:O) -> #VALUE! | M94: =IFERROR(L94/K94,0) -> 0 | N94: =J94*68/24 -> #VALUE! | O94: =SUMIF('[1]Total 2'!$I:$I,_xlfn.TEXTJOIN(" ",TRUE,'NEW ATD PER TEAM'!$D$93,'NEW ATD PER TEAM'!$D94),'[1]Total 2'!R:R) -> #VALUE! | P94: =IFERROR(O94/N94,0) -> 0 | Q94: =J94*68/24 -> #VALUE! | S94: =IFERROR(R94/Q94,0) -> 0 | T94: =J94*68/12 -> #VALUE! | U94: =SUMIF('[1]Total 2'!$I:$I,_xlfn.TEXTJOIN(" ",TRUE,'NEW ATD PER TEAM'!$D$93,'NEW ATD PER TEAM'!$D94),'[1]Total 2'!X:X) -> #VALUE! | V94: =IFERROR(U94/T94,0) -> 0 | W94: =J94*68/12 -> #VALUE! | X94: =SUMIF('[1]Total 2'!$I:$I,_xlfn.TEXTJOIN(" ",TRUE,'NEW ATD PER TEAM'!$D$93,'NEW ATD PER TEAM'!$D94),'[1]Total 2'!AA:AA) -> #VALUE! | Y94: =IFERROR(X94/W94,0) -> 0 | Z94: =SUMIF('[1]Total 2'!$I:$I,_xlfn.TEXTJOIN(" ",TRUE,'NEW ATD PER TEAM'!$D$93,'NEW ATD PER TEAM'!$D94),'[1]Total 2'!AC:AC) -> #VALUE! | AA94: =SUMIF('[1]Total 2'!$I:$I,_xlfn.TEXTJOIN(" ",TRUE,'NEW ATD PER TEAM'!$D$93,'NEW ATD PER TEAM'!$D94),'[1]Total 2'!AD:AD) -> #VALUE! | AC94: =J94*1854*40 -> #VALUE! | AD94: =AA94 -> #VALUE! | AE94: =IFERROR(AD94/AC94,"")
B95: 2 | D95: Team 2 | E95: OLOJE/OJA OBE | G95: 8 | H95: 7 | I95: =IFERROR(H95/G95,"") -> 0.875 | J95: =SUMIF('[1]Total 2'!$I:$I,_xlfn.TEXTJOIN(" ",TRUE,'NEW ATD PER TEAM'!$D$93,'NEW ATD PER TEAM'!$D95),'[1]Total 2'!L:L) -> #VALUE! | K95: =J95*68/40 -> #VALUE! | L95: =SUMIF('[1]Total 2'!$I:$I,_xlfn.TEXTJOIN(" ",TRUE,'NEW ATD PER TEAM'!$D$93,'NEW ATD PER TEAM'!$D95),'[1]Total 2'!O:O) -> #VALUE! | M95: =IFERROR(L95/K95,0) -> 0 | N95: =J95*68/24 -> #VALUE! | O95: =SUMIF('[1]Total 2'!$I:$I,_xlfn.TEXTJOIN(" ",TRUE,'NEW ATD PER TEAM'!$D$93,'NEW ATD PER TEAM'!$D95),'[1]Total 2'!R:R) -> #VALUE! | P95: =IFERROR(O95/N95,0) -> 0 | Q95: =J95*68/24 -> #VALUE! | S95: =IFERROR(R95/Q95,0) -> 0 | T95: =J95*68/12 -> #VALUE! | U95: =SUMIF('[1]Total 2'!$I:$I,_xlfn.TEXTJOIN(" ",TRUE,'NEW ATD PER TEAM'!$D$93,'NEW ATD PER TEAM'!$D95),'[1]Total 2'!X:X) -> #VALUE! | V95: =IFERROR(U95/T95,0) -> 0 | W95: =J95*68/12 -> #VALUE! | X95: =SUMIF('[1]Total 2'!$I:$I,_xlfn.TEXTJOIN(" ",TRUE,'NEW ATD PER TEAM'!$D$93,'NEW ATD PER TEAM'!$D95),'[1]Total 2'!AA:AA) -> #VALUE! | Y95: =IFERROR(X95/W95,0) -> 0 | Z95: =SUMIF('[1]Total 2'!$I:$I,_xlfn.TEXTJOIN(" ",TRUE,'NEW ATD PER TEAM'!$D$93,'NEW ATD PER TEAM'!$D95),'[1]Total 2'!AC:AC) -> #VALUE! | AA95: =SUMIF('[1]Total 2'!$I:$I,_xlfn.TEXTJOIN(" ",TRUE,'NEW ATD PER TEAM'!$D$93,'NEW ATD PER TEAM'!$D95),'[1]Total 2'!AD:AD) -> #VALUE! | AC95: =J95*1854*40 -> #VALUE! | AD95: =AA95 -> #VALUE! | AE95: =IFERROR(AD95/AC95,"")
B96: 3 | D96: Team 3 | G96: 8 | I96: =IFERROR(H96/G96,"") -> 0 | J96: =SUMIF('[1]Total 2'!$I:$I,_xlfn.TEXTJOIN(" ",TRUE,'NEW ATD PER TEAM'!$D$93,'NEW ATD PER TEAM'!$D96),'[1]Total 2'!L:L) -> #VALUE! | K96: =J96*68/40 -> #VALUE! | L96: =SUMIF('[1]Total 2'!$I:$I,_xlfn.TEXTJOIN(" ",TRUE,'NEW ATD PER TEAM'!$D$93,'NEW ATD PER TEAM'!$D96),'[1]Total 2'!O:O) -> #VALUE! | M96: =IFERROR(L96/K96,0) -> 0 | N96: =J96*68/24 -> #VALUE! | O96: =SUMIF('[1]Total 2'!$I:$I,_xlfn.TEXTJOIN(" ",TRUE,'NEW ATD PER TEAM'!$D$93,'NEW ATD PER TEAM'!$D96),'[1]Total 2'!R:R) -> #VALUE! | P96: =IFERROR(O96/N96,0) -> 0 | Q96: =J96*68/24 -> #VALUE! | S96: =IFERROR(R96/Q96,0) -> 0 | T96: =J96*68/12 -> #VALUE! | U96: =SUMIF('[1]Total 2'!$I:$I,_xlfn.TEXTJOIN(" ",TRUE,'NEW ATD PER TEAM'!$D$93,'NEW ATD PER TEAM'!$D96),'[1]Total 2'!X:X) -> #VALUE! | V96: =IFERROR(U96/T96,0) -> 0 | W96: =J96*68/12 -> #VALUE! | X96: =SUMIF('[1]Total 2'!$I:$I,_xlfn.TEXTJOIN(" ",TRUE,'NEW ATD PER TEAM'!$D$93,'NEW ATD PER TEAM'!$D96),'[1]Total 2'!AA:AA) -> #VALUE! | Y96: =IFERROR(X96/W96,0) -> 0 | Z96: =SUMIF('[1]Total 2'!$I:$I,_xlfn.TEXTJOIN(" ",TRUE,'NEW ATD PER TEAM'!$D$93,'NEW ATD PER TEAM'!$D96),'[1]Total 2'!AC:AC) -> #VALUE! | AA96: =SUMIF('[1]Total 2'!$I:$I,_xlfn.TEXTJOIN(" ",TRUE,'NEW ATD PER TEAM'!$D$93,'NEW ATD PER TEAM'!$D96),'[1]Total 2'!AD:AD) -> #VALUE! | AC96: =J96*1854*40 -> #VALUE! | AD96: =AA96 -> #VALUE! | AE96: =IFERROR(AD96/AC96,"")
B97: 4 | D97: Team 4 | G97: 8 | I97: =IFERROR(H97/G97,"") -> 0 | J97: =SUMIF('[1]Total 2'!$I:$I,_xlfn.TEXTJOIN(" ",TRUE,'NEW ATD PER TEAM'!$D$93,'NEW ATD PER TEAM'!$D97),'[1]Total 2'!L:L) -> #VALUE! | K97: =J97*68/40 -> #VALUE! | L97: =SUMIF('[1]Total 2'!$I:$I,_xlfn.TEXTJOIN(" ",TRUE,'NEW ATD PER TEAM'!$D$93,'NEW ATD PER TEAM'!$D97),'[1]Total 2'!O:O) -> #VALUE! | M97: =IFERROR(L97/K97,0) -> 0 | N97: =J97*68/24 -> #VALUE! | O97: =SUMIF('[1]Total 2'!$I:$I,_xlfn.TEXTJOIN(" ",TRUE,'NEW ATD PER TEAM'!$D$93,'NEW ATD PER TEAM'!$D97),'[1]Total 2'!R:R) -> #VALUE! | P97: =IFERROR(O97/N97,0) -> 0 | Q97: =J97*68/24 -> #VALUE! | S97: =IFERROR(R97/Q97,0) -> 0 | T97: =J97*68/12 -> #VALUE! | U97: =SUMIF('[1]Total 2'!$I:$I,_xlfn.TEXTJOIN(" ",TRUE,'NEW ATD PER TEAM'!$D$93,'NEW ATD PER TEAM'!$D97),'[1]Total 2'!X:X) -> #VALUE! | V97: =IFERROR(U97/T97,0) -> 0 | W97: =J97*68/12 -> #VALUE! | X97: =SUMIF('[1]Total 2'!$I:$I,_xlfn.TEXTJOIN(" ",TRUE,'NEW ATD PER TEAM'!$D$93,'NEW ATD PER TEAM'!$D97),'[1]Total 2'!AA:AA) -> #VALUE! | Y97: =IFERROR(X97/W97,0) -> 0 | Z97: =SUMIF('[1]Total 2'!$I:$I,_xlfn.TEXTJOIN(" ",TRUE,'NEW ATD PER TEAM'!$D$93,'NEW ATD PER TEAM'!$D97),'[1]Total 2'!AC:AC) -> #VALUE! | AA97: =SUMIF('[1]Total 2'!$I:$I,_xlfn.TEXTJOIN(" ",TRUE,'NEW ATD PER TEAM'!$D$93,'NEW ATD PER TEAM'!$D97),'[1]Total 2'!AD:AD) -> #VALUE! | AC97: =J97*1854*40 -> #VALUE! | AD97: =AA97 -> #VALUE! | AE97: =IFERROR(AD97/AC97,"")
B98: TOTAL | G98: =SUM(G94:G97) -> 32 | H98: =SUM(H94:H97) -> 14 | I98: =IFERROR(H98/G98,"") -> 0.4375 | J98: =SUM(J94:J97) -> #VALUE! | K98: =SUM(K94:K97) -> #VALUE! | L98: =SUM(L94:L97) -> #VALUE! | M98: =IFERROR(L98/K98,0) -> 0 | N98: =SUM(N94:N97) -> #VALUE! | O98: =SUM(O94:O97) -> #VALUE! | P98: =IFERROR(O98/N98,0) -> 0 | Q98: =SUM(Q94:Q97) -> #VALUE! | S98: =IFERROR(R98/Q98,0) -> 0 | T98: =SUM(T94:T97) -> #VALUE! | U98: =SUM(U94:U97) -> #VALUE! | V98: =IFERROR(U98/T98,0) -> 0 | W98: =SUM(W94:W97) -> #VALUE! | X98: =SUM(X94:X97) -> #VALUE! | Y98: =IFERROR(X98/W98,0) -> 0 | Z98: =SUM(Z94:Z97) -> #VALUE! | AA98: =SUM(AA94:AA97) -> #VALUE! | AC98: =SUM(AC94:AC97) -> #VALUE! | AD98: =SUM(AD94:AD97) -> #VALUE! | AE98: =IFERROR(AD98/AC98,"")
C99: West 2 | D99: BENIN 1 | F99: TRINITY EZEIBE
B100: 1 | D100: Team 1 | E100: 3 HOUSE/Olukuu | G100: 8 | H100: 6 | I100: =IFERROR(H100/G100,"") -> 0.75 | J100: =SUMIF('[1]Total 2'!$I:$I,_xlfn.TEXTJOIN(" ",TRUE,'NEW ATD PER TEAM'!$D$99,'NEW ATD PER TEAM'!$D100),'[1]Total 2'!L:L) -> #VALUE! | K100: =J100*68/40 -> #VALUE! | L100: =SUMIF('[1]Total 2'!$I:$I,_xlfn.TEXTJOIN(" ",TRUE,'NEW ATD PER TEAM'!$D$99,'NEW ATD PER TEAM'!$D100),'[1]Total 2'!O:O) -> #VALUE! | M100: =IFERROR(L100/K100,0) -> 0 | N100: =J100*68/24 -> #VALUE! | O100: =SUMIF('[1]Total 2'!$I:$I,_xlfn.TEXTJOIN(" ",TRUE,'NEW ATD PER TEAM'!$D$99,'NEW ATD PER TEAM'!$D100),'[1]Total 2'!R:R) -> #VALUE! | P100: =IFERROR(O100/N100,0) -> 0 | Q100: =J100*68/24 -> #VALUE! | R100: =SUMIF('[1]Total 2'!$I:$I,_xlfn.TEXTJOIN(" ",TRUE,'NEW ATD PER TEAM'!$D$99,'NEW ATD PER TEAM'!$D100),'[1]Total 2'!U:U) -> #VALUE! | S100: =IFERROR(R100/Q100,0) -> 0 | T100: =J100*68/12 -> #VALUE! | U100: =SUMIF('[1]Total 2'!$I:$I,_xlfn.TEXTJOIN(" ",TRUE,'NEW ATD PER TEAM'!$D$99,'NEW ATD PER TEAM'!$D100),'[1]Total 2'!X:X) -> #VALUE! | V100: =IFERROR(U100/T100,0) -> 0 | W100: =J100*68/12 -> #VALUE! | X100: =SUMIF('[1]Total 2'!$I:$I,_xlfn.TEXTJOIN(" ",TRUE,'NEW ATD PER TEAM'!$D$99,'NEW ATD PER TEAM'!$D100),'[1]Total 2'!AA:AA) -> #VALUE! | Y100: =IFERROR(X100/W100,0) -> 0 | Z100: =SUMIF('[1]Total 2'!$I:$I,_xlfn.TEXTJOIN(" ",TRUE,'NEW ATD PER TEAM'!$D$99,'NEW ATD PER TEAM'!$D100),'[1]Total 2'!AC:AC) -> #VALUE! | AA100: =SUMIF('[1]Total 2'!$I:$I,_xlfn.TEXTJOIN(" ",TRUE,'NEW ATD PER TEAM'!$D$99,'NEW ATD PER TEAM'!$D100),'[1]Total 2'!AD:AD) -> #VALUE! | AC100: =J100*1854*40 -> #VALUE! | AD100: =AA100 -> #VALUE! | AE100: =IFERROR(AD100/AC100,"")
B101: 2 | D101: Team 2 | E101: EBOVWIE/Isihor | G101: 8 | H101: 6 | I101: =IFERROR(H101/G101,"") -> 0.75 | J101: =SUMIF('[1]Total 2'!$I:$I,_xlfn.TEXTJOIN(" ",TRUE,'NEW ATD PER TEAM'!$D$99,'NEW ATD PER TEAM'!$D101),'[1]Total 2'!L:L) -> #VALUE! | K101: =J101*68/40 -> #VALUE! | L101: =SUMIF('[1]Total 2'!$I:$I,_xlfn.TEXTJOIN(" ",TRUE,'NEW ATD PER TEAM'!$D$99,'NEW ATD PER TEAM'!$D101),'[1]Total 2'!O:O) -> #VALUE! | M101: =IFERROR(L101/K101,0) -> 0 | N101: =J101*68/24 -> #VALUE! | O101: =SUMIF('[1]Total 2'!$I:$I,_xlfn.TEXTJOIN(" ",TRUE,'NEW ATD PER TEAM'!$D$99,'NEW ATD PER TEAM'!$D101),'[1]Total 2'!R:R) -> #VALUE! | P101: =IFERROR(O101/N101,0) -> 0 | Q101: =J101*68/24 -> #VALUE! | R101: =SUMIF('[1]Total 2'!$I:$I,_xlfn.TEXTJOIN(" ",TRUE,'NEW ATD PER TEAM'!$D$99,'NEW ATD PER TEAM'!$D101),'[1]Total 2'!U:U) -> #VALUE! | S101: =IFERROR(R101/Q101,0) -> 0 | T101: =J101*68/12 -> #VALUE! | U101: =SUMIF('[1]Total 2'!$I:$I,_xlfn.TEXTJOIN(" ",TRUE,'NEW ATD PER TEAM'!$D$99,'NEW ATD PER TEAM'!$D101),'[1]Total 2'!X:X) -> #VALUE! | V101: =IFERROR(U101/T101,0) -> 0 | W101: =J101*68/12 -> #VALUE! | X101: =SUMIF('[1]Total 2'!$I:$I,_xlfn.TEXTJOIN(" ",TRUE,'NEW ATD PER TEAM'!$D$99,'NEW ATD PER TEAM'!$D101),'[1]Total 2'!AA:AA) -> #VALUE! | Y101: =IFERROR(X101/W101,0) -> 0 | Z101: =SUMIF('[1]Total 2'!$I:$I,_xlfn.TEXTJOIN(" ",TRUE,'NEW ATD PER TEAM'!$D$99,'NEW ATD PER TEAM'!$D101),'[1]Total 2'!AC:AC) -> #VALUE! | AA101: =SUMIF('[1]Total 2'!$I:$I,_xlfn.TEXTJOIN(" ",TRUE,'NEW ATD PER TEAM'!$D$99,'NEW ATD PER TEAM'!$D101),'[1]Total 2'!AD:AD) -> #VALUE! | AC101: =J101*1854*40 -> #VALUE! | AD101: =AA101 -> #VALUE! | AE101: =IFERROR(AD101/AC101,"")
B102: 3 | D102: Team 3 | E102: BYPASS/Uselu | G102: 8 | H102: 2 | I102: =IFERROR(H102/G102,"") -> 0.25 | J102: =SUMIF('[1]Total 2'!$I:$I,_xlfn.TEXTJOIN(" ",TRUE,'NEW ATD PER TEAM'!$D$99,'NEW ATD PER TEAM'!$D102),'[1]Total 2'!L:L) -> #VALUE! | K102: =J102*68/40 -> #VALUE! | L102: =SUMIF('[1]Total 2'!$I:$I,_xlfn.TEXTJOIN(" ",TRUE,'NEW ATD PER TEAM'!$D$99,'NEW ATD PER TEAM'!$D102),'[1]Total 2'!O:O) -> #VALUE! | M102: =IFERROR(L102/K102,0) -> 0 | N102: =J102*68/24 -> #VALUE! | O102: =SUMIF('[1]Total 2'!$I:$I,_xlfn.TEXTJOIN(" ",TRUE,'NEW ATD PER TEAM'!$D$99,'NEW ATD PER TEAM'!$D102),'[1]Total 2'!R:R) -> #VALUE! | P102: =IFERROR(O102/N102,0) -> 0 | Q102: =J102*68/24 -> #VALUE! | R102: =SUMIF('[1]Total 2'!$I:$I,_xlfn.TEXTJOIN(" ",TRUE,'NEW ATD PER TEAM'!$D$99,'NEW ATD PER TEAM'!$D102),'[1]Total 2'!U:U) -> #VALUE! | S102: =IFERROR(R102/Q102,0) -> 0 | T102: =J102*68/12 -> #VALUE! | U102: =SUMIF('[1]Total 2'!$I:$I,_xlfn.TEXTJOIN(" ",TRUE,'NEW ATD PER TEAM'!$D$99,'NEW ATD PER TEAM'!$D102),'[1]Total 2'!X:X) -> #VALUE! | V102: =IFERROR(U102/T102,0) -> 0 | W102: =J102*68/12 -> #VALUE! | X102: =SUMIF('[1]Total 2'!$I:$I,_xlfn.TEXTJOIN(" ",TRUE,'NEW ATD PER TEAM'!$D$99,'NEW ATD PER TEAM'!$D102),'[1]Total 2'!AA:AA) -> #VALUE! | Y102: =IFERROR(X102/W102,0) -> 0 | Z102: =SUMIF('[1]Total 2'!$I:$I,_xlfn.TEXTJOIN(" ",TRUE,'NEW ATD PER TEAM'!$D$99,'NEW ATD PER TEAM'!$D102),'[1]Total 2'!AC:AC) -> #VALUE! | AA102: =SUMIF('[1]Total 2'!$I:$I,_xlfn.TEXTJOIN(" ",TRUE,'NEW ATD PER TEAM'!$D$99,'NEW ATD PER TEAM'!$D102),'[1]Total 2'!AD:AD) -> #VALUE! | AC102: =J102*1854*40 -> #VALUE! | AD102: =AA102 -> #VALUE! | AE102: =IFERROR(AD102/AC102,"")
...

Sheet Overview Dashboard
C7: Date: (August Tuesday 11th - September Friday 4th 2026)
D10: ACTIVE TEAMS | K10: VOLUME | Q10: VALUE
D13: Target | G13: Achieved | I13: % Achieved | K13: Cases Target | M13: Cases Actual | O13: % cases | Q13: Value Target | U13: Value Actual | Y13: % Value Achieved
D16: ='Overview Dashboard'!I78 -> 168 | G16: =I78 -> 168 | I16: =J78 -> 1 | K16: =S78 -> 37548 | M16: =T78 -> 23115 | O16: =U78 -> 0.61561202 | Q16: =Y78 -> 75096000 | U16: =Z78 -> 43923814 | Y16: =U16/Q16 -> 0.58490218
L57: Daily sales target per BA | M57: 21
L58: Consumer Target | M58: 70
L59: No of BAs per Location | M59: 12
H60: Promoter Update | M60: ATD REACH & CONVERSION | S60: ATD VOLUME | V60: Cash Reconciliation | Y60: ATD Value
K61: Man Days | L61: No of Work Days | M61: Reached Target | N61: Reached Archieved | O61: % Ach | P61: Conversion | Q61: Coversion Target | R61: Strike Rate | S61: Hollandia Evap Milk 120g | V61: Cash Reconciliation | Y61: Sales Performance
C62: S/N | D62: Region | E62: Area/Location | F62: Commenced? | G62: Date of Commencement | H62: Expected No of Promoters | I62: Actual Manning | J62: %Ach.
S63: Target | T63: Actual | U63: %Ach. | V63: Expected | W63: Paid | X63: Variance | Y63: TARGET | Z63: ACTUAL | AA63: %ACD
C64: 1 | D64: East 1 | E64: Enugu/Abakaliki | F64: yes | G64: 46247 | H64: 12 | I64: 12 | J64: =IFERROR(I64/H64,0) -> 1 | K64: =SUMIF(Total!G:G,'Overview Dashboard'!E64,Total!K:K) -> 84 | L64: =SUMIF(Total!G:G,'Overview Dashboard'!E64,Total!M:M) -> 7 | M64: =$M$58*$M$59*L64 -> 5880 | N64: =SUMIF(Total!G:G,'Overview Dashboard'!E64,Total!N:N) -> 5880 | O64: =IFERROR(N64/M64,0) -> 1 | P64: =SUMIF(Total!G:G,'Overview Dashboard'!E64,Total!Q:Q) -> 447 | Q64: =$M$57*$M$59*L64 -> 1764 | R64: =IFERROR(P64/Q64,0) -> 0.25340136 | S64: =H64*L64*$M$57 -> 1764 | T64: =SUMIF(Total!G:G,'Overview Dashboard'!E64,Total!Q:Q) -> 447 | U64: =IFERROR(T64/S64,0) -> 0.25340136 | V64: =T64*2000 -> 894000 | W64: =SUMIF(Total!G:G,'Overview Dashboard'!E64,Total!T:T) -> 844852.28 | X64: =V64-W64 -> 49147.72 | Y64: =H64*L64*2000*21 -> 3528000 | Z64: =W64 -> 844852.28 | AA64: =IFERROR(Z64/Y64,0) -> 0.2394706
C65: 2 | D65: East 1 | E65: Onitsha | F65: yes | G65: 46248 | H65: 12 | I65: 12 | J65: =IFERROR(I65/H65,0) -> 1 | K65: =SUMIF(Total!G:G,'Overview Dashboard'!E65,Total!K:K) -> 120 | L65: =SUMIF(Total!G:G,'Overview Dashboard'!E65,Total!M:M) -> 10 | M65: =$M$58*$M$59*L65 -> 8400 | N65: =SUMIF(Total!G:G,'Overview Dashboard'!E65,Total!N:N) -> 8400 | O65: =IFERROR(N65/M65,0) -> 1 | P65: =SUMIF(Total!G:G,'Overview Dashboard'!E65,Total!Q:Q) -> 1477 | Q65: =$M$57*$M$59*L65 -> 2520 | R65: =IFERROR(P65/Q65,0) -> 0.58611111 | S65: =H65*L65*$M$57 -> 2520 | T65: =SUMIF(Total!G:G,'Overview Dashboard'!E65,Total!Q:Q) -> 1477 | U65: =IFERROR(T65/S65,0) -> 0.58611111 | V65: =T65*2000 -> 2954000 | W65: =SUMIF(Total!G:G,'Overview Dashboard'!E65,Total!T:T) -> 2792792 | X65: =V65-W65 -> 161208 | Y65: =H65*L65*2000*21 -> 5040000 | Z65: =W65 -> 2792792 | AA65: =IFERROR(Z65/Y65,0) -> 0.5541254
C66: 3 | D66: East 1 | E66: Asaba | F66: yes | G66: 46247 | H66: 12 | I66: 12 | J66: =IFERROR(I66/H66,0) -> 1 | K66: =SUMIF(Total!G:G,'Overview Dashboard'!E66,Total!K:K) -> 108 | L66: =SUMIF(Total!G:G,'Overview Dashboard'!E66,Total!M:M) -> 9 | M66: =$M$58*$M$59*L66 -> 7560 | N66: =SUMIF(Total!G:G,'Overview Dashboard'!E66,Total!N:N) -> 7560 | O66: =IFERROR(N66/M66,0) -> 1 | P66: =SUMIF(Total!G:G,'Overview Dashboard'!E66,Total!Q:Q) -> 674 | Q66: =$M$57*$M$59*L66 -> 2268 | R66: =IFERROR(P66/Q66,0) -> 0.29717813 | S66: =H66*L66*$M$57 -> 2268 | T66: =SUMIF(Total!G:G,'Overview Dashboard'!E66,Total!Q:Q) -> 674 | U66: =IFERROR(T66/S66,0) -> 0.29717813 | V66: =T66*2000 -> 1348000 | W66: =SUMIF(Total!G:G,'Overview Dashboard'!E66,Total!T:T) -> 1272512 | X66: =V66-W66 -> 75488 | Y66: =H66*L66*2000*21 -> 4536000 | Z66: =W66 -> 1272512 | AA66: =IFERROR(Z66/Y66,0) -> 0.28053616
C67: 4 | D67: East 1 | E67: Owerri | F67: yes | G67: 46251 | H67: 12 | I67: 12 | J67: =IFERROR(I67/H67,0) -> 1 | K67: =SUMIF(Total!G:G,'Overview Dashboard'!E67,Total!K:K) -> 192 | L67: =SUMIF(Total!G:G,'Overview Dashboard'!E67,Total!M:M) -> 16 | M67: =$M$58*$M$59*L67 -> 13440 | N67: =SUMIF(Total!G:G,'Overview Dashboard'!E67,Total!N:N) -> 13440 | O67: =IFERROR(N67/M67,0) -> 1 | P67: =SUMIF(Total!G:G,'Overview Dashboard'!E67,Total!Q:Q) -> 3399 | Q67: =$M$57*$M$59*L67 -> 4032 | R67: =IFERROR(P67/Q67,0) -> 0.84300595 | S67: =H67*L67*$M$57 -> 4032 | T67: =SUMIF(Total!G:G,'Overview Dashboard'!E67,Total!Q:Q) -> 3399 | U67: =IFERROR(T67/S67,0) -> 0.84300595 | V67: =T67*2000 -> 6798000 | W67: =SUMIF(Total!G:G,'Overview Dashboard'!E67,Total!T:T) -> 6476896 | X67: =V67-W67 -> 321104 | Y67: =H67*L67*2000*21 -> 8064000 | Z67: =W67 -> 6476896 | AA67: =IFERROR(Z67/Y67,0) -> 0.80318651
C68: 5 | D68: East 2 | E68: Aba | F68: Yes | G68: 46245 | H68: 12 | I68: 12 | J68: =IFERROR(I68/H68,0) -> 1 | K68: =SUMIF(Total!G:G,'Overview Dashboard'!E68,Total!K:K) -> 12 | L68: =SUMIF(Total!G:G,'Overview Dashboard'!E68,Total!M:M) -> 1 | M68: =$M$58*$M$59*L68 -> 840 | N68: =SUMIF(Total!G:G,'Overview Dashboard'!E68,Total!N:N) -> 840 | O68: =IFERROR(N68/M68,0) -> 1 | P68: =SUMIF(Total!G:G,'Overview Dashboard'!E68,Total!Q:Q) -> 53 | Q68: =$M$57*$M$59*L68 -> 252 | R68: =IFERROR(P68/Q68,0) -> 0.21031746 | S68: =H68*L68*$M$57 -> 252 | T68: =SUMIF(Total!G:G,'Overview Dashboard'!E68,Total!Q:Q) -> 53 | U68: =IFERROR(T68/S68,0) -> 0.21031746 | V68: =T68*2000 -> 106000 | W68: =SUMIF(Total!G:G,'Overview Dashboard'!E68,Total!T:T) -> 100064 | X68: =V68-W68 -> 5936 | Y68: =H68*L68*2000*21 -> 504000 | Z68: =W68 -> 100064 | AA68: =IFERROR(Z68/Y68,0) -> 0.19853968
C69: 6 | D69: East 2 | E69: PHC 1 | F69: Yes | G69: 46248 | H69: 12 | I69: 12 | J69: =IFERROR(I69/H69,0) -> 1 | K69: =SUMIF(Total!G:G,'Overview Dashboard'!E69,Total!K:K) -> 168 | L69: =SUMIF(Total!G:G,'Overview Dashboard'!E69,Total!M:M) -> 14 | M69: =$M$58*$M$59*L69 -> 11760 | N69: =SUMIF(Total!G:G,'Overview Dashboard'!E69,Total!N:N) -> 11760 | O69: =IFERROR(N69/M69,0) -> 1 | P69: =SUMIF(Total!G:G,'Overview Dashboard'!E69,Total!Q:Q) -> 2337 | Q69: =$M$57*$M$59*L69 -> 3528 | R69: =IFERROR(P69/Q69,0) -> 0.66241497 | S69: =H69*L69*$M$57 -> 3528 | T69: =SUMIF(Total!G:G,'Overview Dashboard'!E69,Total!Q:Q) -> 2337 | U69: =IFERROR(T69/S69,0) -> 0.66241497 | V69: =T69*2000 -> 4674000 | W69: =SUMIF(Total!G:G,'Overview Dashboard'!E69,Total!T:T) -> 4440480 | X69: =V69-W69 -> 233520 | Y69: =H69*L69*2000*21 -> 7056000 | Z69: =W69 -> 4440480 | AA69: =IFERROR(Z69/Y69,0) -> 0.62931973
C70: 7 | D70: East 2 | E70: Bayelsa | F70: Yes | G70: 46248 | H70: 12 | I70: 12 | J70: =IFERROR(I70/H70,0) -> 1 | K70: =SUMIF(Total!G:G,'Overview Dashboard'!E70,Total!K:K) -> 120 | L70: =SUMIF(Total!G:G,'Overview Dashboard'!E70,Total!M:M) -> 10 | M70: =$M$58*$M$59*L70 -> 8400 | N70: =SUMIF(Total!G:G,'Overview Dashboard'!E70,Total!N:N) -> 8400 | O70: =IFERROR(N70/M70,0) -> 1 | P70: =SUMIF(Total!G:G,'Overview Dashboard'!E70,Total!Q:Q) -> 2240 | Q70: =$M$57*$M$59*L70 -> 2520 | R70: =IFERROR(P70/Q70,0) -> 0.88888889 | S70: =H70*L70*$M$57 -> 2520 | T70: =SUMIF(Total!G:G,'Overview Dashboard'!E70,Total!Q:Q) -> 2240 | U70: =IFERROR(T70/S70,0) -> 0.88888889 | V70: =T70*2000 -> 4480000 | W70: =SUMIF(Total!G:G,'Overview Dashboard'!E70,Total!T:T) -> 4265211 | X70: =V70-W70 -> 214789 | Y70: =H70*L70*2000*21 -> 5040000 | Z70: =W70 -> 4265211 | AA70: =IFERROR(Z70/Y70,0) -> 0.84627202
C71: 8 | D71: East 2 | E71: Uyo | F71: Yes | G71: 46246 | H71: 12 | I71: 12 | J71: =IFERROR(I71/H71,0) -> 1 | K71: =SUMIF(Total!G:G,'Overview Dashboard'!E71,Total!K:K) -> 168 | L71: =SUMIF(Total!G:G,'Overview Dashboard'!E71,Total!M:M) -> 14 | M71: =$M$58*$M$59*L71 -> 11760 | N71: =SUMIF(Total!G:G,'Overview Dashboard'!E71,Total!N:N) -> 11760 | O71: =IFERROR(N71/M71,0) -> 1 | P71: =SUMIF(Total!G:G,'Overview Dashboard'!E71,Total!Q:Q) -> 1756 | Q71: =$M$57*$M$59*L71 -> 3528 | R71: =IFERROR(P71/Q71,0) -> 0.49773243 | S71: =H71*L71*$M$57 -> 3528 | T71: =SUMIF(Total!G:G,'Overview Dashboard'!E71,Total!Q:Q) -> 1756 | U71: =IFERROR(T71/S71,0) -> 0.49773243 | V71: =T71*2000 -> 3512000 | W71: =SUMIF(Total!G:G,'Overview Dashboard'!E71,Total!T:T) -> 3315328 | X71: =V71-W71 -> 196672 | Y71: =H71*L71*2000*21 -> 7056000 | Z71: =W71 -> 3315328 | AA71: =IFERROR(Z71/Y71,0) -> 0.46985941
C72: 9 | D72: East 2 | E72: Calabar | F72: Yes | G72: 46245 | H72: 12 | I72: 12 | J72: =IFERROR(I72/H72,0) -> 1 | K72: =SUMIF(Total!G:G,'Overview Dashboard'!E72,Total!K:K) -> 144 | L72: =SUMIF(Total!G:G,'Overview Dashboard'!E72,Total!M:M) -> 12 | M72: =$M$58*$M$59*L72 -> 10080 | N72: =SUMIF(Total!G:G,'Overview Dashboard'!E72,Total!N:N) -> 10080 | O72: =IFERROR(N72/M72,0) -> 1 | P72: =SUMIF(Total!G:G,'Overview Dashboard'!E72,Total!Q:Q) -> 1326 | Q72: =$M$57*$M$59*L72 -> 3024 | R72: =IFERROR(P72/Q72,0) -> 0.43849206 | S72: =H72*L72*$M$57 -> 3024 | T72: =SUMIF(Total!G:G,'Overview Dashboard'!E72,Total!Q:Q) -> 1326 | U72: =IFERROR(T72/S72,0) -> 0.43849206 | V72: =T72*2000 -> 2652000 | W72: =SUMIF(Total!G:G,'Overview Dashboard'!E72,Total!T:T) -> 2513980 | X72: =V72-W72 -> 138020 | Y72: =H72*L72*2000*21 -> 6048000 | Z72: =W72 -> 2513980 | AA72: =IFERROR(Z72/Y72,0) -> 0.4156713
C73: 10 | D73: West 2 | E73: Benin | F73: Yes | G73: 46247 | H73: 12 | I73: 12 | J73: =IFERROR(I73/H73,0) -> 1 | K73: =SUMIF(Total!G:G,'Overview Dashboard'!E73,Total!K:K) -> 120 | L73: =SUMIF(Total!G:G,'Overview Dashboard'!E73,Total!M:M) -> 10 | M73: =$M$58*$M$59*L73 -> 8400 | N73: =SUMIF(Total!G:G,'Overview Dashboard'!E73,Total!N:N) -> 8400 | O73: =IFERROR(N73/M73,0) -> 1 | P73: =SUMIF(Total!G:G,'Overview Dashboard'!E73,Total!Q:Q) -> 975 | Q73: =$M$57*$M$59*L73 -> 2520 | R73: =IFERROR(P73/Q73,0) -> 0.38690476 | S73: =H73*L73*$M$57 -> 2520 | T73: =SUMIF(Total!G:G,'Overview Dashboard'!E73,Total!Q:Q) -> 975 | U73: =IFERROR(T73/S73,0) -> 0.38690476 | V73: =T73*2000 -> 1950000 | W73: =SUMIF(Total!G:G,'Overview Dashboard'!E73,Total!T:T) -> 1851711 | X73: =V73-W73 -> 98289 | Y73: =H73*L73*2000*21 -> 5040000 | Z73: =W73 -> 1851711 | AA73: =IFERROR(Z73/Y73,0) -> 0.36740298
C74: 11 | D74: West 2 | E74: Auchi | F74: Yes | G74: 46251 | H74: 12 | I74: 12 | J74: =IFERROR(I74/H74,0) -> 1 | K74: =SUMIF(Total!G:G,'Overview Dashboard'!E74,Total!K:K) -> 204 | L74: =SUMIF(Total!G:G,'Overview Dashboard'!E74,Total!M:M) -> 17 | M74: =$M$58*$M$59*L74 -> 14280 | N74: =SUMIF(Total!G:G,'Overview Dashboard'!E74,Total!N:N) -> 14280 | O74: =IFERROR(N74/M74,0) -> 1 | P74: =SUMIF(Total!G:G,'Overview Dashboard'!E74,Total!Q:Q) -> 3804 | Q74: =$M$57*$M$59*L74 -> 4284 | R74: =IFERROR(P74/Q74,0) -> 0.88795518 | S74: =H74*L74*$M$57 -> 4284 | T74: =SUMIF(Total!G:G,'Overview Dashboard'!E74,Total!Q:Q) -> 3804 | U74: =IFERROR(T74/S74,0) -> 0.88795518 | V74: =T74*2000 -> 7608000 | W74: =SUMIF(Total!G:G,'Overview Dashboard'!E74,Total!T:T) -> 7239072 | X74: =V74-W74 -> 368928 | Y74: =H74*L74*2000*21 -> 8568000 | Z74: =W74 -> 7239072 | AA74: =IFERROR(Z74/Y74,0) -> 0.84489636
C75: 12 | D75: West 2 | E75: Akure | F75: yes | G75: 46247 | H75: 12 | I75: 12 | J75: =IFERROR(I75/H75,0) -> 1 | K75: =SUMIF(Total!G:G,'Overview Dashboard'!E75,Total!K:K) -> 48 | L75: =SUMIF(Total!G:G,'Overview Dashboard'!E75,Total!M:M) -> 4 | M75: =$M$58*$M$59*L75 -> 3360 | N75: =SUMIF(Total!G:G,'Overview Dashboard'!E75,Total!N:N) -> 3360 | O75: =IFERROR(N75/M75,0) -> 1 | P75: =SUMIF(Total!G:G,'Overview Dashboard'!E75,Total!Q:Q) -> 391 | Q75: =$M$57*$M$59*L75 -> 1008 | R75: =IFERROR(P75/Q75,0) -> 0.38789683 | S75: =H75*L75*$M$57 -> 1008 | T75: =SUMIF(Total!G:G,'Overview Dashboard'!E75,Total!Q:Q) -> 391 | U75: =IFERROR(T75/S75,0) -> 0.38789683 | V75: =T75*2000 -> 782000 | W75: =SUMIF(Total!G:G,'Overview Dashboard'!E75,Total!T:T) -> 738208 | X75: =V75-W75 -> 43792 | Y75: =H75*L75*2000*21 -> 2016000 | Z75: =W75 -> 738208 | AA75: =IFERROR(Z75/Y75,0) -> 0.3661746
... C77: 14 | D77: West 2 | E77: Warri | F77: yes | G77: 46248 | H77: 12 | I77: 12 | J77: =IFERROR(I77/H77,0) -> 1 | K77: =SUMIF(Total!G:G,'Overview Dashboard'!E77,Total!K:K) -> 156 | L77: =SUMIF(Total!G:G,'Overview Dashboard'!E77,Total!M:M) -> 13 | M77: =$M$58*$M$59*L77 -> 10920 | N77: =SUMIF(Total!G:G,'Overview Dashboard'!E77,Total!N:N) -> 10920 | O77: =IFERROR(N77/M77,0) -> 1 | P77: =SUMIF(Total!G:G,'Overview Dashboard'!E77,Total!Q:Q) -> 2550 | Q77: =$M$57*$M$59*L77 -> 3276 | R77: =IFERROR(P77/Q77,0) -> 0.77838828 | S77: =H77*L77*$M$57 -> 3276 | T77: =SUMIF(Total!G:G,'Overview Dashboard'!E77,Total!Q:Q) -> 2550 | U77: =IFERROR(T77/S77,0) -> 0.77838828 | V77: =T77*2000 -> 5100000 | W77: =SUMIF(Total!G:G,'Overview Dashboard'!E77,Total!T:T) -> 4852412 | X77: =V77-W77 -> 247588 | Y77: =H77*L77*2000*21 -> 6552000 | Z77: =W77 -> 4852412 | AA77: =IFERROR(Z77/Y77,0) -> 0.74060012
C78: TOTAL | H78: =SUM(H64:H77) -> 168 | I78: =SUM(I64:I77) -> 168 | J78: =I78/H78 -> 1 | K78: =SUM(K64:K77) -> 1788 | L78: =SUM(L64:L77) -> 149 | M78: =SUM(M64:M77) -> 125160 | N78: =SUM(N64:N77) -> 125160 | O78: =N78/M78 -> 1 | P78: =SUM(P64:P77) -> 23115 | Q78: =SUM(Q64:Q77) -> 37548 | R78: =P78/Q78 -> 0.61561202 | S78: =SUM(S64:S77) -> 37548 | T78: =SUM(T64:T77) -> 23115 | U78: =T78/S78 -> 0.61561202 | V78: =SUM(V64:V77) -> 46230000 | W78: =SUM(W64:W77) -> 43923814 | X78: =SUM(X64:X77) -> 2306185.7 | Y78: =SUM(Y64:Y77) -> 75096000 | Z78: =SUM(Z64:Z77) -> 43923814 | AA78: =IFERROR(Z78/Y78,0) -> 0.58490218
H81: Promoters Update | M81: ATD REACH & CONVERSION | S81: ATD VOLUME | V81: Cash Reconciliation | Y81: Sales Performance
G82: Region | H82: Expected No of Promoters | I82: Actual Manning | J82: %Ach. | K82: Man Days | L82: No of Work Days | M82: Reached Target | N82: Reached Achieved | O82: %Ach | P82: Conversion | Q82: Coversion Target | R82: Strike Rate | S82: Hollandia Evap Milk 120g | V82: Cash Reconciliation | Y82: PER REGION
S83: Target | T83: Actual | U83: %Ach. | V83: Expected | W83: Paid | X83: Variance | Y83: TARGET | Z83: ACTUAL | AA83: %ACD
G84: East 1 | H84: =SUMIF($D$64:$D$77,$G84,H$64:H$77) -> 48 | I84: =SUMIF($D$64:$D$77,$G84,I$64:I$77) -> 48 | J84: =IFERROR(I84/H84,"") -> 1 | K84: =SUMIF($D$64:$D$77,$G84,K$64:K$77) -> 504 | L84: =SUMIF($D$64:$D$77,$G84,L$64:L$77) -> 42 | M84: =SUMIF($D$64:$D$77,$G84,M$64:M$77) -> 35280 | N84: =SUMIF($D$64:$D$77,$G84,N$64:N$77) -> 35280 | O84: =SUMIF($D$64:$D$77,$G84,O$64:O$77) -> 4 | P84: =SUMIF($D$64:$D$77,$G84,P$64:P$77) -> 5997 | Q84: =SUMIF($D$64:$D$77,$G84,Q$64:Q$77) -> 10584 | R84: =SUMIF($D$64:$D$77,$G84,R$64:R$77) -> 1.9796966 | ... T84: =SUMIF($D$64:$D$77,$G84,T$64:T$77) -> 5997 | U84: =IFERROR(T84/S84,"") -> 0.56660998 | V84: =SUMIF($D$64:$D$77,$G84,V$64:V$77) -> 11994000 | W84: =SUMIF($D$64:$D$77,$G84,W$64:W$77) -> 11387052 | X84: =V84-W84 -> 606947.72 | Y84: =SUMIF($D$64:$D$77,$G84,Y$64:Y$77) -> 21168000 | Z84: =SUMIF($D$64:$D$77,$G84,Z$64:Z$77) -> 11387052 | AA84: =IFERROR(Z84/Y84,"") -> 0.53793709
G85: East 2 | H85: =SUMIF($D$64:$D$77,$G85,H$64:H$77) -> 60 | I85: =SUMIF($D$64:$D$77,$G85,I$64:I$77) -> 60 | J85: =IFERROR(I85/H85,"") -> 1 | K85: =SUMIF($D$64:$D$77,$G85,K$64:K$77) -> 612 | L85: =SUMIF($D$64:$D$77,$G85,L$64:L$77) -> 51 | M85: =SUMIF($D$64:$D$77,$G85,M$64:M$77) -> 42840 | N85: =SUMIF($D$64:$D$77,$G85,N$64:N$77) -> 42840 | O85: =SUMIF($D$64:$D$77,$G85,O$64:O$77) -> 5 | P85: =SUMIF($D$64:$D$77,$G85,P$64:P$77) -> 7712 | Q85: =SUMIF($D$64:$D$77,$G85,Q$64:Q$77) -> 12852 | R85: =SUMIF($D$64:$D$77,$G85,R$64:R$77) -> 2.6978458 | ... T85: =SUMIF($D$64:$D$77,$G85,T$64:T$77) -> 7712 | U85: =IFERROR(T85/S85,"") -> 0.60006225 | V85: =SUMIF($D$64:$D$77,$G85,V$64:V$77) -> 15424000 | W85: =SUMIF($D$64:$D$77,$G85,W$64:W$77) -> 14635063 | X85: =V85-W85 -> 788937 | Y85: =SUMIF($D$64:$D$77,$G85,Y$64:Y$77) -> 25704000 | Z85: =SUMIF($D$64:$D$77,$G85,Z$64:Z$77) -> 14635063 | AA85: =IFERROR(Z85/Y85,"") -> 0.56936909
G86: West 2 | H86: =SUMIF($D$64:$D$77,$G86,H$64:H$77) -> 60 | I86: =SUMIF($D$64:$D$77,$G86,I$64:I$77) -> 60 | J86: =IFERROR(I86/H86,"") -> 1 | K86: =SUMIF($D$64:$D$77,$G86,K$64:K$77) -> 672 | L86: =SUMIF($D$64:$D$77,$G86,L$64:L$77) -> 56 | M86: =SUMIF($D$64:$D$77,$G86,M$64:M$77) -> 47040 | N86: =SUMIF($D$64:$D$77,$G86,N$64:N$77) -> 47040 | O86: =SUMIF($D$64:$D$77,$G86,O$64:O$77) -> 5 | P86: =SUMIF($D$64:$D$77,$G86,P$64:P$77) -> 9406 | Q86: =SUMIF($D$64:$D$77,$G86,Q$64:Q$77) -> 14112 | R86: =SUMIF($D$64:$D$77,$G86,R$64:R$77) -> 2.9986847 | ... T86: =SUMIF($D$64:$D$77,$G86,T$64:T$77) -> 9406 | U86: =IFERROR(T86/S86,"") -> 0.66652494 | V86: =SUMIF($D$64:$D$77,$G86,V$64:V$77) -> 18812000 | W86: =SUMIF($D$64:$D$77,$G86,W$64:W$77) -> 17901699 | X86: =V86-W86 -> 910301 | Y86: =SUMIF($D$64:$D$77,$G86,Y$64:Y$77) -> 28224000 | Z86: =SUMIF($D$64:$D$77,$G86,Z$64:Z$77) -> 17901699 | AA86: =IFERROR(Z86/Y86,"") -> 0.63427222
G87: TOTAL | H87: =SUM(H84:H86) -> 168 | I87: =SUM(I84:I86) -> 168 | J87: =IFERROR(I87/H87,"") -> 1 | K87: =SUM(K84:K86) -> 1788 | L87: =SUM(L84:L86) -> 149 | M87: =SUM(M84:M86) -> 125160 | N87: =SUM(N84:N86) -> 125160 | O87: =N87/M87 -> 1 | P87: =SUM(P84:P86) -> 23115 | Q87: =SUM(Q84:Q86) -> 37548 | R87: =P87/Q87 -> 0.61561202 | S87: =SUM(S84:S86) -> 37548 | T87: =SUM(T84:T86) -> 23115 | U87: =T87/S87 -> 0.61561202 | V87: =SUM(V84:V86) -> 46230000 | W87: =SUM(W84:W86) -> 43923814 | X87: =SUM(X84:X86) -> 2306185.7 | Y87: =SUM(Y84:Y86) -> 75096000 | Z87: =SUM(Z84:Z86) -> 43923814 | AA87: =IFERROR(Z87/Y87,"") -> 0.58490218

Sheet Sheet8
A3: Row Labels | B3: Sum of Expected No of Promoters | C3: Sum of Actual Manning | D3: Sum of % Ach
A4: East 1 | B4: 48 | C4: 48 | D4: 0.56689342
A5: East 2 | B5: 60 | C5: 60 | D5: 0.60006225
A6: West 2 | B6: 60 | C6: 60 | D6: 0.66652494
A7: Grand Total | B7: 168 | C7: 168 | D7: 0.61569191
A11: Row Labels | B11: Sum of Target Consumer days | C11: Sum of Actual Consumer Days
A12: East 1 | B12: 50400 | C12: 50400
A13: East 2 | B13: 73440 | C13: 73440
A14: West 2 | B14: 36000 | C14: 36000
A15: Grand Total | B15: 159840 | C15: 159840
D16: =D18/D17 -> 1
D17: =GETPIVOTDATA("Sum of Target Consumer days",$A$11) -> 159840 | E17: Target
D18: =GETPIVOTDATA("Sum of Actual Consumer Days ",$A$11) -> 159840 | E18: Actual
A19: Row Labels | B19: Sum of Target Volume | C19: Sum of Total Volume
A20: East 1 | B20: 10584 | C20: 6000
A21: East 2 | B21: 12852 | C21: 7712
A22: West 2 | B22: 14112 | C22: 9406
A23: Grand Total | B23: 37548 | C23: 23118
A26: Row Labels | B26: Sum of Target Hollandia Evap Milk 120g | C26: Sum of Actual Hollandia Evap Milk 120g
A27: East 1 | B27: 10584 | C27: 6000
A28: East 2 | B28: 12852 | C28: 7712
A29: West 2 | B29: 14112 | C29: 9406
A30: Grand Total | B30: 37548 | C30: 23118
A34: Row Labels | B34: Target_Volume | C34: Actual _Volume | D34: % Ach
A35: Aba | B35: 252 | C35: 53 | D35: 0.21031746
A36: Ado-Ekiti | B36: 3024 | C36: 1686 | D36: 0.55753968
A37: Asaba | B37: 2268 | C37: 674 | D37: 0.29717813
A38: Bayelsa | B38: 2520 | C38: 2240 | D38: 0.88888889
A39: Calabar | B39: 3024 | C39: 1326 | D39: 0.43849206
A40: Onitsha | B40: 2520 | C40: 1477 | D40: 0.58611111
A41: Owerri | B41: 4032 | C41: 3399 | D41: 0.84300595
A42: PHC 1 | B42: 3528 | C42: 2337 | D42: 0.66241497
A43: Uyo | B43: 3528 | C43: 1756 | D43: 0.49773243
A44: Warri | B44: 3276 | C44: 2550 | D44: 0.77838828
A45: Akure | B45: 1008 | C45: 391 | D45: 0.38789683
A46: Benin | B46: 2520 | C46: 975 | D46: 0.38690476
... A49: Grand Total | B49: 37548 | C49: 23118 | D49: 0.61569191

Sheet ATD Daily> (2)
L1: Daily sales target per BA | M1: 21
L2: Consumer Target | M2: 60
L3: NO OF Bas per Location | M3: 12
I4: Promoter Update | N4: ATD REACH & CONVERSION | T4: ATD VOLUME | W4: Cash Reconciliation | Z4: ATD Value
L5: Man Days | M5: No of Work Days | N5: Reached Target | O5: Reached Archieved | T5: Hollandia Evap Milk 120g | W5: Cash Reconciliation | Z5: Sales Performance
C6: S/N | D6: Region | E6: Area/Location | F6: Agency Supervisor | G6: Commenced? | H6: Date of Commencement | I6: Expected No of Promoters | J6: Actual Manning | K6: %Ach. | P6: % Ach | Q6: Conversion | S6: Strike Rate
T7: Target | U7: Actual | V7: %Ach. | W7: Expected | X7: Paid | Y7: Variance | Z7: TARGET | AA7: ACTUAL | AB7: %ACD
C8: 1 | D8: East 1 | E8: Enugu/Abakaliki | F8: MUDIA | I8: 12 | J8: 12 | K8: =IFERROR(J8/I8,0) -> 1 | L8: =SUMIF(Total!G:G,'ATD Daily> (2)'!E8,Total!K:K) -> 84 | M8: =SUMIF(Total!G:G,'ATD Daily> (2)'!E8,Total!M:M) -> 7 | N8: =$M$2*$M$3*M8 -> 5040 | O8: =SUMIF(Total!G:G,'ATD Daily> (2)'!E8,Total!N:N) -> 5880 | P8: =IFERROR(O8/N8,0) -> 1.1666667 | Q8: =SUMIF(Total!G:G,'ATD Daily> (2)'!E8,Total!P:P) -> 450 | S8: =IFERROR(Q8/O8,0) -> 0.076530612 | T8: =I8*M8*$M$1 -> 1764 | U8: =SUMIF(Total!G:G,'ATD Daily> (2)'!E8,Total!P:P) -> 450 | V8: =IFERROR(U8/T8,0) -> 0.25510204 | W8: =U8*2000 -> 900000 | X8: =SUMIF(Total!G:G,'ATD Daily> (2)'!E8,Total!T:T) -> 844852.28 | Y8: =W8-X8 -> 55147.72 | Z8: =I8*M8*2000*21 -> 3528000 | AA8: =X8 -> 844852.28 | AB8: =IFERROR(AA8/Z8,0) -> 0.2394706
C9: 2 | D9: East 1 | E9: Abakaliki | I9: 12 | J9: 12 | K9: =IFERROR(J9/I9,0) -> 1 | L9: =SUMIF(Total!G:G,'ATD Daily> (2)'!E9,Total!K:K) -> 0 | M9: =SUMIF(Total!G:G,'ATD Daily> (2)'!E9,Total!M:M) -> 0 | N9: =$M$2*$M$3*M9 -> 0 | O9: =SUMIF(Total!G:G,'ATD Daily> (2)'!E9,Total!N:N) -> 0 | P9: =IFERROR(O9/N9,0) -> 0 | Q9: =SUMIF(Total!G:G,'ATD Daily> (2)'!E9,Total!P:P) -> 0 | S9: =IFERROR(Q9/O9,0) -> 0 | T9: =I9*M9*$M$1 -> 0 | U9: =SUMIF(Total!G:G,'ATD Daily> (2)'!E9,Total!P:P) -> 0 | V9: =IFERROR(U9/T9,0) -> 0 | W9: =U9*2000 -> 0 | X9: =SUMIF(Total!G:G,'ATD Daily> (2)'!E9,Total!T:T) -> 0 | Y9: =W9-X9 -> 0 | Z9: =I9*M9*2000*21 -> 0 | AA9: =X9 -> 0 | AB9: =IFERROR(AA9/Z9,0) -> 0
C10: 3 | D10: East 1 | E10: Onitsha | I10: 12 | J10: 12 | K10: =IFERROR(J10/I10,0) -> 1 | L10: =SUMIF(Total!G:G,'ATD Daily> (2)'!E10,Total!K:K) -> 120 | M10: =SUMIF(Total!G:G,'ATD Daily> (2)'!E10,Total!M:M) -> 10 | N10: =$M$2*$M$3*M10 -> 7200 | O10: =SUMIF(Total!G:G,'ATD Daily> (2)'!E10,Total!N:N) -> 8400 | P10: =IFERROR(O10/N10,0) -> 1.1666667 | Q10: =SUMIF(Total!G:G,'ATD Daily> (2)'!E10,Total!P:P) -> 1477 | S10: =IFERROR(Q10/O10,0) -> 0.17583333 | T10: =I10*M10*$M$1 -> 2520 | U10: =SUMIF(Total!G:G,'ATD Daily> (2)'!E10,Total!P:P) -> 1477 | V10: =IFERROR(U10/T10,0) -> 0.58611111 | W10: =U10*2000 -> 2954000 | X10: =SUMIF(Total!G:G,'ATD Daily> (2)'!E10,Total!T:T) -> 2792792 | Y10: =W10-X10 -> 161208 | Z10: =I10*M10*2000*21 -> 5040000 | AA10: =X10 -> 2792792 | AB10: =IFERROR(AA10/Z10,0) -> 0.5541254
C11: 4 | D11: East 1 | E11: Asaba | F11: IFEANYI CHIADIKABIA | I11: 12 | J11: 12 | K11: =IFERROR(J11/I11,0) -> 1 | L11: =SUMIF(Total!G:G,'ATD Daily> (2)'!E11,Total!K:K) -> 108 | M11: =SUMIF(Total!G:G,'ATD Daily> (2)'!E11,Total!M:M) -> 9 | N11: =$M$2*$M$3*M11 -> 6480 | O11: =SUMIF(Total!G:G,'ATD Daily> (2)'!E11,Total!N:N) -> 7560 | P11: =IFERROR(O11/N11,0) -> 1.1666667 | Q11: =SUMIF(Total!G:G,'ATD Daily> (2)'!E11,Total!P:P) -> 674 | S11: =IFERROR(Q11/O11,0) -> 0.089153439 | T11: =I11*M11*$M$1 -> 2268 | U11: =SUMIF(Total!G:G,'ATD Daily> (2)'!E11,Total!P:P) -> 674 | V11: =IFERROR(U11/T11,0) -> 0.29717813 | W11: =U11*2000 -> 1348000 | X11: =SUMIF(Total!G:G,'ATD Daily> (2)'!E11,Total!T:T) -> 1272512 | Y11: =W11-X11 -> 75488 | Z11: =I11*M11*2000*21 -> 4536000 | AA11: =X11 -> 1272512 | AB11: =IFERROR(AA11/Z11,0) -> 0.28053616
C12: 5 | D12: East 1 | E12: Owerri | I12: 12 | J12: 12 | K12: =IFERROR(J12/I12,0) -> 1 | L12: =SUMIF(Total!G:G,'ATD Daily> (2)'!E12,Total!K:K) -> 192 | M12: =SUMIF(Total!G:G,'ATD Daily> (2)'!E12,Total!M:M) -> 16 | N12: =$M$2*$M$3*M12 -> 11520 | O12: =SUMIF(Total!G:G,'ATD Daily> (2)'!E12,Total!N:N) -> 13440 | P12: =IFERROR(O12/N12,0) -> 1.1666667 | Q12: =SUMIF(Total!G:G,'ATD Daily> (2)'!E12,Total!P:P) -> 3399 | S12: =IFERROR(Q12/O12,0) -> 0.25290179 | T12: =I12*M12*$M$1 -> 4032 | U12: =SUMIF(Total!G:G,'ATD Daily> (2)'!E12,Total!P:P) -> 3399 | V12: =IFERROR(U12/T12,0) -> 0.84300595 | W12: =U12*2000 -> 6798000 | X12: =SUMIF(Total!G:G,'ATD Daily> (2)'!E12,Total!T:T) -> 6476896 | Y12: =W12-X12 -> 321104 | Z12: =I12*M12*2000*21 -> 8064000 | AA12: =X12 -> 6476896 | AB12: =IFERROR(AA12/Z12,0) -> 0.80318651
C13: 6 | D13: East 2 | E13: Aba | I13: 12 | J13: 12 | K13: =IFERROR(J13/I13,0) -> 1 | L13: =SUMIF(Total!G:G,'ATD Daily> (2)'!E13,Total!K:K) -> 12 | M13: =SUMIF(Total!G:G,'ATD Daily> (2)'!E13,Total!M:M) -> 1 | N13: =$M$2*$M$3*M13 -> 720 | O13: =SUMIF(Total!G:G,'ATD Daily> (2)'!E13,Total!N:N) -> 840 | P13: =IFERROR(O13/N13,0) -> 1.1666667 | Q13: =SUMIF(Total!G:G,'ATD Daily> (2)'!E13,Total!P:P) -> 53 | S13: =IFERROR(Q13/O13,0) -> 0.063095238 | T13: =I13*M13*$M$1 -> 252 | U13: =SUMIF(Total!G:G,'ATD Daily> (2)'!E13,Total!P:P) -> 53 | V13: =IFERROR(U13/T13,0) -> 0.21031746 | W13: =U13*2000 -> 106000 | X13: =SUMIF(Total!G:G,'ATD Daily> (2)'!E13,Total!T:T) -> 100064 | Y13: =W13-X13 -> 5936 | Z13: =I13*M13*2000*21 -> 504000 | AA13: =X13 -> 100064 | AB13: =IFERROR(AA13/Z13,0) -> 0.19853968
C14: 7 | D14: East 2 | E14: PHC 1 | I14: 12 | J14: 12 | K14: =IFERROR(J14/I14,0) -> 1 | L14: =SUMIF(Total!G:G,'ATD Daily> (2)'!E14,Total!K:K) -> 168 | M14: =SUMIF(Total!G:G,'ATD Daily> (2)'!E14,Total!M:M) -> 14 | N14: =$M$2*$M$3*M14 -> 10080 | O14: =SUMIF(Total!G:G,'ATD Daily> (2)'!E14,Total!N:N) -> 11760 | P14: =IFERROR(O14/N14,0) -> 1.1666667 | Q14: =SUMIF(Total!G:G,'ATD Daily> (2)'!E14,Total!P:P) -> 2337 | S14: =IFERROR(Q14/O14,0) -> 0.19872449 | T14: =I14*M14*$M$1 -> 3528 | U14: =SUMIF(Total!G:G,'ATD Daily> (2)'!E14,Total!P:P) -> 2337 | V14: =IFERROR(U14/T14,0) -> 0.66241497 | W14: =U14*2000 -> 4674000 | X14: =SUMIF(Total!G:G,'ATD Daily> (2)'!E14,Total!T:T) -> 4440480 | Y14: =W14-X14 -> 233520 | Z14: =I14*M14*2000*21 -> 7056000 | AA14: =X14 -> 4440480 | AB14: =IFERROR(AA14/Z14,0) -> 0.62931973
C15: 8 | D15: East 2 | E15: PHC 2 | K15: =IFERROR(J15/I15,0) -> 0 | L15: =SUMIF(Total!G:G,'ATD Daily> (2)'!E15,Total!K:K) -> 0 | M15: =SUMIF(Total!G:G,'ATD Daily> (2)'!E15,Total!M:M) -> 0 | N15: =$M$2*$M$3*M15 -> 0 | O15: =SUMIF(Total!G:G,'ATD Daily> (2)'!E15,Total!N:N) -> 0 | P15: =IFERROR(O15/N15,0) -> 0 | Q15: =SUMIF(Total!G:G,'ATD Daily> (2)'!E15,Total!P:P) -> 0 | S15: =IFERROR(Q15/O15,0) -> 0 | T15: =I15*M15*$M$1 -> 0 | U15: =SUMIF(Total!G:G,'ATD Daily> (2)'!E15,Total!P:P) -> 0 | V15: =IFERROR(U15/T15,0) -> 0 | W15: =U15*2000 -> 0 | X15: =SUMIF(Total!G:G,'ATD Daily> (2)'!E15,Total!T:T) -> 0 | Y15: =W15-X15 -> 0 | Z15: =I15*M15*2000*21 -> 0 | AA15: =X15 -> 0 | AB15: =IFERROR(AA15/Z15,0) -> 0
C16: 9 | D16: East 2 | E16: Bayelsa | I16: 12 | J16: 12 | K16: =IFERROR(J16/I16,0) -> 1 | L16: =SUMIF(Total!G:G,'ATD Daily> (2)'!E16,Total!K:K) -> 120 | M16: =SUMIF(Total!G:G,'ATD Daily> (2)'!E16,Total!M:M) -> 10 | N16: =$M$2*$M$3*M16 -> 7200 | O16: =SUMIF(Total!G:G,'ATD Daily> (2)'!E16,Total!N:N) -> 8400 | P16: =IFERROR(O16/N16,0) -> 1.1666667 | Q16: =SUMIF(Total!G:G,'ATD Daily> (2)'!E16,Total!P:P) -> 2240 | S16: =IFERROR(Q16/O16,0) -> 0.26666667 | T16: =I16*M16*$M$1 -> 2520 | U16: =SUMIF(Total!G:G,'ATD Daily> (2)'!E16,Total!P:P) -> 2240 | V16: =IFERROR(U16/T16,0) -> 0.88888889 | W16: =U16*2000 -> 4480000 | X16: =SUMIF(Total!G:G,'ATD Daily> (2)'!E16,Total!T:T) -> 4265211 | Y16: =W16-X16 -> 214789 | Z16: =I16*M16*2000*21 -> 5040000 | AA16: =X16 -> 4265211 | AB16: =IFERROR(AA16/Z16,0) -> 0.84627202
C17: 10 | D17: East 2 | E17: Uyo | F17: Victor Umeh | G17: yes | H17: 46246 | I17: 12 | J17: 12 | K17: =IFERROR(J17/I17,0) -> 1 | L17: =SUMIF(Total!G:G,'ATD Daily> (2)'!E17,Total!K:K) -> 168 | M17: =SUMIF(Total!G:G,'ATD Daily> (2)'!E17,Total!M:M) -> 14 | N17: =$M$2*$M$3*M17 -> 10080 | O17: =SUMIF(Total!G:G,'ATD Daily> (2)'!E17,Total!N:N) -> 11760 | P17: =IFERROR(O17/N17,0) -> 1.1666667 | Q17: =SUMIF(Total!G:G,'ATD Daily> (2)'!E17,Total!P:P) -> 1756 | S17: =IFERROR(Q17/O17,0) -> 0.14931973 | T17: =I17*M17*$M$1 -> 3528 | U17: =SUMIF(Total!G:G,'ATD Daily> (2)'!E17,Total!P:P) -> 1756 | V17: =IFERROR(U17/T17,0) -> 0.49773243 | W17: =U17*2000 -> 3512000 | X17: =SUMIF(Total!G:G,'ATD Daily> (2)'!E17,Total!T:T) -> 3315328 | Y17: =W17-X17 -> 196672 | Z17: =I17*M17*2000*21 -> 7056000 | AA17: =X17 -> 3315328 | AB17: =IFERROR(AA17/Z17,0) -> 0.46985941
C18: 11 | D18: East 2 | E18: Calabar | F18: ENOIDEM AKPAN | G18: Yes | H18: 46245 | I18: 12 | J18: 12 | K18: =IFERROR(J18/I18,0) -> 1 | L18: =SUMIF(Total!G:G,'ATD Daily> (2)'!E18,Total!K:K) -> 144 | M18: =SUMIF(Total!G:G,'ATD Daily> (2)'!E18,Total!M:M) -> 12 | N18: =$M$2*$M$3*M18 -> 8640 | O18: =SUMIF(Total!G:G,'ATD Daily> (2)'!E18,Total!N:N) -> 10080 | P18: =IFERROR(O18/N18,0) -> 1.1666667 | Q18: =SUMIF(Total!G:G,'ATD Daily> (2)'!E18,Total!P:P) -> 1326 | S18: =IFERROR(Q18/O18,0) -> 0.13154762 | T18: =I18*M18*$M$1 -> 3024 | U18: =SUMIF(Total!G:G,'ATD Daily> (2)'!E18,Total!P:P) -> 1326 | V18: =IFERROR(U18/T18,0) -> 0.43849206 | W18: =U18*2000 -> 2652000 | X18: =SUMIF(Total!G:G,'ATD Daily> (2)'!E18,Total!T:T) -> 2513980 | Y18: =W18-X18 -> 138020 | Z18: =I18*M18*2000*21 -> 6048000 | AA18: =X18 -> 2513980 | AB18: =IFERROR(AA18/Z18,0) -> 0.4156713
C19: 12 | D19: West 1 | E19: Ibadan 1 | K19: =IFERROR(J19/I19,0) -> 0 | L19: =SUMIF(Total!G:G,'ATD Daily> (2)'!E19,Total!K:K) -> 0 | M19: =SUMIF(Total!G:G,'ATD Daily> (2)'!E19,Total!M:M) -> 0 | N19: =$M$2*$M$3*M19 -> 0 | O19: =SUMIF(Total!G:G,'ATD Daily> (2)'!E19,Total!N:N) -> 0 | P19: =IFERROR(O19/N19,0) -> 0 | Q19: =SUMIF(Total!G:G,'ATD Daily> (2)'!E19,Total!P:P) -> 0 | S19: =IFERROR(Q19/O19,0) -> 0 | T19: =I19*M19*$M$1 -> 0 | U19: =SUMIF(Total!G:G,'ATD Daily> (2)'!E19,Total!P:P) -> 0 | V19: =IFERROR(U19/T19,0) -> 0 | W19: =U19*2000 -> 0 | X19: =SUMIF(Total!G:G,'ATD Daily> (2)'!E19,Total!T:T) -> 0 | Y19: =W19-X19 -> 0 | Z19: =I19*M19*2000*21 -> 0 | AA19: =X19 -> 0 | AB19: =IFERROR(AA19/Z19,0) -> 0
C20: 13 | D20: West 1 | E20: Ibadan 2 | K20: =IFERROR(J20/I20,0) -> 0 | L20: =SUMIF(Total!G:G,'ATD Daily> (2)'!E20,Total!K:K) -> 0 | M20: =SUMIF(Total!G:G,'ATD Daily> (2)'!E20,Total!M:M) -> 0 | N20: =$M$2*$M$3*M20 -> 0 | O20: =SUMIF(Total!G:G,'ATD Daily> (2)'!E20,Total!N:N) -> 0 | P20: =IFERROR(O20/N20,0) -> 0 | Q20: =SUMIF(Total!G:G,'ATD Daily> (2)'!E20,Total!P:P) -> 0 | S20: =IFERROR(Q20/O20,0) -> 0 | T20: =I20*M20*$M$1 -> 0 | U20: =SUMIF(Total!G:G,'ATD Daily> (2)'!E20,Total!P:P) -> 0 | V20: =IFERROR(U20/T20,0) -> 0 | W20: =U20*2000 -> 0 | X20: =SUMIF(Total!G:G,'ATD Daily> (2)'!E20,Total!T:T) -> 0 | Y20: =W20-X20 -> 0 | Z20: =I20*M20*2000*21 -> 0 | AA20: =X20 -> 0 | AB20: =IFERROR(AA20/Z20,0) -> 0
C21: 14 | D21: West 1 | E21: Oshogbo | K21: =IFERROR(J21/I21,0) -> 0 | L21: =SUMIF(Total!G:G,'ATD Daily> (2)'!E21,Total!K:K) -> 0 | M21: =SUMIF(Total!G:G,'ATD Daily> (2)'!E21,Total!M:M) -> 0 | N21: =$M$2*$M$3*M21 -> 0 | O21: =SUMIF(Total!G:G,'ATD Daily> (2)'!E21,Total!N:N) -> 0 | P21: =IFERROR(O21/N21,0) -> 0 | Q21: =SUMIF(Total!G:G,'ATD Daily> (2)'!E21,Total!P:P) -> 0 | S21: =IFERROR(Q21/O21,0) -> 0 | T21: =I21*M21*$M$1 -> 0 | U21: =SUMIF(Total!G:G,'ATD Daily> (2)'!E21,Total!P:P) -> 0 | V21: =IFERROR(U21/T21,0) -> 0 | W21: =U21*2000 -> 0 | X21: =SUMIF(Total!G:G,'ATD Daily> (2)'!E21,Total!T:T) -> 0 | Y21: =W21-X21 -> 0 | Z21: =I21*M21*2000*21 -> 0 | AA21: =X21 -> 0 | AB21: =IFERROR(AA21/Z21,0) -> 0
C22: 15 | D22: West 1 | E22: Ilorin | K22: =IFERROR(J22/I22,0) -> 0 | L22: =SUMIF(Total!G:G,'ATD Daily> (2)'!E22,Total!K:K) -> 0 | M22: =SUMIF(Total!G:G,'ATD Daily> (2)'!E22,Total!M:M) -> 0 | N22: =$M$2*$M$3*M22 -> 0 | O22: =SUMIF(Total!G:G,'ATD Daily> (2)'!E22,Total!N:N) -> 0 | P22: =IFERROR(O22/N22,0) -> 0 | Q22: =SUMIF(Total!G:G,'ATD Daily> (2)'!E22,Total!P:P) -> 0 | S22: =IFERROR(Q22/O22,0) -> 0 | T22: =I22*M22*$M$1 -> 0 | U22: =SUMIF(Total!G:G,'ATD Daily> (2)'!E22,Total!P:P) -> 0 | V22: =IFERROR(U22/T22,0) -> 0 | W22: =U22*2000 -> 0 | X22: =SUMIF(Total!G:G,'ATD Daily> (2)'!E22,Total!T:T) -> 0 | Y22: =W22-X22 -> 0 | Z22: =I22*M22*2000*21 -> 0 | AA22: =X22 -> 0 | AB22: =IFERROR(AA22/Z22,0) -> 0
C23: 16 | D23: West 2 | E23: Benin | I23: 12 | J23: 12 | K23: =IFERROR(J23/I23,0) -> 1 | L23: =SUMIF(Total!G:G,'ATD Daily> (2)'!E23,Total!K:K) -> 120 | M23: =SUMIF(Total!G:G,'ATD Daily> (2)'!E23,Total!M:M) -> 10 | N23: =$M$2*$M$3*M23 -> 7200 | O23: =SUMIF(Total!G:G,'ATD Daily> (2)'!E23,Total!N:N) -> 8400 | P23: =IFERROR(O23/N23,0) -> 1.1666667 | Q23: =SUMIF(Total!G:G,'ATD Daily> (2)'!E23,Total!P:P) -> 975 | S23: =IFERROR(Q23/O23,0) -> 0.11607143 | T23: =I23*M23*$M$1 -> 2520 | U23: =SUMIF(Total!G:G,'ATD Daily> (2)'!E23,Total!P:P) -> 975 | V23: =IFERROR(U23/T23,0) -> 0.38690476 | W23: =U23*2000 -> 1950000 | X23: =SUMIF(Total!G:G,'ATD Daily> (2)'!E23,Total!T:T) -> 1851711 | Y23: =W23-X23 -> 98289 | Z23: =I23*M23*2000*21 -> 5040000 | AA23: =X23 -> 1851711 | AB23: =IFERROR(AA23/Z23,0) -> 0.36740298
C24: 17 | D24: West 2 | E24: Auchi | I24: 12 | J24: 12 | K24: =IFERROR(J24/I24,0) -> 1 | L24: =SUMIF(Total!G:G,'ATD Daily> (2)'!E24,Total!K:K) -> 204 | M24: =SUMIF(Total!G:G,'ATD Daily> (2)'!E24,Total!M:M) -> 17 | N24: =$M$2*$M$3*M24 -> 12240 | O24: =SUMIF(Total!G:G,'ATD Daily> (2)'!E24,Total!N:N) -> 14280 | P24: =IFERROR(O24/N24,0) -> 1.1666667 | Q24: =SUMIF(Total!G:G,'ATD Daily> (2)'!E24,Total!P:P) -> 3804 | S24: =IFERROR(Q24/O24,0) -> 0.26638655 | T24: =I24*M24*$M$1 -> 4284 | U24: =SUMIF(Total!G:G,'ATD Daily> (2)'!E24,Total!P:P) -> 3804 | V24: =IFERROR(U24/T24,0) -> 0.88795518 | W24: =U24*2000 -> 7608000 | X24: =SUMIF(Total!G:G,'ATD Daily> (2)'!E24,Total!T:T) -> 7239072 | Y24: =W24-X24 -> 368928 | Z24: =I24*M24*2000*21 -> 8568000 | AA24: =X24 -> 7239072 | AB24: =IFERROR(AA24/Z24,0) -> 0.84489636
C25: 18 | D25: West 2 | E25: Akure | G25: yes | I25: 12 | J25: 12 | K25: =IFERROR(J25/I25,0) -> 1 | L25: =SUMIF(Total!G:G,'ATD Daily> (2)'!E25,Total!K:K) -> 48 | M25: =SUMIF(Total!G:G,'ATD Daily> (2)'!E25,Total!M:M) -> 4 | N25: =$M$2*$M$3*M25 -> 2880 | O25: =SUMIF(Total!G:G,'ATD Daily> (2)'!E25,Total!N:N) -> 3360 | P25: =IFERROR(O25/N25,0) -> 1.1666667 | Q25: =SUMIF(Total!G:G,'ATD Daily> (2)'!E25,Total!P:P) -> 391 | S25: =IFERROR(Q25/O25,0) -> 0.11636905 | T25: =I25*M25*$M$1 -> 1008 | U25: =SUMIF(Total!G:G,'ATD Daily> (2)'!E25,Total!P:P) -> 391 | V25: =IFERROR(U25/T25,0) -> 0.38789683 | W25: =U25*2000 -> 782000 | X25: =SUMIF(Total!G:G,'ATD Daily> (2)'!E25,Total!T:T) -> 738208 | Y25: =W25-X25 -> 43792 | Z25: =I25*M25*2000*21 -> 2016000 | AA25: =X25 -> 738208 | AB25: =IFERROR(AA25/Z25,0) -> 0.3661746
C26: 19 | D26: West 2 | E26: Ado-Ekiti | F26: Akingbolu Isiaka | G26: Yes | H26: 46245 | I26: 12 | J26: 12 | K26: =IFERROR(J26/I26,0) -> 1 | L26: =SUMIF(Total!G:G,'ATD Daily> (2)'!E26,Total!K:K) -> 144 | M26: =SUMIF(Total!G:G,'ATD Daily> (2)'!E26,Total!M:M) -> 12 | N26: =$M$2*$M$3*M26 -> 8640 | O26: =SUMIF(Total!G:G,'ATD Daily> (2)'!E26,Total!N:N) -> 10080 | P26: =IFERROR(O26/N26,0) -> 1.1666667 | Q26: =SUMIF(Total!G:G,'ATD Daily> (2)'!E26,Total!P:P) -> 1686 | S26: =IFERROR(Q26/O26,0) -> 0.1672619 | T26: =I26*M26*$M$1 -> 3024 | U26: =SUMIF(Total!G:G,'ATD Daily> (2)'!E26,Total!P:P) -> 1686 | V26: =IFERROR(U26/T26,0) -> 0.55753968 | W26: =U26*2000 -> 3372000 | X26: =SUMIF(Total!G:G,'ATD Daily> (2)'!E26,Total!T:T) -> 3220296 | Y26: =W26-X26 -> 151704 | Z26: =I26*M26*2000*21 -> 6048000 | AA26: =X26 -> 3220296 | AB26: =IFERROR(AA26/Z26,0) -> 0.53245635
C27: 20 | D27: West 2 | E27: Warri | I27: 12 | J27: 12 | K27: =IFERROR(J27/I27,0) -> 1 | L27: =SUMIF(Total!G:G,'ATD Daily> (2)'!E27,Total!K:K) -> 156 | M27: =SUMIF(Total!G:G,'ATD Daily> (2)'!E27,Total!M:M) -> 13 | N27: =$M$2*$M$3*M27 -> 9360 | O27: =SUMIF(Total!G:G,'ATD Daily> (2)'!E27,Total!N:N) -> 10920 | P27: =IFERROR(O27/N27,0) -> 1.1666667 | Q27: =SUMIF(Total!G:G,'ATD Daily> (2)'!E27,Total!P:P) -> 2550 | S27: =IFERROR(Q27/O27,0) -> 0.23351648 | T27: =I27*M27*$M$1 -> 3276 | U27: =SUMIF(Total!G:G,'ATD Daily> (2)'!E27,Total!P:P) -> 2550 | V27: =IFERROR(U27/T27,0) -> 0.77838828 | W27: =U27*2000 -> 5100000 | X27: =SUMIF(Total!G:G,'ATD Daily> (2)'!E27,Total!T:T) -> 4852412 | Y27: =W27-X27 -> 247588 | Z27: =I27*M27*2000*21 -> 6552000 | AA27: =X27 -> 4852412 | AB27: =IFERROR(AA27/Z27,0) -> 0.74060012
C28: TOTAL | I28: =SUM(I8:I27) -> 180 | J28: =SUM(J8:J27) -> 180 | K28: =J28/I28 -> 1 | L28: =SUM(L8:L27) -> 1788 | M28: =SUM(M8:M27) -> 149 | N28: =SUM(N8:N27) -> 107280 | O28: =SUM(O8:O27) -> 125160 | P28: =O28/N28 -> 1.1666667 | Q28: =SUM(Q8:Q27) -> 23118 | S28: =Q28/O28 -> 0.18470757 | T28: =SUM(T8:T27) -> 37548 | U28: =SUM(U8:U27) -> 23118 | V28: =U28/T28 -> 0.61569191 | W28: =SUM(W8:W27) -> 46236000 | X28: =SUM(X8:X27) -> 43923814 | Y28: =SUM(Y8:Y27) -> 2312185.7 | Z28: =SUM(Z8:Z27) -> 75096000 | AA28: =SUM(AA8:AA27) -> 43923814 | AB28: =IFERROR(AA28/Z28,0) -> 0.58490218
I35: Promoters Update | W35: Cash Reconciliation | Z35: Sales Performance
G36: Region | I36: Expected No of Promoters | J36: Actual Manning | K36: %Ach. | L36: Man Days | M36: No of Work Days | N36: Reached Target | O36: Reached Achieved | P36: %Ach | Q36: Conversion | S36: Strike Rate | T36: Hollandia Evap Milk 120g | W36: Cash Reconciliation | Z36: PER REGION
T37: Target | U37: Actual | V37: %Ach. | W37: Expected | X37: Paid | Y37: Variance | Z37: TARGET | AA37: ACTUAL | AB37: %ACD
G38: East 1 | I38: =SUMIF($D$8:$D$27,$G38,I$8:I$27) -> 60 | J38: =SUMIF($D$8:$D$27,$G38,J$8:J$27) -> 60 | K38: =IFERROR(J38/I38,"") -> 1 | L38: =SUMIF($D$8:$D$27,$G38,L$8:L$27) -> 504 | M38: =SUMIF($D$8:$D$27,$G38,M$8:M$27) -> 42 | N38: =SUMIF($D$8:$D$27,$G38,N$8:N$27) -> 30240 | O38: =SUMIF($D$8:$D$27,$G38,O$8:O$27) -> 35280 | P38: =SUMIF($D$8:$D$27,$G38,P$8:P$27) -> 4.6666667 | Q38: =SUMIF($D$8:$D$27,$G38,Q$8:Q$27) -> 6000 | S38: =SUMIF($D$8:$D$27,$G38,S$8:S$27) -> 0.59441917 | T38: =SUMIF($D$8:$D$27,$G38,T$8:T$27) -> 10584 | U38: =SUMIF($D$8:$D$27,$G38,U$8:U$27) -> 6000 | V38: =IFERROR(U38/T38,"") -> 0.56689342 | W38: =SUMIF($D$8:$D$27,$G38,W$8:W$27) -> 12000000 | X38: =SUMIF($D$8:$D$27,$G38,X$8:X$27) -> 11387052 | Y38: =X38-W38 -> -612947.72 | Z38: =SUMIF($D$8:$D$27,$G38,Z$8:Z$27) -> 21168000 | AA38: =SUMIF($D$8:$D$27,$G38,AA$8:AA$27) -> 11387052 | AB38: =IFERROR(AA38/Z38,"") -> 0.53793709
G39: East 2 | I39: =SUMIF($D$8:$D$27,$G39,I$8:I$27) -> 60 | J39: =SUMIF($D$8:$D$27,$G39,J$8:J$27) -> 60 | K39: =IFERROR(J39/I39,"") -> 1 | L39: =SUMIF($D$8:$D$27,$G39,L$8:L$27) -> 612 | M39: =SUMIF($D$8:$D$27,$G39,M$8:M$27) -> 51 | N39: =SUMIF($D$8:$D$27,$G39,N$8:N$27) -> 36720 | O39: =SUMIF($D$8:$D$27,$G39,O$8:O$27) -> 42840 | P39: =SUMIF($D$8:$D$27,$G39,P$8:P$27) -> 5.8333333 | Q39: =SUMIF($D$8:$D$27,$G39,Q$8:Q$27) -> 7712 | S39: =SUMIF($D$8:$D$27,$G39,S$8:S$27) -> 0.80935374 | T39: =SUMIF($D$8:$D$27,$G39,T$8:T$27) -> 12852 | U39: =SUMIF($D$8:$D$27,$G39,U$8:U$27) -> 7712 | V39: =IFERROR(U39/T39,"") -> 0.60006225 | W39: =SUMIF($D$8:$D$27,$G39,W$8:W$27) -> 15424000 | X39: =SUMIF($D$8:$D$27,$G39,X$8:X$27) -> 14635063 | Y39: =X39-W39 -> -788937 | Z39: =SUMIF($D$8:$D$27,$G39,Z$8:Z$27) -> 25704000 | AA39: =SUMIF($D$8:$D$27,$G39,AA$8:AA$27) -> 14635063 | AB39: =IFERROR(AA39/Z39,"") -> 0.56936909
G40: West 1 | I40: =SUMIF($D$8:$D$27,$G40,I$8:I$27) -> 0 | J40: =SUMIF($D$8:$D$27,$G40,J$8:J$27) -> 0 | K40: =IFERROR(J40/I40,"") | L40: =SUMIF($D$8:$D$27,$G40,L$8:L$27) -> 0 | M40: =SUMIF($D$8:$D$27,$G40,M$8:M$27) -> 0 | N40: =SUMIF($D$8:$D$27,$G40,N$8:N$27) -> 0 | O40: =SUMIF($D$8:$D$27,$G40,O$8:O$27) -> 0 | P40: =SUMIF($D$8:$D$27,$G40,P$8:P$27) -> 0 | Q40: =SUMIF($D$8:$D$27,$G40,Q$8:Q$27) -> 0 | S40: =SUMIF($D$8:$D$27,$G40,S$8:S$27) -> 0 | T40: =SUMIF($D$8:$D$27,$G40,T$8:T$27) -> 0 | U40: =SUMIF($D$8:$D$27,$G40,U$8:U$27) -> 0 | V40: =IFERROR(U40/T40,"") | W40: =SUMIF($D$8:$D$27,$G40,W$8:W$27) -> 0 | X40: =SUMIF($D$8:$D$27,$G40,X$8:X$27) -> 0 | Y40: =X40-W40 -> 0 | Z40: =SUMIF($D$8:$D$27,$G40,Z$8:Z$27) -> 0 | AA40: =SUMIF($D$8:$D$27,$G40,AA$8:AA$27) -> 0 | AB40: =IFERROR(AA40/Z40,"")
G41: West 2 | I41: =SUMIF($D$8:$D$27,$G41,I$8:I$27) -> 60 | J41: =SUMIF($D$8:$D$27,$G41,J$8:J$27) -> 60 | K41: =IFERROR(J41/I41,"") -> 1 | L41: =SUMIF($D$8:$D$27,$G41,L$8:L$27) -> 672 | M41: =SUMIF($D$8:$D$27,$G41,M$8:M$27) -> 56 | N41: =SUMIF($D$8:$D$27,$G41,N$8:N$27) -> 40320 | O41: =SUMIF($D$8:$D$27,$G41,O$8:O$27) -> 47040 | P41: =SUMIF($D$8:$D$27,$G41,P$8:P$27) -> 5.8333333 | Q41: =SUMIF($D$8:$D$27,$G41,Q$8:Q$27) -> 9406 | S41: =SUMIF($D$8:$D$27,$G41,S$8:S$27) -> 0.89960542 | T41: =SUMIF($D$8:$D$27,$G41,T$8:T$27) -> 14112 | U41: =SUMIF($D$8:$D$27,$G41,U$8:U$27) -> 9406 | V41: =IFERROR(U41/T41,"") -> 0.66652494 | W41: =SUMIF($D$8:$D$27,$G41,W$8:W$27) -> 18812000 | X41: =SUMIF($D$8:$D$27,$G41,X$8:X$27) -> 17901699 | Y41: =X41-W41 -> -910301 | Z41: =SUMIF($D$8:$D$27,$G41,Z$8:Z$27) -> 28224000 | AA41: =SUMIF($D$8:$D$27,$G41,AA$8:AA$27) -> 17901699 | AB41: =IFERROR(AA41/Z41,"") -> 0.63427222
G42: TOTAL | I42: =SUM(I38:I41) -> 180 | J42: =SUM(J38:J41) -> 180 | K42: =IFERROR(J42/I42,"") -> 1 | L42: =SUM(L38:L41) -> 1788 | M42: =SUM(M38:M41) -> 149 | N42: =SUM(N38:N41) -> 107280 | O42: =SUM(O38:O41) -> 125160 | P42: =O42/N42 -> 1.1666667 | Q42: =SUM(Q38:Q41) -> 23118 | S42: =SUM(S38:S41) -> 2.3033783 | T42: =SUM(T38:T41) -> 37548 | U42: =SUM(U38:U41) -> 23118 | V42: =U42/T42 -> 0.61569191 | W42: =SUM(W38:W41) -> 46236000 | X42: =SUM(X38:X41) -> 43923814 | Y42: =SUM(Y38:Y41) -> -2312185.7 | Z42: =SUM(Z38:Z41) -> 75096000 | AA42: =SUM(AA38:AA41) -> 43923814 | AB42: =IFERROR(AA42/Z42,"") -> 0.58490218

Sheet Table
A1: Weeks | B1: Region | C1: Area/Location | D1: Agency Supervisor | E1: Commenced? | F1: Expected No of Promoters | G1: Actual Manning | H1: %Ach. | I1: Man Days | J1: Target Consumer days | K1: Actual Consumer Days | L1: Target Hollandia Evap Milk 120g | M1: Actual Hollandia Evap Milk 120g | N1: Cash Expected | O1: Cash Paid | P1: TARGET PER REGION | Q1: ACTUAL PER REGION | R1: Column1 | S1: Target Volume | T1: Total Volume
B2: ='[1]ATD >'!D5 -> East 1 | C2: Enugu/Abakaliki | D2: MUDIA | E2: ='[1]ATD >'!G5 -> YES | F2: =SUMIF('ATD Daily> (2)'!E:E,Table1[[#This Row],[Area/Location]],'ATD Daily> (2)'!I:I) -> 12 | G2: =SUMIF('ATD Daily> (2)'!E:E,Table1[[#This Row],[Area/Location]],'ATD Daily> (2)'!J:J) -> 12 | H2: =SUMIF('ATD >'!$E:$E,Table1[[#This Row],[Area/Location]],'ATD >'!K:K) -> 0 | I2: =SUMIF('ATD >'!$E:$E,Table1[[#This Row],[Area/Location]],'ATD >'!L:L) -> 0 | J2: =Table1[[#This Row],[Man Days]]*120 -> 0 | K2: =Table1[[#This Row],[Target Consumer days]] -> 0 | L2: =SUMIF('ATD Daily> (2)'!E:E,Table1[[#This Row],[Area/Location]],'ATD Daily> (2)'!T:T) -> 1764 | M2: =SUMIF('ATD Daily> (2)'!E:E,Table1[[#This Row],[Area/Location]],'ATD Daily> (2)'!U:U) -> 450 | N2: =SUMIF('ATD >'!$E:$E,Table1[[#This Row],[Area/Location]],'ATD >'!Q:Q) -> 0 | O2: =SUMIF('ATD >'!$E:$E,Table1[[#This Row],[Area/Location]],'ATD >'!R:R) -> 0 | P2: =SUMIF('ATD Daily> (2)'!E:E,Table1[[#This Row],[Area/Location]],'ATD Daily> (2)'!T:T) -> 1764 | Q2: =SUMIF('ATD Daily> (2)'!E:E,Table1[[#This Row],[Area/Location]],'ATD Daily> (2)'!U:U) -> 450 | S2: =Table1[[#This Row],[Target Hollandia Evap Milk 120g]] -> 1764 | T2: =Table1[[#This Row],[Actual Hollandia Evap Milk 120g]] -> 450
B3: ='[1]ATD >'!D7 -> East 1 | C3: ='[1]ATD >'!E7 -> Onitsha | E3: ='[1]ATD >'!G7 -> YES | F3: =SUMIF('ATD Daily> (2)'!E:E,Table1[[#This Row],[Area/Location]],'ATD Daily> (2)'!I:I) -> 12 | G3: =SUMIF('ATD Daily> (2)'!E:E,Table1[[#This Row],[Area/Location]],'ATD Daily> (2)'!J:J) -> 12 | H3: =SUMIF('ATD >'!$E:$E,Table1[[#This Row],[Area/Location]],'ATD >'!K:K) -> 0 | I3: =SUMIF('ATD >'!$E:$E,Table1[[#This Row],[Area/Location]],'ATD >'!L:L) -> 120 | J3: =Table1[[#This Row],[Man Days]]*120 -> 14400 | K3: =Table1[[#This Row],[Target Consumer days]] -> 14400 | L3: =SUMIF('ATD Daily> (2)'!E:E,Table1[[#This Row],[Area/Location]],'ATD Daily> (2)'!T:T) -> 2520 | M3: =SUMIF('ATD Daily> (2)'!E:E,Table1[[#This Row],[Area/Location]],'ATD Daily> (2)'!U:U) -> 1477 | N3: =SUMIF('ATD >'!$E:$E,Table1[[#This Row],[Area/Location]],'ATD >'!Q:Q) -> 2954000 | O3: =SUMIF('ATD >'!$E:$E,Table1[[#This Row],[Area/Location]],'ATD >'!R:R) -> 2792792 | P3: =SUMIF('ATD Daily> (2)'!E:E,Table1[[#This Row],[Area/Location]],'ATD Daily> (2)'!T:T) -> 2520 | Q3: =SUMIF('ATD Daily> (2)'!E:E,Table1[[#This Row],[Area/Location]],'ATD Daily> (2)'!U:U) -> 1477 | S3: =Table1[[#This Row],[Target Hollandia Evap Milk 120g]] -> 2520 | T3: =Table1[[#This Row],[Actual Hollandia Evap Milk 120g]] -> 1477
B4: ='[1]ATD >'!D8 -> East 1 | C4: Asaba | D4: IFEANYI CHIADIKABIA | E4: ='[1]ATD >'!G8 -> YES | F4: =SUMIF('ATD Daily> (2)'!E:E,Table1[[#This Row],[Area/Location]],'ATD Daily> (2)'!I:I) -> 12 | G4: =SUMIF('ATD Daily> (2)'!E:E,Table1[[#This Row],[Area/Location]],'ATD Daily> (2)'!J:J) -> 12 | H4: =SUMIF('ATD >'!$E:$E,Table1[[#This Row],[Area/Location]],'ATD >'!K:K) -> 0 | I4: =SUMIF('ATD >'!$E:$E,Table1[[#This Row],[Area/Location]],'ATD >'!L:L) -> 108 | J4: =Table1[[#This Row],[Man Days]]*120 -> 12960 | K4: =Table1[[#This Row],[Target Consumer days]] -> 12960 | L4: =SUMIF('ATD Daily> (2)'!E:E,Table1[[#This Row],[Area/Location]],'ATD Daily> (2)'!T:T) -> 2268 | M4: =SUMIF('ATD Daily> (2)'!E:E,Table1[[#This Row],[Area/Location]],'ATD Daily> (2)'!U:U) -> 674 | N4: =SUMIF('ATD >'!$E:$E,Table1[[#This Row],[Area/Location]],'ATD >'!Q:Q) -> 1348000 | O4: =SUMIF('ATD >'!$E:$E,Table1[[#This Row],[Area/Location]],'ATD >'!R:R) -> 1272512 | P4: =SUMIF('ATD Daily> (2)'!E:E,Table1[[#This Row],[Area/Location]],'ATD Daily> (2)'!T:T) -> 2268 | Q4: =SUMIF('ATD Daily> (2)'!E:E,Table1[[#This Row],[Area/Location]],'ATD Daily> (2)'!U:U) -> 674 | S4: =Table1[[#This Row],[Target Hollandia Evap Milk 120g]] -> 2268 | T4: =Table1[[#This Row],[Actual Hollandia Evap Milk 120g]] -> 674
B5: ='[1]ATD >'!D9 -> East 1 | C5: ='[1]ATD >'!E9 -> Owerri | E5: ='[1]ATD >'!G9 -> YES | F5: =SUMIF('ATD Daily> (2)'!E:E,Table1[[#This Row],[Area/Location]],'ATD Daily> (2)'!I:I) -> 12 | G5: =SUMIF('ATD Daily> (2)'!E:E,Table1[[#This Row],[Area/Location]],'ATD Daily> (2)'!J:J) -> 12 | H5: =SUMIF('ATD >'!$E:$E,Table1[[#This Row],[Area/Location]],'ATD >'!K:K) -> 0 | I5: =SUMIF('ATD >'!$E:$E,Table1[[#This Row],[Area/Location]],'ATD >'!L:L) -> 192 | J5: =Table1[[#This Row],[Man Days]]*120 -> 23040 | K5: =Table1[[#This Row],[Target Consumer days]] -> 23040 | L5: =SUMIF('ATD Daily> (2)'!E:E,Table1[[#This Row],[Area/Location]],'ATD Daily> (2)'!T:T) -> 4032 | M5: =SUMIF('ATD Daily> (2)'!E:E,Table1[[#This Row],[Area/Location]],'ATD Daily> (2)'!U:U) -> 3399 | N5: =SUMIF('ATD >'!$E:$E,Table1[[#This Row],[Area/Location]],'ATD >'!Q:Q) -> 6798000 | O5: =SUMIF('ATD >'!$E:$E,Table1[[#This Row],[Area/Location]],'ATD >'!R:R) -> 6476896 | P5: =SUMIF('ATD Daily> (2)'!E:E,Table1[[#This Row],[Area/Location]],'ATD Daily> (2)'!T:T) -> 4032 | Q5: =SUMIF('ATD Daily> (2)'!E:E,Table1[[#This Row],[Area/Location]],'ATD Daily> (2)'!U:U) -> 3399 | S5: =Table1[[#This Row],[Target Hollandia Evap Milk 120g]] -> 4032 | T5: =Table1[[#This Row],[Actual Hollandia Evap Milk 120g]] -> 3399
